Workbook

Sheet Configurator (2)
A1: 1/8” Emitter, 954 cavity foil, standard, PVDF, 3/8” FPT, 1/8” FPT | B1: S003953105 | C1: D09530000VXE0NM | D1: 3340.5
A2: 1/8” Emitter, 953 dome foil, standard, stainless, 3/8” FPT, 1/8” FPT | B2: S00195310X | C2: D09530000VXE0TX | D2: 3215
A3: 1/4” Emitter, 953 dome foil, standard, stainless, 3/4” FPT, 1/4” FPT | B3: S002953X4F | C3: D09530002VXESDF | D3: 3215
A4: 1/4” Emitter, 953 dome foil, escutcheon, stainless, 3/4” FPT, 1/4” FPT | B4: S002953X2E | C4: D09530002VXEEDF | D4: 3215
A5: 1/4” Emitter, 954 cavity foil, standard, PVDF, 3/8” FPT, 1/8” FPT | B5: S003953170 | C5: D09530002VXCVE0 | D5: 3339
A6: 3/8” Emitter, 953 dome foil, escutcheon, stainless, 3/4” FPT, 1/4” FPT | B6: S003953032 | C6: D09530003VXE0DF | D6: 1490.5
A7: 3/8” Emitter, 953 dome foil, standard, stainless, 3/4” FPT, 1/4” FPT | B7: S003953X02 | C7: D09530003VXESFF | D7: 1490.5
A8: 3/8” Emitter, 954 cavity foil, escutcheon, stainless, 3/4” FPT, 1/4” FPT | B8: S003953031 | C8: D09530003VXE0CF | D8: 1490.5
A9: 3/8” Emitter, 954 cavity foil, standard, stainless, 3/4” FPT, 1/4” FPT | B9: S003953001 | C9: D09540003VXE0CF | D9: 1490.5
A10: 1/2” Emitter, 953 dome foil, standard, brass, 3/4” MPT, 1/4” FPT | B10: S006953400 | C10: D09530006VXE0B0 | D10: 1412.5
A11: 1/2” Emitter, 953 dome foil, standard, stainless, 3/4” MPT, 1/4” FPT | B11: S006953X40 | C11: D09530006VXE0XX | D11: 1412.5
A12: 1/2” Emitter, 953 dome foil, standard, PVDF, 3/4” MPT, 1/4” FPT | B12: S006953406 | C12: D09530006VXE0N0 | D12: 2622.5
... A36: 7/16-20 Female JIC x 36” PTFE lined braided stainless hose, 1/4” ID | B36: P360955228 | C36: D09550360VXJICX | D36: 668
A37: 1/8" MNPT x 7/16-20 Male JIC Straight Adapter, stainless | B37: P001950X00 | D37: 37.5
A38: 1/4" MNPT x 7/16-20 Male JIC Straight Adapter, brass | B38: PAY7000C01 | C38: D09550002VXMFBA | D38: 27.5
A39: 1/4" MNPT x 7/16-20 Male JIC Straight Adapter, stainless | B39: P002950X00 | D39: 35.5
A40: 1/4" MNPT x 7/16-20 Male JIC 90 Degree Adapter, stainless | B40: PS35950X00 | D40: 23
A41: 1/8" NPT x 1/4" OD Compression, Straight Adapter, polypropylene | B41: P003953028 | D41: 8
A42: 1/4" NPT x 3/8" OD Compression, Straight Adapter, polypropylene | B42: P000950019 | D42: 32.5
A43: 1” 951 Combination Panel, Dry Contact, Ball Valve | B43: S010951DRY | C43: D09510010VX3DC1 | D43: 51232
A44: 1” 951 Combination Panel, Active Release, Ball Valve | B44: S010951ACT | C44: D09510010VX3ARC | D44: 51450
A45: 1.5” 951 Combination Panel, Dry Contact, Ball Valve | B45: S014951DRY | C45: D09510014VX3DCC | D45: 53923.5
A46: 1.5” 951 Combination Panel, Active Release, Ball Valve | B46: S014951ACT | C46: D09510014VX3ARC | D46: 53930.5
A47: 1” 951 Fluid Panel, Dry Contact | B47: S010951F00 | C47: D09510010VX3DC2 | D47: 36054.5
A48: 1” 951 Fluid Panel, Active Release | B48: S010951FA0 | C48: D09510010VX3ARF | D48: 38650.5
A49: 1.5” 951 Fluid Panel, Dry Contact | B49: S014951F00 | C49: D09510014VX3DCF | D49: 38535
A50: 1.5” 951 Fluid Panel, Active Release | B50: S014951FA0 | C50: D09510014VX3ARF | D50: 39798.5
A51: 1.5” 951 Zone Panel, Dry Contact, Ball Valve | B51: S01495110A | C51: D09510014VX3DCZ | D51: 27103
A52: 2” 951 Zone Panel, Dry Contact, Ball Valve | B52: S02095110A | C52: D09510020VX3DCZ | D52: 31186
A53: Pressure Transducer, Standard, 0-100 psi | B53: P000951140 | C53: D09510000VXST00 | D53: 2181.5
A54: Pressure Transducer Spec. App, Explosion Proof | B54: P000951TRM | C54: D09510000VXTRVP | D54: 5143
... A106: Nozzle Cap, 1/4-1/2”,Standard Style Nozzle, Orange | B106: P002953260 | C106: D09530002VXC0OP | D106: 38.5
A107: Nozzle Cap, 1/8" Nozzle, Black | B107: P0019530B0 | D107: 16.5
A108: Nozzle Cap, 1/4-5/8" Nozzle, Black | B108: P006953522 | C108: D09530002VXE0BP | D108: 38.5
A109: Nozzle Cap, 1" Nozzle, Black | B109: P010953522 | D109: 12
A110: O-ring Kit, primary/ secondary | B110: K000950KIT | C110: K09500000VXPK00 | D110: 219
A111: Discharge Hose, 49L/50L, rt angle, 22.25” OAL | B111: P000955B29 | C111: D09550004VX40DH | D111: 624.5
A112: Discharge Hose, DOT 80L, rt angle, 13.5” OAL | B112: P000955A29 | C112: D09550080VX8DH0 | D112: 573
A113: Discharge Hose Check Valve | B113: S000950BA1 | C113: D09500006VXSICV | D113: 375
A114: 1/4” Pilot Hose, 300 mm, for adjacent cylinders | B114: S000950P32 | C114: D09500002VXSSP0 | D114: 128
A115: 1/4” Pilot Hose, 450 mm, right angle, for primary | B115: S000950B08 | C115: D09500006VXSPH9 | D115: 191
A116: Pilot Line Tee Nipple, 1/4” BSPP | B116: S000950BA2 | C116: D09500002VXSICV | D116: 105
A117: Bleed Valve, 1/4” End of Pilot Line, with Crush Washer | B117: S000950BA4 | C117: D095000002VXSBV | D117: 499
A118: Copper Crush Washer for Bleed Valve | B118: P000950018 | C118: P0950000000CW00 | D118: 24.5
A119: Copper Crush Washer For Vortex Primary/Secondary Gauge | B119: P000950001 | C119: K09500000VXRCCW | D119: 13.5
A120: Primary Solenoid Release Assembly | B120: S000950B22 | C120: D0950000VXPMO0A | D120: 6410.5
A121: Snubber Assembly, with Crush Washer | B121: P000955035 | C121: D09500002VXSWCS | D121: 300
... A153: Plug for Manifold | B153: P006000Z07 | C153: P00000006NPTV00 | D153: 23

Sheet 2.5.2025 Configurator
A1: 1/8” Emitter, 954 cavity foil, standard, PVDF, 3/8” FPT, 1/8” FPT | B1: S003953105 | C1: D09530000VXE0NM | D1: 3340.5
A2: 1/8” Emitter, 953 dome foil, standard, stainless, 3/8” FPT, 1/8” FPT | B2: S00195310X | C2: D09530000VXE0TX | D2: 3215
A3: 1/4” Emitter, 953 dome foil, standard, stainless, 3/4” FPT, 1/4” FPT | B3: S002953X4F | C3: D09530002VXESDF | D3: 3215
A4: 1/4” Emitter, 953 dome foil, escutcheon, stainless, 3/4” FPT, 1/4” FPT | B4: S002953X2E | C4: D09530002VXEEDF | D4: 3215
A5: 1/4” Emitter, 954 cavity foil, standard, PVDF, 3/8” FPT, 1/8” FPT | B5: S003953170 | C5: D09530002VXCVE0 | D5: 3339
A6: 3/8” Emitter, 953 dome foil, escutcheon, stainless, 3/4” FPT, 1/4” FPT | B6: S003953032 | C6: D09530003VXE0DF | D6: 1490.5
A7: 3/8” Emitter, 953 dome foil, standard, stainless, 3/4” FPT, 1/4” FPT | B7: S003953X02 | C7: D09530003VXESFF | D7: 1490.5
A8: 3/8” Emitter, 954 cavity foil, escutcheon, stainless, 3/4” FPT, 1/4” FPT | B8: S003953031 | C8: D09530003VXE0CF | D8: 1490.5
A9: 3/8” Emitter, 954 cavity foil, standard, stainless, 3/4” FPT, 1/4” FPT | B9: S003953001 | C9: D09540003VXE0CF | D9: 1490.5
A10: 1/2” Emitter, 953 dome foil, standard, brass, 3/4” MPT, 1/4” FPT | B10: S006953400 | C10: D09530006VXE0B0 | D10: 1412.5
A11: 1/2” Emitter, 953 dome foil, standard, stainless, 3/4” MPT, 1/4” FPT | B11: S006953X40 | C11: D09530006VXE0XX | D11: 1412.5
A12: 1/2” Emitter, 953 dome foil, standard, PVDF, 3/4” MPT, 1/4” FPT | B12: S006953406 | C12: D09530006VXE0N0 | D12: 2622.5
... A36: 7/16-20 Female JIC x 36” PTFE lined braided stainless hose, 1/4” ID | B36: P360955228 | C36: D09550360VXJICX | D36: 668
A37: 1/8" MNPT x 7/16-20 Male JIC Straight Adapter, stainless | B37: P001950X00 | D37: 37.5
A38: 1/4" MNPT x 7/16-20 Male JIC Straight Adapter, brass | B38: PAY7000C01 | C38: D09550002VXMFBA | D38: 27.5
A39: 1/4" MNPT x 7/16-20 Male JIC Straight Adapter, stainless | B39: P002950X00 | D39: 35.5
A40: 1/4" MNPT x 7/16-20 Male JIC 90 Degree Adapter, stainless | B40: PS35950X00 | D40: 23
A41: 1/8" NPT x 1/4" OD Compression, Straight Adapter, polypropylene | B41: P003953028 | D41: 8
A42: 1/4" NPT x 3/8" OD Compression, Straight Adapter, polypropylene | B42: P000950019 | D42: 32.5
A43: 1” 951 Combination Panel, Dry Contact, Ball Valve | B43: S010951DRY | C43: D09510010VX3DC1 | D43: 51232
A44: 1” 951 Combination Panel, Active Release, Ball Valve | B44: S010951ACT | C44: D09510010VX3ARC | D44: 51450
A45: 1.5” 951 Combination Panel, Dry Contact, Ball Valve | B45: S014951DRY | C45: D09510014VX3DCC | D45: 53923.5
A46: 1.5” 951 Combination Panel, Active Release, Ball Valve | B46: S014951ACT | C46: D09510014VX3ARC | D46: 53930.5
A47: 1” 951 Fluid Panel, Dry Contact | B47: S010951F00 | C47: D09510010VX3DC2 | D47: 36054.5
A48: 1” 951 Fluid Panel, Active Release | B48: S010951FA0 | C48: D09510010VX3ARF | D48: 38650.5
A49: 1.5” 951 Fluid Panel, Dry Contact | B49: S014951F00 | C49: D09510014VX3DCF | D49: 38535
A50: 1.5” 951 Fluid Panel, Active Release | B50: S014951FA0 | C50: D09510014VX3ARF | D50: 39798.5
A51: 1.5” 951 Zone Panel, Dry Contact, Ball Valve | B51: S01495110A | C51: D09510014VX3DCZ | D51: 27103
A52: 2” 951 Zone Panel, Dry Contact, Ball Valve | B52: S02095110A | C52: D09510020VX3DCZ | D52: 31186
A53: Pressure Transducer, Standard, 0-100 psi | B53: P000951140 | C53: D09510000VXST00 | D53: 2181.5
A54: Pressure Transducer Spec. App, Explosion Proof | B54: P000951TRM | C54: D09510000VXTRVP | D54: 5143
... A106: Nozzle Cap, 1/4-1/2”,Standard Style Nozzle, Orange | B106: P002953260 | C106: D09530002VXC0OP | D106: 38.5
A107: Nozzle Cap, 1/8" Nozzle, Black | B107: P0019530B0 | D107: 16.5
A108: Nozzle Cap, 1/4-5/8" Nozzle, Black | B108: P006953522 | C108: D09530002VXE0BP | D108: 38.5
A109: Nozzle Cap, 1" Nozzle, Black | B109: P010953522 | D109: 12
A110: O-ring Kit, primary/ secondary | B110: K000950KIT | C110: K09500000VXPK00 | D110: 219
A111: Discharge Hose, 49L/50L, rt angle, 22.25” OAL | B111: P000955B29 | C111: D09550004VX40DH | D111: 624.5
A112: Discharge Hose, DOT 80L, rt angle, 13.5” OAL | B112: P000955A29 | C112: D09550080VX8DH0 | D112: 573
A113: Discharge Hose Check Valve | B113: S000950BA1 | C113: D09500006VXSICV | D113: 375
A114: 1/4” Pilot Hose, 300 mm, for adjacent cylinders | B114: S000950P32 | C114: D09500002VXSSP0 | D114: 128
A115: 1/4” Pilot Hose, 450 mm, right angle, for primary | B115: S000950B08 | C115: D09500006VXSPH9 | D115: 191
A116: Pilot Line Tee Nipple, 1/4” BSPP | B116: S000950BA2 | C116: D09500002VXSICV | D116: 105
A117: Bleed Valve, 1/4” End of Pilot Line, with Crush Washer | B117: S000950BA4 | C117: D095000002VXSBV | D117: 499
A118: Copper Crush Washer for Bleed Valve | B118: P000950018 | C118: P0950000000CW00 | D118: 24.5
A119: Copper Crush Washer For Vortex Primary/Secondary Gauge | B119: P000950001 | C119: K09500000VXRCCW | D119: 13.5
A120: Primary Solenoid Release Assembly | B120: S000950B22 | C120: D0950000VXPMO0A | D120: 6410.5
A121: Snubber Assembly, with Crush Washer | B121: P000955035 | C121: D09500002VXSWCS | D121: 300
... A153: Plug for Manifold | B153: P006000Z07 | C153: P00000006NPTV00 | D153: 23

Sheet 1.7.2026 Configurator
A1: 1/8” Emitter, 954 cavity foil, standard, PVDF, 3/8” FPT, 1/8” FPT | B1: S003953105 | C1: D09530000VXE0NM | D1: 3340.5 | E1: 1
A2: 1/8” Emitter, 953 dome foil, standard, stainless, 3/8” FPT, 1/8” FPT | B2: S00195310X | C2: D09530000VXE0TX | D2: 3215 | E2: 1
A3: 1/4” Emitter, 953 dome foil, standard, stainless, 3/4” FPT, 1/4” FPT | B3: S002953X4F | C3: D09530002VXESDF | D3: 3215 | E3: 1
A4: 1/4” Emitter, 953 dome foil, escutcheon, stainless, 3/4” FPT, 1/4” FPT | B4: S002953X2E | C4: D09530002VXEEDF | D4: 3215 | E4: 1
A5: 1/4” Emitter, 954 cavity foil, standard, PVDF, 3/8” FPT, 1/8” FPT | B5: S003953170 | C5: D09530002VXCVE0 | D5: 3339 | E5: 1
A6: 3/8” Emitter, 953 dome foil, escutcheon, stainless, 3/4” FPT, 1/4” FPT | B6: S003953032 | C6: D09530003VXE0DF | D6: 1490.5 | E6: 1
A7: 3/8” Emitter, 953 dome foil, standard, stainless, 3/4” FPT, 1/4” FPT | B7: S003953X02 | C7: D09530003VXESFF | D7: 1490.5 | E7: 1
A8: 3/8” Emitter, 954 cavity foil, escutcheon, stainless, 3/4” FPT, 1/4” FPT | B8: S003953031 | C8: D09530003VXE0CF | D8: 1490.5 | E8: 1
A9: 3/8” Emitter, 954 cavity foil, standard, stainless, 3/4” FPT, 1/4” FPT | B9: S003953001 | C9: D09540003VXE0CF | D9: 1490.5 | E9: 1
A10: 1/2” Emitter, 953 dome foil, standard, brass, 3/4” MPT, 1/4” FPT | B10: S006953400 | C10: D09530006VXE0B0 | D10: 1412.5 | E10: 1
A11: 1/2” Emitter, 953 dome foil, standard, stainless, 3/4” MPT, 1/4” FPT | B11: S006953X40 | C11: D09530006VXE0XX | D11: 1412.5 | E11: 1
A12: 1/2” Emitter, 953 dome foil, standard, PVDF, 3/4” MPT, 1/4” FPT | B12: S006953406 | C12: D09530006VXE0N0 | D12: 2622.5 | E12: 1
... A36: 7/16-20 Female JIC x 36” PTFE lined braided stainless hose, 1/4” ID | B36: P360955228 | C36: D09550360VXJICX | D36: 668 | E36: 1
A37: 1/8" MNPT x 7/16-20 Male JIC Straight Adapter, stainless | B37: P001950X00 | D37: 37.5 | E37: 1
A38: 1/4" MNPT x 7/16-20 Male JIC Straight Adapter, brass | B38: PAY7000C01 | C38: D09550002VXMFBA | D38: 27.5 | E38: 1
A39: 1/4" MNPT x 7/16-20 Male JIC Straight Adapter, stainless | B39: P002950X00 | D39: 35.5 | E39: 1
A40: 1/4" MNPT x 7/16-20 Male JIC 90 Degree Adapter, stainless | B40: PS35950X00 | D40: 23 | E40: 1
A41: 1/8" NPT x 1/4" OD Compression, Straight Adapter, polypropylene | B41: P003953028 | D41: 8 | E41: 1
A42: 1/4" NPT x 3/8" OD Compression, Straight Adapter, polypropylene | B42: P000950019 | D42: 32.5 | E42: 1
A43: 1” 951 Combination Panel, Dry Contact, Ball Valve | B43: S010951DRY | C43: D09510010VX3DC1 | D43: 51232 | E43: 1
A44: 1” 951 Combination Panel, Active Release, Ball Valve | B44: S010951ACT | C44: D09510010VX3ARC | D44: 51450 | E44: 1
A45: 1.5” 951 Combination Panel, Dry Contact, Ball Valve | B45: S014951DRY | C45: D09510014VX3DCC | D45: 53923.5 | E45: 1
A46: 1.5” 951 Combination Panel, Active Release, Ball Valve | B46: S014951ACT | C46: D09510014VX3ARC | D46: 53930.5 | E46: 1
A47: 1” 951 Fluid Panel, Dry Contact | B47: S010951F00 | C47: D09510010VX3DC2 | D47: 36054.5 | E47: 1
A48: 1” 951 Fluid Panel, Active Release | B48: S010951FA0 | C48: D09510010VX3ARF | D48: 38650.5 | E48: 1
A49: 1.5” 951 Fluid Panel, Dry Contact | B49: S014951F00 | C49: D09510014VX3DCF | D49: 38535 | E49: 1
A50: 1.5” 951 Fluid Panel, Active Release | B50: S014951FA0 | C50: D09510014VX3ARF | D50: 39798.5 | E50: 1
A51: 1.5” 951 Zone Panel, Dry Contact, Ball Valve | B51: S01495110A | C51: D09510014VX3DCZ | D51: 27103 | E51: 1
A52: 2” 951 Zone Panel, Dry Contact, Ball Valve | B52: S02095110A | C52: D09510020VX3DCZ | D52: 31186 | E52: 1
A53: Pressure Transducer, Standard, 0-100 psi | B53: P000951140 | C53: D09510000VXST00 | D53: 2181.5 | E53: 1
A54: Pressure Transducer Spec. App, Explosion Proof | B54: P000951TRM | C54: D09510000VXTRVP | D54: 5143 | E54: 1
... A96: 1/2 MNPT x 36” Stainless Steel Hose for Water Tank Regulator | B96: P004950010 | C96: P09500004ZZ0WTR | D96: 1032 | E96: 1
A97: D/950 WATER TANK ASY UPDATED DESIGN 100L SS316L CE | B97: D09500000VXWTXA | C97: D09500000VXWTX1 | D97: 33244.5
A98: D/950 WATER TANK ASY 150L SS316L CE | B98: D09500000VXWTXA | C98: D09500000VXWTXS | D98: 39076
A99: D/950 WATER TANK ASY 300L SS316L CE | B99: D09500000VXWTXA | C99: D09500000VXWTX3 | D99: 48170
A100: D/950 WATER TANK ASY 500L SS316L CE | B100: S000950X50 | C100: D09500000VXWTX5 | D100: 39381.5
A101: D/950 WATER TANK ASY 750L SS316L CE | B101: D09500000VXWTXA | C101: D09500000VXWTX7 | D101: 57134
A102: D/950 WATER TANK ASY 1000L SS316L CE | B102: D09500000VXWTXA | C102: D09500000VXWTXA | D102: 62405
A103: Nozzle Cap, 1/4-1/2”,Standard Style Nozzle, Orange | B103: P002953260 | C103: D09530002VXC0OP | D103: 38.5 | E103: 1
A104: Nozzle Cap, 1/8" Nozzle, Black | B104: P0019530B0 | D104: 16.5 | E104: 1
A105: Nozzle Cap, 1/4-5/8" Nozzle, Black | B105: P006953522 | C105: D09530002VXE0BP | D105: 38.5 | E105: 1
A106: Nozzle Cap, 1" Nozzle, Black | B106: P010953522 | D106: 12 | E106: 1
A107: O-ring Kit, primary/ secondary | B107: K000950KIT | C107: K09500000VXPK00 | D107: 219 | E107: 1
A108: Discharge Hose, 49L/50L, rt angle, 22.25” OAL | B108: P000955B29 | C108: D09550004VX40DH | D108: 624.5 | E108: 1
A109: Discharge Hose, DOT 80L, rt angle, 13.5” OAL | B109: P000955A29 | C109: D09550080VX8DH0 | D109: 573 | E109: 1
A110: Discharge Hose Check Valve | B110: S000950BA1 | C110: D09500006VXSICV | D110: 375 | E110: 1
A111: 1/4” Pilot Hose, 300 mm, for adjacent cylinders | B111: S000950P32 | C111: D09500002VXSSP0 | D111: 128 | E111: 1
A112: 1/4” Pilot Hose, 450 mm, right angle, for primary | B112: S000950B08 | C112: D09500006VXSPH9 | D112: 191 | E112: 1
A113: Pilot Line Tee Nipple, 1/4” BSPP | B113: S000950BA2 | C113: D09500002VXSICV | D113: 105 | E113: 1
A114: Bleed Valve, 1/4” End of Pilot Line, with Crush Washer | B114: S000950BA4 | C114: D095000002VXSBV | D114: 499 | E114: 1
A115: Copper Crush Washer for Bleed Valve | B115: P000950018 | C115: P0950000000CW00 | D115: 24.5 | E115: 1
A116: Copper Crush Washer For Vortex Primary/Secondary Gauge | B116: P000950001 | C116: K09500000VXRCCW | D116: 13.5 | E116: 1
A117: Primary Solenoid Release Assembly | B117: S000950B22 | C117: D0950000VXPMO0A | D117: 6410.5 | E117: 1
A118: Snubber Assembly, with Crush Washer | B118: P000955035 | C118: D09500002VXSWCS | D118: 300 | E118: 1
... A137: 220VAC Battery Backup Power Supply w/ (2) 12 Ah batteries | B137: S000950220 | C137: D09500220VX0BDC | D137: 6439.5 | E137: 1
A138: FM Approved for Data Processing Rooms (Pre-Engineered) | B138: Z521073LBL | C138: ZL2107300000000 | D138: 66
A139: VORTEX PRE ENGINEERED ONE CYLINDER | B139: S800950001 | C139: D09500020VXCY00 | D139: 32248
A140: VORTEX PRE ENGINEERED TWO CYLINDER | B140: S800950002 | C140: D09500020VXCY00 | D140: 32238
A141: VORTEX PRE ENGINEERED THREE CYLINDER | B141: S800950003 | C141: D09500030VXCY00 | D141: 32278.5
A142: VORTEX PRE ENGINEERED FOUR CYLINDER | B142: S800950004 | C142: D09500040VXCY00 | D142: 32268.5
A143: VORTEX PRE ENGINEERED FIVE CYLINDER | B143: S800950005 | C143: D09500050VXCY00 | D143: 33598.5
A144: VORTEX PRE ENGINEERED SIX CYLINDER | B144: S800950006 | C144: D09500060VXCY00 | D144: 33588.5
A145: VORTEX PRE ENGINEERED SEVEN CYLINDER | B145: S800950007 | C145: D09500070VXCY00 | D145: 33578
A146: VORTEX PRE ENGINEERED EIGHT CYLINDER | B146: S800950008 | C146: D09500080VXCY00 | D146: 33568
A147: VICTAULIC VORTEX NITROGEN CYL - 80L W/VALVE UNPRESSURIZED | B147: S000950E01 | C147: D09500000VX8CE0 | D147: 5873
A148: I-VORTEX/PE.DIOM | B148: Z000VTXPES | C148: ZM2036200000000 | D148: 2
A149: I-VORTEX.IOM | B149: Z000VTX00M | C149: ZM2014700000000 | D149: 2
... A151: Plug for Manifold | B151: P006000Z07 | C151: P00000006NPTV00 | D151: 23

Sheet 10.28.2025 Configurator
A1: 1/8” Emitter, 954 cavity foil, standard, PVDF, 3/8” FPT, 1/8” FPT | B1: S003953105 | C1: D09530000VXE0NM | D1: 3181
A2: 1/8” Emitter, 953 dome foil, standard, stainless, 3/8” FPT, 1/8” FPT | B2: S00195310X | C2: D09530000VXE0TX | D2: 3061.5
A3: 1/4” Emitter, 953 dome foil, standard, stainless, 3/4” FPT, 1/4” FPT | B3: S002953X4F | C3: D09530002VXESDF | D3: 3061.5
A4: 1/4” Emitter, 954 cavity foil, standard, PVDF, 3/8” FPT, 1/8” FPT | B4: S003953170 | C4: D09530002VXCVE0 | D4: 3180
A5: 1/4” Emitter, 953 dome foil, escutcheon, stainless, 3/4” FPT, 1/4” FPT | B5: S002953X2E | C5: D09530002VXEEDF | D5: 3061.5
A6: 3/8” Emitter, 953 dome foil, escutcheon, stainless, 3/4” FPT, 1/4” FPT | B6: S003953032 | C6: D09530003VXE0DF | D6: 1419.5
A7: 3/8” Emitter, 953 dome foil, standard, stainless, 3/4” FPT, 1/4” FPT | B7: S003953X02 | C7: D09530003VXESFF | D7: 1419.5
A8: 3/8” Emitter, 954 cavity foil, escutcheon, stainless, 3/4” FPT, 1/4” FPT | B8: S003953031 | C8: D09530003VXE0CF | D8: 1419.5
A9: 3/8” Emitter, 954 cavity foil, standard, stainless, 3/4” FPT, 1/4” FPT | B9: S003953001 | C9: D09540003VXE0CF | D9: 1419.5
A10: 1/2” Emitter, 953 dome foil, standard, brass, 3/4” MPT, 1/4” FPT | B10: S006953400 | C10: D09530006VXE0B0 | D10: 1345
A11: 1/2” Emitter, 953 dome foil, standard, PVDF, 3/4” MPT, 1/4” FPT | B11: S006953406 | C11: D09530006VXE0N0 | D11: 2497.5
A12: 1/2” Emitter, 953 dome foil, escutcheon, stainless, 3/4” FPT, 1/4” FPT | B12: S004953511 | C12: D09530004VXE0D4 | D12: 1419.5
... A150: Plug for Manifold | B150: P006000Z07 | C150: P00000006NPTV00 | D150: 21.5

Sheet 9.9.2025 Configurator
A1: 1/8” Emitter, 954 cavity foil, standard, PVDF, 3/8” FPT, 1/8” FPT | B1: S003953105 | C1: D09530000VXE0NM | D1: 3181
A2: 1/8” Emitter, 953 dome foil, standard, stainless, 3/8” FPT, 1/8” FPT | B2: S00195310X | C2: D09530000VXE0TX | D2: 3061.5
A3: 1/4” Emitter, 953 dome foil, standard, stainless, 3/4” MPT, 1/4” FPT | B3: S002953X02 | C3: D09530002VXEXDF | D3: 3550
A4: 1/4” Emitter, 954 cavity foil, standard, PVDF, 3/8” FPT, 1/8” FPT | B4: S003953170 | C4: D09530002VXCVE0 | D4: 3180
A5: 3/8” Emitter, 953 dome foil, escutcheon, stainless, 3/4” FPT, 1/4” FPT | B5: S003953032 | C5: D09530003VXE0DF | D5: 1419.5
A6: 3/8” Emitter, 953 dome foil, standard, stainless, 3/4” FPT, 1/4” FPT | B6: S003953034 | C6: D09530003VXESDF | D6: 1345
A7: 3/8” Emitter, 954 cavity foil, escutcheon, stainless, 3/4” FPT, 1/4” FPT | B7: S003953031 | C7: D09530003VXE0CF | D7: 1419.5
A8: 3/8” Emitter, 954 cavity foil, standard, stainless, 3/4” FPT, 1/4” FPT | B8: S003953033 | C8: D09530003VXESCF | D8: 1345
A9: 1/2” Emitter, 953 dome foil, standard, brass, 3/4” MPT, 1/4” FPT | B9: S006953400 | C9: D09530006VXE0B0 | D9: 1345
A10: 1/2” Emitter, 953 dome foil, standard, PVDF, 3/4” MPT, 1/4” FPT | B10: S006953406 | C10: D09530006VXE0N0 | D10: 2497.5
A11: 1/2” Emitter, 953 dome foil, escutcheon, stainless, 3/4” FPT, 1/4” FPT | B11: S004953511 | C11: D09530004VXE0D4 | D11: 1419.5
A12: 1/2” Emitter, 953 dome foil, standard, stainless, 3/4” FPT, 1/4” FPT | B12: S004953513 | C12: D09530004VXESDF | D12: 1873.5
... A146: 10 Gallon Water Tank, Red, w/ Trim, ASME, FM and CE approved | B146: S10095014C | C146: D09500010VXWTRC | D146: 19369

Sheet 8.19.2025 Configurator
A1: 1/8” Emitter, 954 cavity foil, standard, PVDF, 3/8” FPT, 1/8” FPT | B1: S003953105 | C1: D09530000VXE0NM | D1: 3181
A2: 1/8” Emitter, 953 dome foil, standard, stainless, 3/8” FPT, 1/8” FPT | B2: S00195310X | C2: D09530000VXE0TX | D2: 3061.5
A3: 1/4” Emitter, 953 dome foil, standard, stainless, 3/4” MPT, 1/4” FPT | B3: S002953X02 | C3: D09530002VXEXDF | D3: 3550
A4: 1/4” Emitter, 954 cavity foil, standard, PVDF, 3/8” FPT, 1/8” FPT | B4: S003953170 | C4: D09530002VXCVE0 | D4: 3180
A5: 3/8” Emitter, 953 dome foil, escutcheon, stainless, 3/4” FPT, 1/4” FPT | B5: S003953032 | C5: D09530003VXE0DF | D5: 1419.5
A6: 3/8” Emitter, 953 dome foil, standard, stainless, 3/4” FPT, 1/4” FPT | B6: S003953034 | C6: D09530003VXESDF | D6: 1345
A7: 3/8” Emitter, 954 cavity foil, escutcheon, stainless, 3/4” FPT, 1/4” FPT | B7: S003953031 | C7: D09530003VXE0CF | D7: 1419.5
A8: 3/8” Emitter, 954 cavity foil, standard, stainless, 3/4” FPT, 1/4” FPT | B8: S003953033 | C8: D09530003VXESCF | D8: 1345
A9: 1/2” Emitter, 953 dome foil, standard, brass, 3/4” MPT, 1/4” FPT | B9: S006953400 | C9: D09530006VXE0B0 | D9: 1345
A10: 1/2” Emitter, 953 dome foil, standard, PVDF, 3/4” MPT, 1/4” FPT | B10: S006953406 | C10: D09530006VXE0N0 | D10: 2497.5
A11: 1/2” Emitter, 953 dome foil, escutcheon, stainless, 3/4” FPT, 1/4” FPT | B11: S004953511 | C11: D09530004VXE0D4 | D11: 1419.5
A12: 1/2” Emitter, 953 dome foil, standard, stainless, 3/4” FPT, 1/4” FPT | B12: S004953513 | C12: D09530004VXESDF | D12: 1873.5
... A145: D/950 WATER TANK ASY 1000L SS316L CE | B145: D09500000VXWTXA | C145: D09500000VXWTXA | D145: 59433

Sheet 6.23.2025 Configurator
A1: 1/8” Emitter, 954 cavity foil, standard, PVDF, 3/8” FPT, 1/8” FPT | B1: S003953105 | C1: D09530000VXE0NM | D1: 3181
A2: 1/8” Emitter, 953 dome foil, standard, stainless, 3/8” FPT, 1/8” FPT | B2: S00195310X | C2: D09530000VXE0TX | D2: 3061.5
A3: 1/4” Emitter, 953 dome foil, standard, stainless, 3/4” MPT, 1/4” FPT | B3: S002953X02 | C3: D09530002VXEXDF | D3: 3550
A4: 1/4” Emitter, 954 cavity foil, standard, PVDF, 3/8” FPT, 1/8” FPT | B4: S003953170 | C4: D09530002VXCVE0 | D4: 3180
A5: 3/8” Emitter, 953 dome foil, escutcheon, stainless, 3/4” FPT, 1/4” FPT | B5: S003953032 | C5: D09530003VXE0DF | D5: 1419.5
A6: 3/8” Emitter, 953 dome foil, standard, stainless, 3/4” FPT, 1/4” FPT | B6: S003953034 | C6: D09530003VXESDF | D6: 1345
A7: 3/8” Emitter, 954 cavity foil, escutcheon, stainless, 3/4” FPT, 1/4” FPT | B7: S003953031 | C7: D09530003VXE0CF | D7: 1419.5
A8: 3/8” Emitter, 954 cavity foil, standard, stainless, 3/4” FPT, 1/4” FPT | B8: S003953033 | C8: D09530003VXESCF | D8: 1345
A9: 1/2” Emitter, 953 dome foil, standard, brass, 3/4” MPT, 1/4” FPT | B9: S006953400 | C9: D09530006VXE0B0 | D9: 1345
A10: 1/2” Emitter, 953 dome foil, standard, PVDF, 3/4” MPT, 1/4” FPT | B10: S006953406 | C10: D09530006VXE0N0 | D10: 2497.5
A11: 1/2” Emitter, 953 dome foil, escutcheon, stainless, 3/4” FPT, 1/4” FPT | B11: S004953511 | C11: D09530004VXE0D4 | D11: 1419.5
A12: 1/2” Emitter, 953 dome foil, standard, stainless, 3/4” FPT, 1/4” FPT | B12: S004953513 | C12: D09530004VXESDF | D12: 1873.5
... A149: VICTAULIC VORTEX NITROGEN CYL - 80L W/VALVE UNPRESSURIZED | B149: S000950E01 | C149: D09500000VX8CE0 | D149: 5593

Sheet 4.28.2025 Configurator
A1: 1/8” Emitter, 954 cavity foil, standard, PVDF, 3/8” FPT, 1/8” FPT | B1: S003953105 | C1: D09530000VXE0NM | D1: 2986.5
A2: 1/8” Emitter, 953 dome foil, standard, stainless, 3/8” FPT, 1/8” FPT | B2: S00195310X | C2: D09530000VXE0TX | D2: 2874.5
A3: 1/4” Emitter, 953 dome foil, standard, stainless, 3/4” MPT, 1/4” FPT | B3: S002953X02 | C3: D09530002VXEXDF | D3: 3333
A4: 1/4” Emitter, 954 cavity foil, standard, PVDF, 3/8” FPT, 1/8” FPT | B4: S003953170 | C4: D09530002VXCVE0 | D4: 2985.5
A5: 3/8” Emitter, 953 dome foil, escutcheon, stainless, 3/4” FPT, 1/4” FPT | B5: S003953032 | C5: D09530003VXE0DF | D5: 1332.5
A6: 3/8” Emitter, 953 dome foil, standard, stainless, 3/4” FPT, 1/4” FPT | B6: S003953034 | C6: D09530003VXESDF | D6: 1262.5
A7: 3/8” Emitter, 954 cavity foil, escutcheon, stainless, 3/4” FPT, 1/4” FPT | B7: S003953031 | C7: D09530003VXE0CF | D7: 1332.5
A8: 3/8” Emitter, 954 cavity foil, standard, stainless, 3/4” FPT, 1/4” FPT | B8: S003953033 | C8: D09530003VXESCF | D8: 1262.5
A9: 1/2” Emitter, 953 dome foil, standard, brass, 3/4” MPT, 1/4” FPT | B9: S006953400 | C9: D09530006VXE0B0 | D9: 1262.5
A10: 1/2” Emitter, 953 dome foil, standard, PVDF, 3/4” MPT, 1/4” FPT | B10: S006953406 | C10: D09530006VXE0N0 | D10: 2345
A11: 1/2” Emitter, 953 dome foil, escutcheon, stainless, 3/4” FPT, 1/4” FPT | B11: S004953511 | C11: D09530004VXE0D4 | D11: 1332.5
A12: 1/2” Emitter, 953 dome foil, standard, stainless, 3/4” FPT, 1/4” FPT | B12: S004953513 | C12: D09530004VXESDF | D12: 1759
... A149: VICTAULIC VORTEX NITROGEN CYL - 80L W/VALVE UNPRESSURIZED | B149: S000950E01 | C149: D09500000VX8CE0 | D149: 5251.5

Sheet EMEA Updated 2025
B1: Victaulic Vortex® System Product List Price Effective March 1st, 2025
B2: United States
H4: Multiplier:
B5: NOTE: Please add information to the cells shaded in | C5: GREEN. | H5: 0.37
B7: Option Style | C7: Shipping Weight | D7: Item BPCS Number | E7: M3 Item Number | F7: Cost (USD) | G7: List Price (USD) | H7: Extended Price | I7: GM % | J7: 60% Margin Sell | K7: 67.5% Margin Sell | L7: 75% Margin Sell
B9: Emitters | J9: 0.6 | K9: 0.675 | L9: 0.75
B10: 1/8" Emitters
B11: 1/8” Emitter, 954 cavity foil, standard, PVDF, 3/8” FPT, 1/8” FPT | C11: 1 | D11: S003953105 | E11: =VLOOKUP(D11,Sheet1!B:C, 2, FALSE) -> D09530000VXE0NM | F11: 195.71 | G11: ='March 2025'!F11 -> 2986.5 | H11: =G11*$H$5 -> 1105.005 | I11: =((H11-F11)/H11) -> 0.82288768 | J11: =(($F11/(1-$J9))) -> 489.275 | K11: =(($F11/(1-$K$9))) -> 602.18462 | L11: =(($F11/(1-$L9))) -> 782.84
B12: 1/8” Emitter, 953 dome foil, standard, stainless, 3/8” FPT, 1/8” FPT | C12: 1 | D12: S00195310X | E12: =VLOOKUP(D12,Sheet1!B:C, 2, FALSE) -> D09530000VXE0TX | F12: 171.534 | G12: ='March 2025'!F12 -> 2874.5 | H12: =G12*$H$5 -> 1063.565 | I12: =((H12-F12)/H12) -> 0.8387179 | J12: =(($F12/(1-$J$9))) -> 428.835 | K12: =(($F12/(1-$K$9))) -> 527.79692 | L12: =(($F12/(1-$L$9))) -> 686.136
B13: 1/4" Emitters
B14: 1/4” Emitter, 953 dome foil, standard, stainless, 3/4” MPT, 1/4” FPT | C14: 1 | D14: S002953X02 | E14: =VLOOKUP(D14,Sheet1!B:C, 2, FALSE) -> D09530002VXEXDF | F14: 160.1174 | G14: ='March 2025'!F14 -> 3333 | H14: =G14*$H$5 -> 1233.21 | I14: =((H14-F14)/H14) -> 0.8701621 | J14: =(($F14/(1-J$9))) -> 400.2935 | K14: =(($F14/(1-$K$9))) -> 492.66892 | L14: =(($F14/(1-L$9))) -> 640.4696
B15: 1/4” Emitter, 954 cavity foil, standard, PVDF, 3/8” FPT, 1/8” FPT | C15: 1 | D15: S003953170 | E15: =VLOOKUP(D15,Sheet1!B:C, 2, FALSE) -> D09530002VXCVE0 | F15: 241.4136 | G15: ='March 2025'!F15 -> 2985.5 | H15: =G15*$H$5 -> 1104.635 | I15: =((H15-F15)/H15) -> 0.78145396 | J15: =(($F15/(1-$J$9))) -> 603.534 | K15: =(($F15/(1-$K$9))) -> 742.81108 | L15: =(($F15/(1-$L$9))) -> 965.6544
B16: 3/8" Emitters
A17: NEW | B17: 3/8” Emitter, 953 dome foil, escutcheon, stainless, 3/4” FPT, 1/4” FPT | C17: 1 | D17: S003953032 | E17: =VLOOKUP(D17,Sheet1!B:C, 2, FALSE) -> D09530003VXE0DF | F17: 52.3201 | G17: ='March 2025'!F17 -> 1332.5 | H17: =G17*$H$5 -> 493.025 | I17: =((H17-F17)/H17) -> 0.89387942 | J17: =(($F17/(1-J$9))) -> 130.80025 | K17: =(($F17/(1-$K$9))) -> 160.98492 | L17: =(($F17/(1-L$9))) -> 209.2804
A18: NEW | B18: 3/8” Emitter, 953 dome foil, standard, stainless, 3/4” FPT, 1/4” FPT | C18: 1 | D18: S003953034 | E18: =VLOOKUP(D18,Sheet1!B:C, 2, FALSE) -> D09530003VXESDF | F18: 34.5438 | G18: ='March 2025'!F18 -> 1262.5 | H18: =G18*$H$5 -> 467.125 | I18: =((H18-F18)/H18) -> 0.9260502 | J18: =(($F18/(1-J$9))) -> 86.3595 | K18: =(($F18/(1-$K$9))) -> 106.28862 | L18: =(($F18/(1-L$9))) -> 138.1752
A19: NEW | B19: 3/8” Emitter, 954 cavity foil, escutcheon, stainless, 3/4” FPT, 1/4” FPT | C19: 1 | D19: S003953031 | E19: =VLOOKUP(D19,Sheet1!B:C, 2, FALSE) -> D09530003VXE0CF | F19: 51.85424 | G19: ='March 2025'!F19 -> 1332.5 | H19: =G19*$H$5 -> 493.025 | I19: =((H19-F19)/H19) -> 0.89482432 | J19: =(($F19/(1-J$9))) -> 129.6356 | K19: =(($F19/(1-$K$9))) -> 159.55151 | L19: =(($F19/(1-L$9))) -> 207.41696
A20: NEW | B20: 3/8” Emitter, 954 cavity foil, standard, stainless, 3/4” FPT, 1/4” FPT | C20: 1 | D20: S003953033 | E20: =VLOOKUP(D20,Sheet1!B:C, 2, FALSE) -> D09530003VXESCF | F20: 34.07794 | G20: ='March 2025'!F20 -> 1262.5 | H20: =G20*$H$5 -> 467.125 | I20: =((H20-F20)/H20) -> 0.92704749 | J20: =(($F20/(1-J$9))) -> 85.19485 | K20: =(($F20/(1-$K$9))) -> 104.8552 | L20: =(($F20/(1-L$9))) -> 136.31176
B21: 1/2" Emitters
B22: 1/2” Emitter, 953 dome foil, standard, brass, 3/4” MPT, 1/4” FPT | C22: 1 | D22: S006953400 | E22: =VLOOKUP(D22,Sheet1!B:C, 2, FALSE) -> D09530006VXE0B0 | F22: 102.34866 | G22: ='March 2025'!F22 -> 1262.5 | H22: =G22*$H$5 -> 467.125 | I22: =((H22-F22)/H22) -> 0.78089663 | J22: =(($F22/(1-J$9))) -> 255.87165 | K22: =(($F22/(1-$K$9))) -> 314.91895 | L22: =(($F22/(1-L$9))) -> 409.39464
B23: 1/2” Emitter, 953 dome foil, standard, PVDF, 3/4” MPT, 1/4” FPT | C23: 1 | D23: S006953406 | E23: =VLOOKUP(D23,Sheet1!B:C, 2, FALSE) -> D09530006VXE0N0 | F23: 230.5925 | G23: ='March 2025'!F23 -> 2345 | H23: =G23*$H$5 -> 867.65 | I23: =((H23-F23)/H23) -> 0.73423327 | J23: =(($F23/(1-J$9))) -> 576.48125 | K23: =(($F23/(1-$K$9))) -> 709.51538 | L23: =(($F23/(1-L$9))) -> 922.37
A24: NEW | B24: 1/2” Emitter, 953 dome foil, escutcheon, stainless, 3/4” FPT, 1/4” FPT | C24: 1 | D24: S004953511 | E24: =VLOOKUP(D24,Sheet1!B:C, 2, FALSE) -> D09530004VXE0D4 | F24: 60.22 | G24: ='March 2025'!F24 -> 1332.5 | H24: =G24*$H$5 -> 493.025 | I24: =((H24-F24)/H24) -> 0.87785609 | J24: =(($F24/(1-J$9))) -> 150.55 | K24: =(($F24/(1-$K$9))) -> 185.29231 | L24: =(($F24/(1-L$9))) -> 240.88
A25: NEW | B25: 1/2” Emitter, 953 dome foil, standard, stainless, 3/4” FPT, 1/4” FPT | C25: 1 | D25: S004953513 | E25: =VLOOKUP(D25,Sheet1!B:C, 2, FALSE) -> D09530004VXESDF | F25: 35.2038 | G25: ='March 2025'!F25 -> 1759 | H25: =G25*$H$5 -> 650.83 | I25: =((H25-F25)/H25) -> 0.94590938 | J25: =(($F25/(1-J$9))) -> 88.0095 | K25: =(($F25/(1-$K$9))) -> 108.31938 | L25: =(($F25/(1-L$9))) -> 140.8152
B26: 5/8" Emitters
B27: 5/8” Emitter, 954 cavity foil, standard, PVDF, 3/4” FPT, 1/4" FPT | C27: 1 | D27: S006953503 | E27: =VLOOKUP(D27,Sheet1!B:C, 2, FALSE) -> D09530005VXCVE0 | F27: 193.3368 | G27: ='March 2025'!F27 -> 2986.5 | H27: =G27*$H$5 -> 1105.005 | I27: =((H27-F27)/H27) -> 0.82503536 | J27: =(($F27/(1-J$9))) -> 483.342 | K27: =(($F27/(1-$K$9))) -> 594.88246 | L27: =(($F27/(1-L$9))) -> 773.3472
A28: NEW | B28: 5/8” Emitter, 954 cavity foil, escutcheon, stainless, 3/4” FPT, 1/4” FPT | C28: 1 | D28: S006953512 | E28: =VLOOKUP(D28,Sheet1!B:C, 2, FALSE) -> D09530005VXE0CF | F28: 50.4801 | G28: ='March 2025'!F28 -> 1332.5 | H28: =G28*$H$5 -> 493.025 | I28: =((H28-F28)/H28) -> 0.89761148 | J28: =(($F28/(1-J$9))) -> 126.20025 | K28: =(($F28/(1-$K$9))) -> 155.32338 | L28: =(($F28/(1-L$9))) -> 201.9204
A29: NEW | B29: 5/8” Emitter, 954 cavity foil, standard, stainless, 3/4” FPT, 1/4” FPT | C29: 1 | D29: S006953514 | E29: =VLOOKUP(D29,Sheet1!B:C, 2, FALSE) -> D09530005VXESCF | F29: 32.7038 | G29: ='March 2025'!F29 -> 1262.5 | H29: =G29*$H$5 -> 467.125 | I29: =((H29-F29)/H29) -> 0.92998919 | J29: =(($F29/(1-J$9))) -> 81.7595 | K29: =(($F29/(1-$K$9))) -> 100.62708 | L29: =(($F29/(1-L$9))) -> 130.8152
B30: 1" Emitters
A31: NEW | B31: 1” Emitter, 953/954 dome foil, escutcheon, stainless, 1” FPT, 1/8” FPT | C31: 1 | D31: S010953511 | E31: =VLOOKUP(D31,Sheet1!B:C, 2, FALSE) -> D09530010VXE0DF | F31: 68.4904 | G31: ='March 2025'!F31 -> 2316.5 | H31: =G31*$H$5 -> 857.105 | I31: =((H31-F31)/H31) -> 0.920091 | J31: =(($F31/(1-J$9))) -> 171.226 | K31: =(($F31/(1-$K$9))) -> 210.73969 | L31: =(($F31/(1-L$9))) -> 273.9616
B33: Water Flow Kits (Strainer, Flow Cartridge, Emitter Trim Kit)
B34: Water Flow Cartridge Kit, .13 GPM, Brass, 3/4” NPT | C34: 1 | D34: K000953013 | E34: =VLOOKUP(D34,Sheet1!B:C, 2, FALSE) -> D09530006VXWCB3 | F34: 103.42 | G34: ='March 2025'!F34 -> 1310 | H34: =G34*$H$5 -> 484.7 | I34: =((H34-F34)/H34) -> 0.78663091 | J34: =(($F34/(1-J$9))) -> 258.55 | K34: =(($F34/(1-$K$9))) -> 318.21538 | L34: =(($F34/(1-L$9))) -> 413.68
B35: Water Flow Cartridge Kit, .13 GPM, Stainless, 3/4” NPT | C35: 1 | D35: K000953X13 | E35: =VLOOKUP(D35,Sheet1!B:C, 2, FALSE) -> D09530006VXWCX3 | F35: 133.39 | G35: ='March 2025'!F35 -> 1556.5 | H35: =G35*$H$5 -> 575.905 | I35: =((H35-F35)/H35) -> 0.76838194 | J35: =(($F35/(1-J$9))) -> 333.475 | K35: =(($F35/(1-$K$9))) -> 410.43077 | L35: =(($F35/(1-L$9))) -> 533.56
B36: Water Flow Cartridge Kit, .26 GPM, Brass, 3/4” NPT | C36: 1 | D36: K000953026 | E36: =VLOOKUP(D36,Sheet1!B:C, 2, FALSE) -> D09530006VXWCB4 | F36: 109.44 | G36: ='March 2025'!F36 -> 1310 | H36: =G36*$H$5 -> 484.7 | I36: =((H36-F36)/H36) -> 0.77421085 | J36: =(($F36/(1-J$9))) -> 273.6 | K36: =(($F36/(1-$K$9))) -> 336.73846 | L36: =(($F36/(1-L$9))) -> 437.76
B37: Water Flow Cartridge Kit, .26 GPM, Stainless, 3/4” NPT | C37: 1 | D37: K000953X26 | E37: =VLOOKUP(D37,Sheet1!B:C, 2, FALSE) -> D09530006VXWCX4 | F37: 133.39 | G37: ='March 2025'!F37 -> 1556.5 | H37: =G37*$H$5 -> 575.905 | I37: =((H37-F37)/H37) -> 0.76838194 | J37: =(($F37/(1-J$9))) -> 333.475 | K37: =(($F37/(1-$K$9))) -> 410.43077 | L37: =(($F37/(1-L$9))) -> 533.56
B38: Water Flow Cartridge Kit, .53 GPM, Brass, 3/4” NPT | C38: 1 | D38: K000953053 | E38: =VLOOKUP(D38,Sheet1!B:C, 2, FALSE) -> D09530006VXWCB5 | F38: 103.42 | G38: ='March 2025'!F38 -> 1310 | H38: =G38*$H$5 -> 484.7 | I38: =((H38-F38)/H38) -> 0.78663091 | J38: =(($F38/(1-J$9))) -> 258.55 | K38: =(($F38/(1-$K$9))) -> 318.21538 | L38: =(($F38/(1-L$9))) -> 413.68
B39: Water Flow Cartridge Kit, .53 GPM, Stainless, 3/4” NPT | C39: 1 | D39: K000953X53 | E39: =VLOOKUP(D39,Sheet1!B:C, 2, FALSE) -> D09530006VXWCX5 | F39: 135.51 | G39: ='March 2025'!F39 -> 1556.5 | H39: =G39*$H$5 -> 575.905 | I39: =((H39-F39)/H39) -> 0.76470078 | J39: =(($F39/(1-J$9))) -> 338.775 | K39: =(($F39/(1-$K$9))) -> 416.95385 | L39: =(($F39/(1-L$9))) -> 542.04
B40: Water Flow Cartridge Kit, .79 GPM, Brass, 3/4” NPT | C40: 1 | D40: K000953079 | E40: =VLOOKUP(D40,Sheet1!B:C, 2, FALSE) -> D09530006VXWCB7 | F40: 103.42 | G40: ='March 2025'!F40 -> 1310 | H40: =G40*$H$5 -> 484.7 | I40: =((H40-F40)/H40) -> 0.78663091 | J40: =(($F40/(1-J$9))) -> 258.55 | K40: =(($F40/(1-$K$9))) -> 318.21538 | L40: =(($F40/(1-L$9))) -> 413.68
B41: Water Flow Cartridge Kit, .79 GPM, Stainless, 3/4” NPT | C41: 1 | D41: K000953X79 | E41: =VLOOKUP(D41,Sheet1!B:C, 2, FALSE) -> D09530006VXWCX7 | F41: 135.51 | G41: ='March 2025'!F41 -> 1556.5 | H41: =G41*$H$5 -> 575.905 | I41: =((H41-F41)/H41) -> 0.76470078 | J41: =(($F41/(1-J$9))) -> 338.775 | K41: =(($F41/(1-$K$9))) -> 416.95385 | L41: =(($F41/(1-L$9))) -> 542.04
B42: Water Flow Cartridge Kit, 1.06 GPM, Brass, 3/4” NPT | C42: 1 | D42: K000953106 | E42: =VLOOKUP(D42,Sheet1!B:C, 2, FALSE) -> D09530006VXWCB6 | F42: 103.42 | G42: ='March 2025'!F42 -> 1310 | H42: =G42*$H$5 -> 484.7 | I42: =((H42-F42)/H42) -> 0.78663091 | J42: =(($F42/(1-J$9))) -> 258.55 | K42: =(($F42/(1-$K$9))) -> 318.21538 | L42: =(($F42/(1-L$9))) -> 413.68
B43: Water Flow Cartridge Kit, 1.06 GPM, Stainless, 3/4” NPT | C43: 1 | D43: K000953X06 | E43: =VLOOKUP(D43,Sheet1!B:C, 2, FALSE) -> D09530006VXWCX6 | F43: 135.51 | G43: ='March 2025'!F43 -> 1556.5 | H43: =G43*$H$5 -> 575.905 | I43: =((H43-F43)/H43) -> 0.76470078 | J43: =(($F43/(1-J$9))) -> 338.775 | K43: =(($F43/(1-$K$9))) -> 416.95385 | L43: =(($F43/(1-L$9))) -> 542.04
B44: Water Flow Cartridge Kit, 1.59 GPM, Brass, 3/4” NPT | C44: 1 | D44: K000953153 | E44: =VLOOKUP(D44,Sheet1!B:C, 2, FALSE) -> K09530006VXWCB9 | F44: 114.8635 | G44: ='March 2025'!F44 -> 1310 | H44: =G44*$H$5 -> 484.7 | I44: =((H44-F44)/H44) -> 0.76302146 | J44: =(($F44/(1-J$9))) -> 287.15875 | K44: =(($F44/(1-$K$9))) -> 353.42615 | L44: =(($F44/(1-L$9))) -> 459.454
B45: Water Flow Cartridge Kit, 1.59 GPM, Stainless, 3/4” NPT | C45: 1 | D45: K00095315X | E45: =VLOOKUP(D45,Sheet1!B:C, 2, FALSE) -> K09530006VXWCX9 | F45: 148.8035 | G45: ='March 2025'!F45 -> 1556.5 | H45: =G45*$H$5 -> 575.905 | I45: =((H45-F45)/H45) -> 0.74161798 | J45: =(($F45/(1-J$9))) -> 372.00875 | K45: =(($F45/(1-$K$9))) -> 457.85692 | L45: =(($F45/(1-L$9))) -> 595.214
... B49: Water Flow Cartridge Kit, 4.23 GPM, Stainless, 3/4” NPT | C49: 1 | D49: K000953X23 | E49: =VLOOKUP(D49,Sheet1!B:C, 2, FALSE) -> K09530006VXWCX3 | F49: 148.8035 | G49: ='March 2025'!F49 -> 1556.5 | H49: =G49*$H$5 -> 575.905 | I49: =((H49-F49)/H49) -> 0.74161798 | J49: =(($F49/(1-J$9))) -> 372.00875 | K49: =(($F49/(1-$K$9))) -> 457.85692 | L49: =(($F49/(1-L$9))) -> 595.214
B51: Components
B52: 1/4" MNPT x 7/16-20 Male JIC Straight adapter, brass | C52: 0.1 | D52: PAY7000C01 | E52: =VLOOKUP(D52,Sheet1!B:C, 2, FALSE) -> D09550002VXMFBA | F52: 4.26 | G52: ='March 2025'!F52 -> 24 | H52: =G52*$H$5 -> 8.88 | I52: =((H52-F52)/H52) -> 0.52027027 | J52: =(($F52/(1-J$9))) -> 10.65 | K52: =(($F52/(1-$K$9))) -> 13.107692 | L52: =(($F52/(1-L$9))) -> 17.04
B53: 7/16-20 Female JIC x 31” PTFE lined braided stainless hose, 1/4” ID | C53: 0.4 | D53: P310955228 | E53: =VLOOKUP(D53,Sheet1!B:C, 2, FALSE) -> D09550310VXJICX | F53: 67.5127 | G53: ='March 2025'!F53 -> 397 | H53: =G53*$H$5 -> 146.89 | I53: =((H53-F53)/H53) -> 0.540386 | J53: =(($F53/(1-J$9))) -> 168.78175 | K53: =(($F53/(1-$K$9))) -> 207.73138 | L53: =(($F53/(1-L$9))) -> 270.0508
B54: 7/16-20 Female JIC x 36” PTFE lined braided stainless hose, 1/4” ID | C54: 0.4 | D54: P360955228 | E54: =VLOOKUP(D54,Sheet1!B:C, 2, FALSE) -> D09550360VXJICX | F54: 76.17 | G54: ='March 2025'!F54 -> 597 | H54: =G54*$H$5 -> 220.89 | I54: =((H54-F54)/H54) -> 0.65516773 | J54: =(($F54/(1-J$9))) -> 190.425 | K54: =(($F54/(1-$K$9))) -> 234.36923 | L54: =(($F54/(1-L$9))) -> 304.68
B55: 7/16-20 Female JIC x 48” PTFE lined braided stainless hose, 1/4” ID | C55: 1 | D55: P480955228 | E55: =VLOOKUP(D55,Sheet1!B:C, 2, FALSE) -> D09550480VXJICX | F55: 107.544 | G55: ='March 2025'!F55 -> 694 | H55: =G55*$H$5 -> 256.78 | I55: =((H55-F55)/H55) -> 0.58118234 | J55: =(($F55/(1-J$9))) -> 268.86 | K55: =(($F55/(1-$K$9))) -> 330.90462 | L55: =(($F55/(1-L$9))) -> 430.176
B56: 1/4" MNPT x 7/16-20 Male JIC 90 degree adapter, brass | C56: 0.1 | D56: PAY0955001 | E56: =VLOOKUP(D56,Sheet1!B:C, 2, FALSE) -> D09550000VXBSEN | F56: 1.13 | G56: ='March 2025'!F56 -> 9.5 | H56: =G56*$H$5 -> 3.515 | I56: =((H56-F56)/H56) -> 0.67852063 | J56: =(($F56/(1-J$9))) -> 2.825 | K56: =(($F56/(1-$K$9))) -> 3.4769231 | L56: =(($F56/(1-L$9))) -> 4.52
B57: 1/4" NPT x 3/8" OD compression, 90 degree adapter, brass | C57: 0.1 | D57: SY45953001 | E57: =VLOOKUP(D57,Sheet1!B:C, 2, FALSE) -> D09530002TEVXE9 | F57: 2.92 | G57: ='March 2025'!F57 -> 24 | H57: =G57*$H$5 -> 8.88 | I57: =((H57-F57)/H57) -> 0.67117117 | J57: =(($F57/(1-J$9))) -> 7.3 | K57: =(($F57/(1-$K$9))) -> 8.9846154 | L57: =(($F57/(1-L$9))) -> 11.68
B58: 1/4" NPT x 3/8" OD compression, straight adapter, brass | C58: 0.1 | D58: SY45953002 | E58: =VLOOKUP(D58,Sheet1!B:C, 2, FALSE) -> D09530002TEVXAB | F58: 2.19 | G58: ='March 2025'!F58 -> 18.5 | H58: =G58*$H$5 -> 6.845 | I58: =((H58-F58)/H58) -> 0.68005844 | J58: =(($F58/(1-J$9))) -> 5.475 | K58: =(($F58/(1-$K$9))) -> 6.7384615 | L58: =(($F58/(1-L$9))) -> 8.76
B60: Vortex Panels
B61: Combination Panels
B62: 1"
B63: 1” 951 Combination Panel, Dry Contact, Ball Valve | C63: 170 | D63: S010951DRY | E63: =VLOOKUP(D63,Sheet1!B:C, 2, FALSE) -> D09510010VX3DC1 | F63: 3997.8518 | G63: ='March 2025'!F63 -> 45814 | H63: =G63*$H$5 -> 16951.18 | I63: =((H63-F63)/H63) -> 0.76415496 | J63: =(($F63/(1-J$9))) -> 9994.6294 | K63: =(($F63/(1-$K$9))) -> 12301.082 | L63: =(($F63/(1-L$9))) -> 15991.407
B64: 1” 951 Combination Panel, Active Release, Ball Valve | C64: 170 | D64: S010951ACT | E64: =VLOOKUP(D64,Sheet1!B:C, 2, FALSE) -> D09510010VX3ARC | F64: 4014.89 | G64: ='March 2025'!F64 -> 46009 | H64: =G64*$H$5 -> 17023.33 | I64: =((H64-F64)/H64) -> 0.76415366 | J64: =(($F64/(1-J$9))) -> 10037.225 | K64: =(($F64/(1-$K$9))) -> 12353.508 | L64: =(($F64/(1-L$9))) -> 16059.56
B65: 1.5"
B66: 1.5” 951 Combination Panel, Dry Contact, Ball Valve | C66: 180 | D66: S014951DRY | E66: =VLOOKUP(D66,Sheet1!B:C, 2, FALSE) -> D09510014VX3DCC | F66: 4207.94 | G66: ='March 2025'!F66 -> 48221 | H66: =G66*$H$5 -> 17841.77 | I66: =((H66-F66)/H66) -> 0.76415232 | J66: =(($F66/(1-J$9))) -> 10519.85 | K66: =(($F66/(1-$K$9))) -> 12947.508 | L66: =(($F66/(1-L$9))) -> 16831.76
B67: 1.5” 951 Combination Panel, Active Release, Ball Valve | C67: 180 | D67: S014951ACT | E67: =VLOOKUP(D67,Sheet1!B:C, 2, FALSE) -> D09510014VX3ARC | F67: 4208.44 | G67: ='March 2025'!F67 -> 48227 | H67: =G67*$H$5 -> 17843.99 | I67: =((H67-F67)/H67) -> 0.76415365 | J67: =(($F67/(1-J$9))) -> 10521.1 | K67: =(($F67/(1-$K$9))) -> 12949.046 | L67: =(($F67/(1-L$9))) -> 16833.76
B68: * Please note each Combination Panels requires a pressure transducer to be ordered separately. Reference spare parts section for pressure transducer selection.
B70: Fluid Panels
B71: 1"
B72: 1” 951 Fluid Panel, Dry Contact | C72: 130 | D72: S010951F00 | E72: =VLOOKUP(D72,Sheet1!B:C, 2, FALSE) -> D09510010VX3DC2 | F72: 2813.51 | G72: ='March 2025'!F72 -> 32241.5 | H72: =G72*$H$5 -> 11929.355 | I72: =((H72-F72)/H72) -> 0.76415238 | J72: =(($F72/(1-J$9))) -> 7033.775 | K72: =(($F72/(1-$K$9))) -> 8656.9538 | L72: =(($F72/(1-L$9))) -> 11254.04
B73: 1” 951 Fluid Panel, Active Release | C73: 130 | D73: S010951FA0 | E73: =VLOOKUP(D73,Sheet1!B:C, 2, FALSE) -> D09510010VX3ARF | F73: 3016.09 | G73: ='March 2025'!F73 -> 34563 | H73: =G73*$H$5 -> 12788.31 | I73: =((H73-F73)/H73) -> 0.76415257 | J73: =(($F73/(1-J$9))) -> 7540.225 | K73: =(($F73/(1-$K$9))) -> 9280.2769 | L73: =(($F73/(1-L$9))) -> 12064.36
B74: 1.5"
B75: 1.5” 951 Fluid Panel, Dry Contact | C75: 140 | D75: S014951F00 | E75: =VLOOKUP(D75,Sheet1!B:C, 2, FALSE) -> D09510014VX3DCF | F75: 3007.06 | G75: ='March 2025'!F75 -> 34460 | H75: =G75*$H$5 -> 12750.2 | I75: =((H75-F75)/H75) -> 0.76415586 | J75: =(($F75/(1-J$9))) -> 7517.65 | K75: =(($F75/(1-$K$9))) -> 9252.4923 | L75: =(($F75/(1-L$9))) -> 12028.24
B76: 1.5” 951 Fluid Panel, Active Release | C76: 140 | D76: S014951FA0 | E76: =VLOOKUP(D76,Sheet1!B:C, 2, FALSE) -> D09510014VX3ARF | F76: 3105.65 | G76: ='March 2025'!F76 -> 35589.5 | H76: =G76*$H$5 -> 13168.115 | I76: =((H76-F76)/H76) -> 0.76415379 | J76: =(($F76/(1-J$9))) -> 7764.125 | K76: =(($F76/(1-$K$9))) -> 9555.8462 | L76: =(($F76/(1-L$9))) -> 12422.6
B77: *Please note that each Fluid Panel requires a pressure transducer to be ordered separately. Reference spare parts section for pressure transducer selection.
B79: Zone Panels
B80: 1.5"
B81: 1.5” 951 Zone Panel, Dry Contact, Ball Valve | C81: 150 | D81: S01495110A | E81: =VLOOKUP(D81,Sheet1!B:C, 2, FALSE) -> D09510014VX3DCZ | F81: 2114.93 | G81: ='March 2025'!F81 -> 24236.5 | H81: =G81*$H$5 -> 8967.505 | I81: =((H81-F81)/H81) -> 0.76415625 | J81: =(($F81/(1-J$9))) -> 5287.325 | K81: =(($F81/(1-$K$9))) -> 6507.4769 | L81: =(($F81/(1-L$9))) -> 8459.72
B82: 2"
B83: 2” 951 Zone Panel, Dry Contact, Ball Valve | C83: 150 | D83: S02095110A | E83: =VLOOKUP(D83,Sheet1!B:C, 2, FALSE) -> D09510020VX3DCZ | F83: 2433.5 | G83: ='March 2025'!F83 -> 27887.5 | H83: =G83*$H$5 -> 10318.375 | I83: =((H83-F83)/H83) -> 0.7641586 | J83: =(($F83/(1-J$9))) -> 6083.75 | K83: =(($F83/(1-$K$9))) -> 7487.6923 | L83: =(($F83/(1-L$9))) -> 9734
B84: Pressure Transducers
B85: Pressure Transducer, Standard, 0-100 psi | C85: 1 | D85: P000951134 | E85: =VLOOKUP(D85,Sheet1!B:C, 2, FALSE) -> D09510000VXPT0D | F85: 125.48 | G85: ='March 2025'!F85 -> 1950.5 | H85: =G85*$H$5 -> 721.685 | I85: =((H85-F85)/H85) -> 0.82612913 | J85: =(($F85/(1-J$9))) -> 313.7 | K85: =(($F85/(1-$K$9))) -> 386.09231 | L85: =(($F85/(1-L$9))) -> 501.92
B86: Pressure Transducer Spec. App, Explosion Proof | C86: 1 | D86: P000951TRM | E86: =VLOOKUP(D86,Sheet1!B:C, 2, FALSE) -> D09510000VXTRVP | F86: 761.6 | G86: ='March 2025'!F86 -> 4599 | H86: =G86*$H$5 -> 1701.63 | I86: =((H86-F86)/H86) -> 0.55242914 | J86: =(($F86/(1-J$9))) -> 1904 | K86: =(($F86/(1-$K$9))) -> 2343.3846 | L86: =(($F86/(1-L$9))) -> 3046.4
B88: Design Method Labels
B89: FM Approved for Data Processing Rooms (Engineered) | C89: 0.1 | D89: Z519889LBL | E89: ZL1988900000000 | F89: 5.23 | G89: ='March 2025'!F89 -> 58.5 | H89: =G89*$H$5 -> 21.645 | I89: =((H89-F89)/H89) -> 0.75837376 | J89: =(($F89/(1-J$9))) -> 13.075 | K89: =(($F89/(1-$K$9))) -> 16.092308 | L89: =(($F89/(1-L$9))) -> 20.92
B90: FM Approved for Turbine and Machine Spaces | C90: 0.1 | D90: Z519890LBL | E90: ZL1989000000000 | F90: 5.23 | G90: ='March 2025'!F90 -> 58.5 | H90: =G90*$H$5 -> 21.645 | I90: =((H90-F90)/H90) -> 0.75837376 | J90: =(($F90/(1-J$9))) -> 13.075 | K90: =(($F90/(1-$K$9))) -> 16.092308 | L90: =(($F90/(1-L$9))) -> 20.92
B91: FM Approved for Wet Benches | C91: 0.1 | D91: Z519891LBL | E91: ZL1989100000000 | F91: 5.23 | G91: ='March 2025'!F91 -> 58.5 | H91: =G91*$H$5 -> 21.645 | I91: =((H91-F91)/H91) -> 0.75837376 | J91: =(($F91/(1-J$9))) -> 13.075 | K91: =(($F91/(1-$K$9))) -> 16.092308 | L91: =(($F91/(1-L$9))) -> 20.92
B92: FM Approved for Data Processing Rooms (Pre-Engineered) | C92: 0.1 | D92: Z521073LBL | E92: ZL2107300000000 | F92: 6.42 | G92: ='March 2025'!F92 -> 58.5 | H92: =G92*$H$5 -> 21.645 | I92: =((H92-F92)/H92) -> 0.7033957 | J92: =(($F92/(1-J$9))) -> 16.05 | K92: =(($F92/(1-$K$9))) -> 19.753846 | L92: =(($F92/(1-L$9))) -> 25.68
B93: Performance Based Designs | C93: 0.1 | D93: Z519892LBL | E93: ZL1989200000000 | F93: 6.42 | G93: ='March 2025'!F93 -> 58.5 | H93: =G93*$H$5 -> 21.645 | I93: =((H93-F93)/H93) -> 0.7033957 | J93: =(($F93/(1-J$9))) -> 16.05 | K93: =(($F93/(1-$K$9))) -> 19.753846 | L93: =(($F93/(1-L$9))) -> 25.68
B94: Note: Each panel requires a design method label. Design method labels are sold separately.
B95: Nitrogen Supply
B96: Relief Valves
B97: Fluid to Zone Piping Relief Valve .85 Orifice 11/2” | C97: 12 | D97: S010951RLV | E97: =VLOOKUP(D97,Sheet1!B:C, 2, FALSE) -> D09510014VXR000 | F97: 288.17 | G97: ='March 2025'!F96 -> 0 | H97: =G97*$H$5 -> 0 | I97: =((H97-F97)/H97) -> #DIV/0! | J97: =(($F97/(1-J$9))) -> 720.425 | K97: =(($F97/(1-$K$9))) -> 886.67692 | L97: =(($F97/(1-L$9))) -> 1152.68
B98: Fluid to Zone Piping Relief Valve 1.39 Orifice 2” | C98: 12 | D98: S020951RLV | E98: =VLOOKUP(D98,Sheet1!B:C, 2, FALSE) -> D09510020VXRV00 | F98: 369.04 | G98: ='March 2025'!F97 -> 6529 | H98: =G98*$H$5 -> 2415.73 | I98: =((H98-F98)/H98) -> 0.84723458 | J98: =(($F98/(1-J$9))) -> 922.6 | K98: =(($F98/(1-$K$9))) -> 1135.5077 | L98: =(($F98/(1-L$9))) -> 1476.16
B100: Cylinders
B101: Victaulic Vortex Nitrogen Cylinder, 80L, w/Valve, Filled | C101: 320 | D101: S000950A01 | E101: =VLOOKUP(D101,Sheet1!B:C, 2, FALSE) -> D09500000VXS000 | F101: 851.09 | G101: ='March 2025'!F100 -> 0 | H101: =G101*$H$5 -> 0 | I101: =((H101-F101)/H101) -> #DIV/0! | J101: =(($F101/(1-J$9))) -> 2127.725 | K101: =(($F101/(1-$K$9))) -> 2618.7385 | L101: =(($F101/(1-L$9))) -> 3404.36
B102: Victaulic Vortex Nitrogen Cylinder, 49L, w/Valve, Filled | C102: 134 | D102: S000950A02 | E102: =VLOOKUP(D102,Sheet1!B:C, 2, FALSE) -> D09500000VXSC0A | F102: 341.67 | G102: ='March 2025'!F101 -> 6096.5 | H102: =G102*$H$5 -> 2255.705 | I102: =((H102-F102)/H102) -> 0.84853073 | J102: =(($F102/(1-J$9))) -> 854.175 | K102: =(($F102/(1-$K$9))) -> 1051.2923 | L102: =(($F102/(1-L$9))) -> 1366.68
B104: Discharge Hose Kits and Accessories
B105: 80L Cylinder Primary Pilot Kit | C105: 5 | D105: S0009500PP | E105: =VLOOKUP(D105,Sheet1!B:C, 2, FALSE) -> D09500000VXPPK0 | F105: 551.3426 | G105: =CEILING((Master!F126*1.06),0.5) -> 0 | H105: =G105*$H$5 -> 0 | I105: =((H105-F105)/H105) -> #DIV/0! | J105: =(($F105/(1-J$9))) -> 1378.3565 | K105: =(($F105/(1-$K$9))) -> 1696.4388 | L105: =(($F105/(1-L$9))) -> 2205.3704
B106: 80L Cylinder Secondary Kit, With Gauge | C106: 2 | D106: S0009500SP | E106: =VLOOKUP(D106,Sheet1!B:C, 2, FALSE) -> D09500000VX00SP | F106: 130.0367 | G106: =CEILING((Master!F127*1.06),0.5) -> 0 | H106: =G106*$H$5 -> 0 | I106: =((H106-F106)/H106) -> #DIV/0! | J106: =(($F106/(1-J$9))) -> 325.09175 | K106: =(($F106/(1-$K$9))) -> 400.11292 | L106: =(($F106/(1-L$9))) -> 520.1468
B107: 80L Cylinder Secondary Pilot Kit, With Gauge and Pressure Switch | C107: 2 | D107: S000950PSP | E107: =VLOOKUP(D107,Sheet1!B:C, 2, FALSE) -> D09500000VXSPPG | F107: 136.3425 | G107: =CEILING((Master!F128*1.06),0.5) -> 6391.5 | H107: =G107*$H$5 -> 2364.855 | I107: =((H107-F107)/H107) -> 0.94234636 | J107: =(($F107/(1-J$9))) -> 340.85625 | K107: =(($F107/(1-$K$9))) -> 419.51538 | L107: =(($F107/(1-L$9))) -> 545.37
B108: 49L CYLINDER PRIMARY PILOT KIT | C108: 5 | D108: S4909500PP | E108: =VLOOKUP(D108,Sheet1!B:C, 2, FALSE) -> D095000000VX4P0 | F108: 550.49 | G108: =CEILING((Master!F129*1.06),0.5) -> 1513 | H108: =G108*$H$5 -> 559.81 | I108: =((H108-F108)/H108) -> 0.016648506 | J108: =(($F108/(1-J$9))) -> 1376.225 | K108: =(($F108/(1-$K$9))) -> 1693.8154 | L108: =(($F108/(1-L$9))) -> 2201.96
B109: 49L CYLINDER SECONDARY KIT WITH GAUGE | C109: 2 | D109: S4909500SP | E109: =VLOOKUP(D109,Sheet1!B:C, 2, FALSE) -> #N/A | F109: 133.22 | G109: =CEILING((Master!F130*1.06),0.5) -> 2355.5 | H109: =G109*$H$5 -> 871.535 | I109: =((H109-F109)/H109) -> 0.84714326 | J109: =(($F109/(1-J$9))) -> 333.05 | K109: =(($F109/(1-$K$9))) -> 409.90769 | L109: =(($F109/(1-L$9))) -> 532.88
B110: 1/4” Pilot Hose, 700 MM, for joining rows in double stacked racks | C110: 1 | D110: S000950P70 | E110: =VLOOKUP(D110,Sheet1!B:C, 2, FALSE) -> D09500004VXSPH0 | F110: 8.3373 | G110: =CEILING((Master!F131*1.06),0.5) -> 149.5 | H110: =G110*$H$5 -> 55.315 | I110: =((H110-F110)/H110) -> 0.84927596 | J110: =(($F110/(1-J$9))) -> 20.84325 | K110: =(($F110/(1-$K$9))) -> 25.653231 | L110: =(($F110/(1-L$9))) -> 33.3492
B111: 1/4” Pilot Hose, 500 MM, for joining adjacent racks | C111: 1 | D111: S000950P50 | E111: =VLOOKUP(D111,Sheet1!B:C, 2, FALSE) -> D09500002VXPH00 | F111: 6.9395 | G111: =CEILING((Master!F132*1.06),0.5) -> 126.5 | H111: =G111*$H$5 -> 46.805 | I111: =((H111-F111)/H111) -> 0.85173593 | J111: =(($F111/(1-J$9))) -> 17.34875 | K111: =(($F111/(1-$K$9))) -> 21.352308 | L111: =(($F111/(1-L$9))) -> 27.758
B112: Vortex Single Cylinder Refill Adapter, CGA-580 Inlet | C112: 1 | D112: S002950000 | E112: =VLOOKUP(D112,Sheet1!B:C, 2, FALSE) -> D09500000VXT0A5 | F112: 48.1468 | G112: =CEILING((Master!F133*1.06),0.5) -> 757 | H112: =G112*$H$5 -> 280.09 | I112: =((H112-F112)/H112) -> 0.8281024 | J112: =(($F112/(1-J$9))) -> 120.367 | K112: =(($F112/(1-$K$9))) -> 148.144 | L112: =(($F112/(1-L$9))) -> 192.5872
B113: Vortex Single Cylinder Refill Adapter, CGA-677 Inlet | C113: 1 | D113: S002950401 | E113: =VLOOKUP(D113,Sheet1!B:C, 2, FALSE) -> D0950000VXTA00A | F113: 89.8868 | G113: =CEILING((Master!F134*1.06),0.5) -> 757 | H113: =G113*$H$5 -> 280.09 | I113: =((H113-F113)/H113) -> 0.67907887 | J113: =(($F113/(1-J$9))) -> 224.717 | K113: =(($F113/(1-$K$9))) -> 276.57477 | L113: =(($F113/(1-L$9))) -> 359.5472
B114: In Place Bulk Cylinder Refill Kit, 1” NPT Inlet | C114: 20 | D114: S000950015 | E114: =VLOOKUP(D114,Sheet1!B:C, 2, FALSE) -> D09500000VX0MFA | F114: 768.69 | G114: =CEILING((Master!F135*1.06),0.5) -> 6458.5 | H114: =G114*$H$5 -> 2389.645 | I114: =((H114-F114)/H114) -> 0.6783246 | J114: =(($F114/(1-J$9))) -> 1921.725 | K114: =(($F114/(1-$K$9))) -> 2365.2 | L114: =(($F114/(1-L$9))) -> 3074.76
...

Sheet March 2025
B1: Victaulic Vortex® System Product List Price Effective March 1st, 2025
B2: United States
G4: Multiplier:
B5: NOTE: Please add information to the cells shaded in | C5: GREEN. | G5: 0.37
B7: Option Style | C7: Shipping Weight | D7: Part Code | E7: Cost (USD) | F7: List Price (USD) | G7: Extended Price | H7: GM % | I7: 60% Margin Sell | J7: 67.5% Margin Sell | K7: 75% Margin Sell
B9: Emitters | I9: 0.6 | J9: 0.675 | K9: 0.75
B10: 1/8" Emitters
B11: 1/8” Emitter, 954 cavity foil, standard, PVDF, 3/8” FPT, 1/8” FPT | C11: 1 | D11: S003953105 | E11: 195.71 | F11: =CEILING((Updated!F11*1.06),0.5) -> 2986.5 | G11: =F11*$G$5 -> 1105.005 | H11: =((G11-E11)/G11) -> 0.82288768 | I11: =(($E11/(1-$I9))) -> 489.275 | J11: =(($E11/(1-$J$9))) -> 602.18462 | K11: =(($E11/(1-$K9))) -> 782.84
B12: 1/8” Emitter, 953 dome foil, standard, stainless, 3/8” FPT, 1/8” FPT | C12: 1 | D12: S00195310X | E12: 171.534 | F12: =CEILING((Updated!F12*1.06),0.5) -> 2874.5 | G12: =F12*$G$5 -> 1063.565 | H12: =((G12-E12)/G12) -> 0.8387179 | I12: =(($E12/(1-$I$9))) -> 428.835 | J12: =(($E12/(1-$J$9))) -> 527.79692 | K12: =(($E12/(1-$K$9))) -> 686.136
B13: 1/4" Emitters
B14: 1/4” Emitter, 953 dome foil, standard, stainless, 3/4” MPT, 1/4” FPT | C14: 1 | D14: S002953X02 | E14: 160.1174 | F14: =CEILING((Updated!F14*1.06),0.5) -> 3333 | G14: =F14*$G$5 -> 1233.21 | H14: =((G14-E14)/G14) -> 0.8701621 | I14: =(($E14/(1-I$9))) -> 400.2935 | J14: =(($E14/(1-$J$9))) -> 492.66892 | K14: =(($E14/(1-K$9))) -> 640.4696
B15: 1/4” Emitter, 954 cavity foil, standard, PVDF, 3/8” FPT, 1/8” FPT | C15: 1 | D15: S003953170 | E15: 241.4136 | F15: =CEILING((Updated!F15*1.06),0.5) -> 2985.5 | G15: =F15*$G$5 -> 1104.635 | H15: =((G15-E15)/G15) -> 0.78145396 | I15: =(($E15/(1-$I$9))) -> 603.534 | J15: =(($E15/(1-$J$9))) -> 742.81108 | K15: =(($E15/(1-$K$9))) -> 965.6544
B16: 3/8" Emitters
B17: 3/8” Emitter, 953 dome foil, escutcheon, stainless, 3/4” FPT, 1/4” FPT | C17: 1 | D17: S003953032 | E17: 52.3201 | F17: =CEILING((Updated!F17*1.06),0.5) -> 1332.5 | G17: =F17*$G$5 -> 493.025 | H17: =((G17-E17)/G17) -> 0.89387942 | I17: =(($E17/(1-I$9))) -> 130.80025 | J17: =(($E17/(1-$J$9))) -> 160.98492 | K17: =(($E17/(1-K$9))) -> 209.2804
B18: 3/8” Emitter, 953 dome foil, standard, stainless, 3/4” FPT, 1/4” FPT | C18: 1 | D18: S003953034 | E18: 34.5438 | F18: =CEILING((Updated!F18*1.06),0.5) -> 1262.5 | G18: =F18*$G$5 -> 467.125 | H18: =((G18-E18)/G18) -> 0.9260502 | I18: =(($E18/(1-I$9))) -> 86.3595 | J18: =(($E18/(1-$J$9))) -> 106.28862 | K18: =(($E18/(1-K$9))) -> 138.1752
B19: 3/8” Emitter, 954 cavity foil, escutcheon, stainless, 3/4” FPT, 1/4” FPT | C19: 1 | D19: S003953031 | E19: 51.85424 | F19: =CEILING((Updated!F19*1.06),0.5) -> 1332.5 | G19: =F19*$G$5 -> 493.025 | H19: =((G19-E19)/G19) -> 0.89482432 | I19: =(($E19/(1-I$9))) -> 129.6356 | J19: =(($E19/(1-$J$9))) -> 159.55151 | K19: =(($E19/(1-K$9))) -> 207.41696
B20: 3/8” Emitter, 954 cavity foil, standard, stainless, 3/4” FPT, 1/4” FPT | C20: 1 | D20: S003953033 | E20: 34.07794 | F20: =CEILING((Updated!F20*1.06),0.5) -> 1262.5 | G20: =F20*$G$5 -> 467.125 | H20: =((G20-E20)/G20) -> 0.92704749 | I20: =(($E20/(1-I$9))) -> 85.19485 | J20: =(($E20/(1-$J$9))) -> 104.8552 | K20: =(($E20/(1-K$9))) -> 136.31176
B21: 1/2" Emitters
B22: 1/2” Emitter, 953 dome foil, standard, brass, 3/4” MPT, 1/4” FPT | C22: 1 | D22: S006953400 | E22: 102.34866 | F22: =CEILING((Updated!F22*1.06),0.5) -> 1262.5 | G22: =F22*$G$5 -> 467.125 | H22: =((G22-E22)/G22) -> 0.78089663 | I22: =(($E22/(1-I$9))) -> 255.87165 | J22: =(($E22/(1-$J$9))) -> 314.91895 | K22: =(($E22/(1-K$9))) -> 409.39464
B23: 1/2” Emitter, 953 dome foil, standard, PVDF, 3/4” MPT, 1/4” FPT | C23: 1 | D23: S006953406 | E23: 230.5925 | F23: =CEILING((Updated!F23*1.06),0.5) -> 2345 | G23: =F23*$G$5 -> 867.65 | H23: =((G23-E23)/G23) -> 0.73423327 | I23: =(($E23/(1-I$9))) -> 576.48125 | J23: =(($E23/(1-$J$9))) -> 709.51538 | K23: =(($E23/(1-K$9))) -> 922.37
B24: 1/2” Emitter, 953 dome foil, escutcheon, stainless, 3/4” FPT, 1/4” FPT | C24: 1 | D24: S004953511 | E24: 60.22 | F24: =CEILING((Updated!F24*1.06),0.5) -> 1332.5 | G24: =F24*$G$5 -> 493.025 | H24: =((G24-E24)/G24) -> 0.87785609 | I24: =(($E24/(1-I$9))) -> 150.55 | J24: =(($E24/(1-$J$9))) -> 185.29231 | K24: =(($E24/(1-K$9))) -> 240.88
B25: 1/2” Emitter, 953 dome foil, standard, stainless, 3/4” FPT, 1/4” FPT | C25: 1 | D25: S004953513 | E25: 35.2038 | F25: =CEILING((Updated!F25*1.06),0.5) -> 1759 | G25: =F25*$G$5 -> 650.83 | H25: =((G25-E25)/G25) -> 0.94590938 | I25: =(($E25/(1-I$9))) -> 88.0095 | J25: =(($E25/(1-$J$9))) -> 108.31938 | K25: =(($E25/(1-K$9))) -> 140.8152
B26: 5/8" Emitters
B27: 5/8” Emitter, 954 cavity foil, standard, PVDF, 3/4” FPT, 1/4" FPT | C27: 1 | D27: S006953503 | E27: 193.3368 | F27: =CEILING((Updated!F27*1.06),0.5) -> 2986.5 | G27: =F27*$G$5 -> 1105.005 | H27: =((G27-E27)/G27) -> 0.82503536 | I27: =(($E27/(1-I$9))) -> 483.342 | J27: =(($E27/(1-$J$9))) -> 594.88246 | K27: =(($E27/(1-K$9))) -> 773.3472
B28: 5/8” Emitter, 954 cavity foil, escutcheon, stainless, 3/4” FPT, 1/4” FPT | C28: 1 | D28: S006953512 | E28: 50.4801 | F28: =CEILING((Updated!F28*1.06),0.5) -> 1332.5 | G28: =F28*$G$5 -> 493.025 | H28: =((G28-E28)/G28) -> 0.89761148 | I28: =(($E28/(1-I$9))) -> 126.20025 | J28: =(($E28/(1-$J$9))) -> 155.32338 | K28: =(($E28/(1-K$9))) -> 201.9204
B29: 5/8” Emitter, 954 cavity foil, standard, stainless, 3/4” FPT, 1/4” FPT | C29: 1 | D29: S006953514 | E29: 32.7038 | F29: =CEILING((Updated!F29*1.06),0.5) -> 1262.5 | G29: =F29*$G$5 -> 467.125 | H29: =((G29-E29)/G29) -> 0.92998919 | I29: =(($E29/(1-I$9))) -> 81.7595 | J29: =(($E29/(1-$J$9))) -> 100.62708 | K29: =(($E29/(1-K$9))) -> 130.8152
B30: 1" Emitters
B31: 1” Emitter, 953/954 dome foil, escutcheon, stainless, 1” FPT, 1/8” FPT | C31: 1 | D31: S010953511 | E31: 68.4904 | F31: =CEILING((Updated!F31*1.06),0.5) -> 2316.5 | G31: =F31*$G$5 -> 857.105 | H31: =((G31-E31)/G31) -> 0.920091 | I31: =(($E31/(1-I$9))) -> 171.226 | J31: =(($E31/(1-$J$9))) -> 210.73969 | K31: =(($E31/(1-K$9))) -> 273.9616
B33: Water Flow Kits (Strainer, Flow Cartridge, Emitter Trim Kit)
B34: Water Flow Cartridge Kit, .13 GPM, Brass, 3/4” NPT | C34: 1 | D34: K000953013 | E34: 103.42 | F34: =CEILING((Updated!F34*1.06),0.5) -> 1310 | G34: =F34*$G$5 -> 484.7 | H34: =((G34-E34)/G34) -> 0.78663091 | I34: =(($E34/(1-I$9))) -> 258.55 | J34: =(($E34/(1-$J$9))) -> 318.21538 | K34: =(($E34/(1-K$9))) -> 413.68
B35: Water Flow Cartridge Kit, .13 GPM, Stainless, 3/4” NPT | C35: 1 | D35: K000953X13 | E35: 133.39 | F35: =CEILING((Updated!F35*1.06),0.5) -> 1556.5 | G35: =F35*$G$5 -> 575.905 | H35: =((G35-E35)/G35) -> 0.76838194 | I35: =(($E35/(1-I$9))) -> 333.475 | J35: =(($E35/(1-$J$9))) -> 410.43077 | K35: =(($E35/(1-K$9))) -> 533.56
B36: Water Flow Cartridge Kit, .26 GPM, Brass, 3/4” NPT | C36: 1 | D36: K000953026 | E36: 109.44 | F36: =CEILING((Updated!F36*1.06),0.5) -> 1310 | G36: =F36*$G$5 -> 484.7 | H36: =((G36-E36)/G36) -> 0.77421085 | I36: =(($E36/(1-I$9))) -> 273.6 | J36: =(($E36/(1-$J$9))) -> 336.73846 | K36: =(($E36/(1-K$9))) -> 437.76
B37: Water Flow Cartridge Kit, .26 GPM, Stainless, 3/4” NPT | C37: 1 | D37: K000953X26 | E37: 133.39 | F37: =CEILING((Updated!F37*1.06),0.5) -> 1556.5 | G37: =F37*$G$5 -> 575.905 | H37: =((G37-E37)/G37) -> 0.76838194 | I37: =(($E37/(1-I$9))) -> 333.475 | J37: =(($E37/(1-$J$9))) -> 410.43077 | K37: =(($E37/(1-K$9))) -> 533.56
B38: Water Flow Cartridge Kit, .53 GPM, Brass, 3/4” NPT | C38: 1 | D38: K000953053 | E38: 103.42 | F38: =CEILING((Updated!F38*1.06),0.5) -> 1310 | G38: =F38*$G$5 -> 484.7 | H38: =((G38-E38)/G38) -> 0.78663091 | I38: =(($E38/(1-I$9))) -> 258.55 | J38: =(($E38/(1-$J$9))) -> 318.21538 | K38: =(($E38/(1-K$9))) -> 413.68
B39: Water Flow Cartridge Kit, .53 GPM, Stainless, 3/4” NPT | C39: 1 | D39: K000953X53 | E39: 135.51 | F39: =CEILING((Updated!F39*1.06),0.5) -> 1556.5 | G39: =F39*$G$5 -> 575.905 | H39: =((G39-E39)/G39) -> 0.76470078 | I39: =(($E39/(1-I$9))) -> 338.775 | J39: =(($E39/(1-$J$9))) -> 416.95385 | K39: =(($E39/(1-K$9))) -> 542.04
B40: Water Flow Cartridge Kit, .79 GPM, Brass, 3/4” NPT | C40: 1 | D40: K000953079 | E40: 103.42 | F40: =CEILING((Updated!F40*1.06),0.5) -> 1310 | G40: =F40*$G$5 -> 484.7 | H40: =((G40-E40)/G40) -> 0.78663091 | I40: =(($E40/(1-I$9))) -> 258.55 | J40: =(($E40/(1-$J$9))) -> 318.21538 | K40: =(($E40/(1-K$9))) -> 413.68
B41: Water Flow Cartridge Kit, .79 GPM, Stainless, 3/4” NPT | C41: 1 | D41: K000953X79 | E41: 135.51 | F41: =CEILING((Updated!F41*1.06),0.5) -> 1556.5 | G41: =F41*$G$5 -> 575.905 | H41: =((G41-E41)/G41) -> 0.76470078 | I41: =(($E41/(1-I$9))) -> 338.775 | J41: =(($E41/(1-$J$9))) -> 416.95385 | K41: =(($E41/(1-K$9))) -> 542.04
B42: Water Flow Cartridge Kit, 1.06 GPM, Brass, 3/4” NPT | C42: 1 | D42: K000953106 | E42: 103.42 | F42: =CEILING((Updated!F42*1.06),0.5) -> 1310 | G42: =F42*$G$5 -> 484.7 | H42: =((G42-E42)/G42) -> 0.78663091 | I42: =(($E42/(1-I$9))) -> 258.55 | J42: =(($E42/(1-$J$9))) -> 318.21538 | K42: =(($E42/(1-K$9))) -> 413.68
B43: Water Flow Cartridge Kit, 1.06 GPM, Stainless, 3/4” NPT | C43: 1 | D43: K000953X06 | E43: 135.51 | F43: =CEILING((Updated!F43*1.06),0.5) -> 1556.5 | G43: =F43*$G$5 -> 575.905 | H43: =((G43-E43)/G43) -> 0.76470078 | I43: =(($E43/(1-I$9))) -> 338.775 | J43: =(($E43/(1-$J$9))) -> 416.95385 | K43: =(($E43/(1-K$9))) -> 542.04
B44: Water Flow Cartridge Kit, 1.59 GPM, Brass, 3/4” NPT | C44: 1 | D44: K000953153 | E44: 114.8635 | F44: =CEILING((Updated!F44*1.06),0.5) -> 1310 | G44: =F44*$G$5 -> 484.7 | H44: =((G44-E44)/G44) -> 0.76302146 | I44: =(($E44/(1-I$9))) -> 287.15875 | J44: =(($E44/(1-$J$9))) -> 353.42615 | K44: =(($E44/(1-K$9))) -> 459.454
B45: Water Flow Cartridge Kit, 1.59 GPM, Stainless, 3/4” NPT | C45: 1 | D45: K00095315X | E45: 148.8035 | F45: =CEILING((Updated!F45*1.06),0.5) -> 1556.5 | G45: =F45*$G$5 -> 575.905 | H45: =((G45-E45)/G45) -> 0.74161798 | I45: =(($E45/(1-I$9))) -> 372.00875 | J45: =(($E45/(1-$J$9))) -> 457.85692 | K45: =(($E45/(1-K$9))) -> 595.214
... B49: Water Flow Cartridge Kit, 4.23 GPM, Stainless, 3/4” NPT | C49: 1 | D49: K000953X23 | E49: 148.8035 | F49: =CEILING((Updated!F49*1.06),0.5) -> 1556.5 | G49: =F49*$G$5 -> 575.905 | H49: =((G49-E49)/G49) -> 0.74161798 | I49: =(($E49/(1-I$9))) -> 372.00875 | J49: =(($E49/(1-$J$9))) -> 457.85692 | K49: =(($E49/(1-K$9))) -> 595.214
B51: Components
B52: 1/4" MNPT x 7/16-20 Male JIC Straight adapter, brass | C52: 0.1 | D52: PAY7000C01 | E52: 4.26 | F52: =CEILING((Updated!F52*1.06),0.5) -> 24 | G52: =F52*$G$5 -> 8.88 | H52: =((G52-E52)/G52) -> 0.52027027 | I52: =(($E52/(1-I$9))) -> 10.65 | J52: =(($E52/(1-$J$9))) -> 13.107692 | K52: =(($E52/(1-K$9))) -> 17.04
B53: 7/16-20 Female JIC x 31” PTFE lined braided stainless hose, 1/4” ID | C53: 0.4 | D53: P310955228 | E53: 67.5127 | F53: =CEILING((Updated!F53*1.06),0.5) -> 397 | G53: =F53*$G$5 -> 146.89 | H53: =((G53-E53)/G53) -> 0.540386 | I53: =(($E53/(1-I$9))) -> 168.78175 | J53: =(($E53/(1-$J$9))) -> 207.73138 | K53: =(($E53/(1-K$9))) -> 270.0508
B54: 7/16-20 Female JIC x 36” PTFE lined braided stainless hose, 1/4” ID | C54: 0.4 | D54: P360955228 | E54: 76.17 | F54: =CEILING((Updated!F54*1.06),0.5) -> 597 | G54: =F54*$G$5 -> 220.89 | H54: =((G54-E54)/G54) -> 0.65516773 | I54: =(($E54/(1-I$9))) -> 190.425 | J54: =(($E54/(1-$J$9))) -> 234.36923 | K54: =(($E54/(1-K$9))) -> 304.68
B55: 7/16-20 Female JIC x 48” PTFE lined braided stainless hose, 1/4” ID | C55: 1 | D55: P480955228 | E55: 107.544 | F55: =CEILING((Updated!F55*1.06),0.5) -> 694 | G55: =F55*$G$5 -> 256.78 | H55: =((G55-E55)/G55) -> 0.58118234 | I55: =(($E55/(1-I$9))) -> 268.86 | J55: =(($E55/(1-$J$9))) -> 330.90462 | K55: =(($E55/(1-K$9))) -> 430.176
B56: 1/4" MNPT x 7/16-20 Male JIC 90 degree adapter, brass | C56: 0.1 | D56: PAY0955001 | E56: 1.13 | F56: =CEILING((Updated!F56*1.06),0.5) -> 9.5 | G56: =F56*$G$5 -> 3.515 | H56: =((G56-E56)/G56) -> 0.67852063 | I56: =(($E56/(1-I$9))) -> 2.825 | J56: =(($E56/(1-$J$9))) -> 3.4769231 | K56: =(($E56/(1-K$9))) -> 4.52
B57: 1/4" NPT x 3/8" OD compression, 90 degree adapter, brass | C57: 0.1 | D57: SY45953001 | E57: 2.92 | F57: =CEILING((Updated!F57*1.06),0.5) -> 24 | G57: =F57*$G$5 -> 8.88 | H57: =((G57-E57)/G57) -> 0.67117117 | I57: =(($E57/(1-I$9))) -> 7.3 | J57: =(($E57/(1-$J$9))) -> 8.9846154 | K57: =(($E57/(1-K$9))) -> 11.68
B58: 1/4" NPT x 3/8" OD compression, straight adapter, brass | C58: 0.1 | D58: SY45953002 | E58: 2.19 | F58: =CEILING((Updated!F58*1.06),0.5) -> 18.5 | G58: =F58*$G$5 -> 6.845 | H58: =((G58-E58)/G58) -> 0.68005844 | I58: =(($E58/(1-I$9))) -> 5.475 | J58: =(($E58/(1-$J$9))) -> 6.7384615 | K58: =(($E58/(1-K$9))) -> 8.76
B60: Vortex Panels
B61: Combination Panels
B62: 1"
B63: 1” 951 Combination Panel, Dry Contact, Ball Valve | C63: 170 | D63: S010951DRY | E63: 3997.8518 | F63: =CEILING((Updated!F63*1.06),0.5) -> 45814 | G63: =F63*$G$5 -> 16951.18 | H63: =((G63-E63)/G63) -> 0.76415496 | I63: =(($E63/(1-I$9))) -> 9994.6294 | J63: =(($E63/(1-$J$9))) -> 12301.082 | K63: =(($E63/(1-K$9))) -> 15991.407
B64: 1” 951 Combination Panel, Active Release, Ball Valve | C64: 170 | D64: S010951ACT | E64: 4014.89 | F64: =CEILING((Updated!F64*1.06),0.5) -> 46009 | G64: =F64*$G$5 -> 17023.33 | H64: =((G64-E64)/G64) -> 0.76415366 | I64: =(($E64/(1-I$9))) -> 10037.225 | J64: =(($E64/(1-$J$9))) -> 12353.508 | K64: =(($E64/(1-K$9))) -> 16059.56
B65: 1.5"
B66: 1.5” 951 Combination Panel, Dry Contact, Ball Valve | C66: 180 | D66: S014951DRY | E66: 4207.94 | F66: =CEILING((Updated!F66*1.06),0.5) -> 48221 | G66: =F66*$G$5 -> 17841.77 | H66: =((G66-E66)/G66) -> 0.76415232 | I66: =(($E66/(1-I$9))) -> 10519.85 | J66: =(($E66/(1-$J$9))) -> 12947.508 | K66: =(($E66/(1-K$9))) -> 16831.76
B67: 1.5” 951 Combination Panel, Active Release, Ball Valve | C67: 180 | D67: S014951ACT | E67: 4208.44 | F67: =CEILING((Updated!F67*1.06),0.5) -> 48227 | G67: =F67*$G$5 -> 17843.99 | H67: =((G67-E67)/G67) -> 0.76415365 | I67: =(($E67/(1-I$9))) -> 10521.1 | J67: =(($E67/(1-$J$9))) -> 12949.046 | K67: =(($E67/(1-K$9))) -> 16833.76
B68: * Please note each Combination Panels requires a pressure transducer to be ordered separately. Reference spare parts section for pressure transducer selection.
B70: Fluid Panels
B71: 1"
B72: 1” 951 Fluid Panel, Dry Contact | C72: 130 | D72: S010951F00 | E72: 2813.51 | F72: =CEILING((Updated!F72*1.06),0.5) -> 32241.5 | G72: =F72*$G$5 -> 11929.355 | H72: =((G72-E72)/G72) -> 0.76415238 | I72: =(($E72/(1-I$9))) -> 7033.775 | J72: =(($E72/(1-$J$9))) -> 8656.9538 | K72: =(($E72/(1-K$9))) -> 11254.04
B73: 1” 951 Fluid Panel, Active Release | C73: 130 | D73: S010951FA0 | E73: 3016.09 | F73: =CEILING((Updated!F73*1.06),0.5) -> 34563 | G73: =F73*$G$5 -> 12788.31 | H73: =((G73-E73)/G73) -> 0.76415257 | I73: =(($E73/(1-I$9))) -> 7540.225 | J73: =(($E73/(1-$J$9))) -> 9280.2769 | K73: =(($E73/(1-K$9))) -> 12064.36
B74: 1.5"
B75: 1.5” 951 Fluid Panel, Dry Contact | C75: 140 | D75: S014951F00 | E75: 3007.06 | F75: =CEILING((Updated!F75*1.06),0.5) -> 34460 | G75: =F75*$G$5 -> 12750.2 | H75: =((G75-E75)/G75) -> 0.76415586 | I75: =(($E75/(1-I$9))) -> 7517.65 | J75: =(($E75/(1-$J$9))) -> 9252.4923 | K75: =(($E75/(1-K$9))) -> 12028.24
B76: 1.5” 951 Fluid Panel, Active Release | C76: 140 | D76: S014951FA0 | E76: 3105.65 | F76: =CEILING((Updated!F76*1.06),0.5) -> 35589.5 | G76: =F76*$G$5 -> 13168.115 | H76: =((G76-E76)/G76) -> 0.76415379 | I76: =(($E76/(1-I$9))) -> 7764.125 | J76: =(($E76/(1-$J$9))) -> 9555.8462 | K76: =(($E76/(1-K$9))) -> 12422.6
B77: *Please note that each Fluid Panel requires a pressure transducer to be ordered separately. Reference spare parts section for pressure transducer selection.
B79: Zone Panels
B80: 1.5"
B81: 1.5” 951 Zone Panel, Dry Contact, Ball Valve | C81: 150 | D81: S01495110A | E81: 2114.93 | F81: =CEILING((Updated!F81*1.06),0.5) -> 24236.5 | G81: =F81*$G$5 -> 8967.505 | H81: =((G81-E81)/G81) -> 0.76415625 | I81: =(($E81/(1-I$9))) -> 5287.325 | J81: =(($E81/(1-$J$9))) -> 6507.4769 | K81: =(($E81/(1-K$9))) -> 8459.72
B82: 2"
B83: 2” 951 Zone Panel, Dry Contact, Ball Valve | C83: 150 | D83: S02095110A | E83: 2433.5 | F83: =CEILING((Updated!F83*1.06),0.5) -> 27887.5 | G83: =F83*$G$5 -> 10318.375 | H83: =((G83-E83)/G83) -> 0.7641586 | I83: =(($E83/(1-I$9))) -> 6083.75 | J83: =(($E83/(1-$J$9))) -> 7487.6923 | K83: =(($E83/(1-K$9))) -> 9734
B84: Pressure Transducers
B85: Pressure Transducer, Standard, 0-100 psi | C85: 1 | D85: P000951134 | E85: 125.48 | F85: =CEILING((Updated!F85*1.06),0.5) -> 1950.5 | G85: =F85*$G$5 -> 721.685 | H85: =((G85-E85)/G85) -> 0.82612913 | I85: =(($E85/(1-I$9))) -> 313.7 | J85: =(($E85/(1-$J$9))) -> 386.09231 | K85: =(($E85/(1-K$9))) -> 501.92
B86: Pressure Transducer Spec. App, Explosion Proof | C86: 1 | D86: P000951TRM | E86: 761.6 | F86: =CEILING((Updated!F86*1.06),0.5) -> 4599 | G86: =F86*$G$5 -> 1701.63 | H86: =((G86-E86)/G86) -> 0.55242914 | I86: =(($E86/(1-I$9))) -> 1904 | J86: =(($E86/(1-$J$9))) -> 2343.3846 | K86: =(($E86/(1-K$9))) -> 3046.4
B88: Design Method Labels
B89: FM Approved for Data Processing Rooms (Engineered) | C89: 0.1 | D89: Z519889LBL | E89: 5.23 | F89: =CEILING((Updated!F89*1.06),0.5) -> 58.5 | G89: =F89*$G$5 -> 21.645 | H89: =((G89-E89)/G89) -> 0.75837376 | I89: =(($E89/(1-I$9))) -> 13.075 | J89: =(($E89/(1-$J$9))) -> 16.092308 | K89: =(($E89/(1-K$9))) -> 20.92
B90: FM Approved for Turbine and Machine Spaces | C90: 0.1 | D90: Z519890LBL | E90: 5.23 | F90: =CEILING((Updated!F90*1.06),0.5) -> 58.5 | G90: =F90*$G$5 -> 21.645 | H90: =((G90-E90)/G90) -> 0.75837376 | I90: =(($E90/(1-I$9))) -> 13.075 | J90: =(($E90/(1-$J$9))) -> 16.092308 | K90: =(($E90/(1-K$9))) -> 20.92
B91: FM Approved for Wet Benches | C91: 0.1 | D91: Z519891LBL | E91: 5.23 | F91: =CEILING((Updated!F91*1.06),0.5) -> 58.5 | G91: =F91*$G$5 -> 21.645 | H91: =((G91-E91)/G91) -> 0.75837376 | I91: =(($E91/(1-I$9))) -> 13.075 | J91: =(($E91/(1-$J$9))) -> 16.092308 | K91: =(($E91/(1-K$9))) -> 20.92
A92: NEW | B92: FM Approved for Data Processing Rooms (Pre-Engineered) | C92: 0.1 | D92: Z521073LBL | E92: 6.42 | F92: =CEILING((Updated!F92*1.06),0.5) -> 58.5 | G92: =F92*$G$5 -> 21.645 | H92: =((G92-E92)/G92) -> 0.7033957 | I92: =(($E92/(1-I$9))) -> 16.05 | J92: =(($E92/(1-$J$9))) -> 19.753846 | K92: =(($E92/(1-K$9))) -> 25.68
B93: Performance Based Designs | C93: 0.1 | D93: Z519892LBL | E93: 6.42 | F93: =CEILING((Updated!F93*1.06),0.5) -> 58.5 | G93: =F93*$G$5 -> 21.645 | H93: =((G93-E93)/G93) -> 0.7033957 | I93: =(($E93/(1-I$9))) -> 16.05 | J93: =(($E93/(1-$J$9))) -> 19.753846 | K93: =(($E93/(1-K$9))) -> 25.68
B94: Note: Each panel requires a design method label. Design method labels are sold separately.
B95: Nitrogen Supply
B96: Relief Valves
B97: Fluid to Zone Piping Relief Valve .85 Orifice 11/2” | C97: 12 | D97: S010951RLV | E97: 288.17 | F97: =CEILING((Updated!F97*1.06),0.5) -> 6529 | G97: =F97*$G$5 -> 2415.73 | H97: =((G97-E97)/G97) -> 0.88071101 | I97: =(($E97/(1-I$9))) -> 720.425 | J97: =(($E97/(1-$J$9))) -> 886.67692 | K97: =(($E97/(1-K$9))) -> 1152.68
B98: Fluid to Zone Piping Relief Valve 1.39 Orifice 2” | C98: 12 | D98: S020951RLV | E98: 369.04 | F98: =CEILING((Updated!F98*1.06),0.5) -> 6728.5 | G98: =F98*$G$5 -> 2489.545 | H98: =((G98-E98)/G98) -> 0.85176408 | I98: =(($E98/(1-I$9))) -> 922.6 | J98: =(($E98/(1-$J$9))) -> 1135.5077 | K98: =(($E98/(1-K$9))) -> 1476.16
B100: Cylinders
B101: Victaulic Vortex Nitrogen Cylinder, 80L, w/Valve, Filled | C101: 320 | D101: S000950A01 | E101: 851.09 | F101: =CEILING((Updated!F101*1.06),0.5) -> 6096.5 | G101: =F101*$G$5 -> 2255.705 | H101: =((G101-E101)/G101) -> 0.62269446 | I101: =(($E101/(1-I$9))) -> 2127.725 | J101: =(($E101/(1-$J$9))) -> 2618.7385 | K101: =(($E101/(1-K$9))) -> 3404.36
B102: Victaulic Vortex Nitrogen Cylinder, 49L, w/Valve, Filled | C102: 134 | D102: S000950A02 | E102: 341.67 | F102: =CEILING((Updated!F102*1.06),0.5) -> 2447.5 | G102: =F102*$G$5 -> 905.575 | H102: =((G102-E102)/G102) -> 0.62270381 | I102: =(($E102/(1-I$9))) -> 854.175 | J102: =(($E102/(1-$J$9))) -> 1051.2923 | K102: =(($E102/(1-K$9))) -> 1366.68
B104: Discharge Hose Kits and Accessories
B105: 80L Cylinder Primary Pilot Kit | C105: 5 | D105: S0009500PP | E105: 551.3426 | F105: =CEILING((Updated!F107*1.06),0.5) -> 6775 | G105: =F105*$G$5 -> 2506.75 | H105: =((G105-E105)/G105) -> 0.78005681 | I105: =(($E105/(1-I$9))) -> 1378.3565 | J105: =(($E105/(1-$J$9))) -> 1696.4388 | K105: =(($E105/(1-K$9))) -> 2205.3704
B106: 80L Cylinder Secondary Kit, With Gauge | C106: 2 | D106: S0009500SP | E106: 130.0367 | F106: =CEILING((Updated!F108*1.06),0.5) -> 1604 | G106: =F106*$G$5 -> 593.48 | H106: =((G106-E106)/G106) -> 0.78089118 | I106: =(($E106/(1-I$9))) -> 325.09175 | J106: =(($E106/(1-$J$9))) -> 400.11292 | K106: =(($E106/(1-K$9))) -> 520.1468
B107: 80L Cylinder Secondary Pilot Kit, With Gauge and Pressure Switch | C107: 2 | D107: S000950PSP | E107: 136.3425 | F107: =CEILING((Updated!F109*1.06),0.5) -> 2497 | G107: =F107*$G$5 -> 923.89 | H107: =((G107-E107)/G107) -> 0.85242561 | I107: =(($E107/(1-I$9))) -> 340.85625 | J107: =(($E107/(1-$J$9))) -> 419.51538 | K107: =(($E107/(1-K$9))) -> 545.37
A108: NEW | B108: 49L CYLINDER PRIMARY PILOT KIT | C108: 5 | D108: S4909500PP | E108: 550.49 | F108: =CEILING((Updated!F110*1.06),0.5) -> 3154.5 | G108: =F108*$G$5 -> 1167.165 | H108: =((G108-E108)/G108) -> 0.52835289 | I108: =(($E108/(1-I$9))) -> 1376.225 | J108: =(($E108/(1-$J$9))) -> 1693.8154 | K108: =(($E108/(1-K$9))) -> 2201.96
A109: NEW | B109: 49L CYLINDER SECONDARY KIT WITH GAUGE | C109: 2 | D109: S4909500SP | E109: 133.22 | F109: =CEILING((Updated!F111*1.06),0.5) -> 763.5 | G109: =F109*$G$5 -> 282.495 | H109: =((G109-E109)/G109) -> 0.52841643 | I109: =(($E109/(1-I$9))) -> 333.05 | J109: =(($E109/(1-$J$9))) -> 409.90769 | K109: =(($E109/(1-K$9))) -> 532.88
B110: 1/4” Pilot Hose, 700 MM, for joining rows in double stacked racks | C110: 1 | D110: S000950P70 | E110: 8.3373 | F110: =CEILING((Updated!F112*1.06),0.5) -> 158.5 | G110: =F110*$G$5 -> 58.645 | H110: =((G110-E110)/G110) -> 0.85783443 | I110: =(($E110/(1-I$9))) -> 20.84325 | J110: =(($E110/(1-$J$9))) -> 25.653231 | K110: =(($E110/(1-K$9))) -> 33.3492
B111: 1/4” Pilot Hose, 500 MM, for joining adjacent racks | C111: 1 | D111: S000950P50 | E111: 6.9395 | F111: =CEILING((Updated!F113*1.06),0.5) -> 134.5 | G111: =F111*$G$5 -> 49.765 | H111: =((G111-E111)/G111) -> 0.86055461 | I111: =(($E111/(1-I$9))) -> 17.34875 | J111: =(($E111/(1-$J$9))) -> 21.352308 | K111: =(($E111/(1-K$9))) -> 27.758
B112: Vortex Single Cylinder Refill Adapter, CGA-580 Inlet | C112: 1 | D112: S002950000 | E112: 48.1468 | F112: =CEILING((Updated!F114*1.06),0.5) -> 802.5 | G112: =F112*$G$5 -> 296.925 | H112: =((G112-E112)/G112) -> 0.83784861 | I112: =(($E112/(1-I$9))) -> 120.367 | J112: =(($E112/(1-$J$9))) -> 148.144 | K112: =(($E112/(1-K$9))) -> 192.5872
B113: Vortex Single Cylinder Refill Adapter, CGA-677 Inlet | C113: 1 | D113: S002950401 | E113: 89.8868 | F113: =CEILING((Updated!F115*1.06),0.5) -> 802.5 | G113: =F113*$G$5 -> 296.925 | H113: =((G113-E113)/G113) -> 0.6972744 | I113: =(($E113/(1-I$9))) -> 224.717 | J113: =(($E113/(1-$J$9))) -> 276.57477 | K113: =(($E113/(1-K$9))) -> 359.5472
B114: In Place Bulk Cylinder Refill Kit, 1” NPT Inlet | C114: 20 | D114: S000950015 | E114: 768.69 | F114: =CEILING((Updated!F116*1.06),0.5) -> 6846.5 | G114: =F114*$G$5 -> 2533.205 | H114: =((G114-E114)/G114) -> 0.69655436 | I114: =(($E114/(1-I$9))) -> 1921.725 | J114: =(($E114/(1-$J$9))) -> 2365.2 | K114: =(($E114/(1-K$9))) -> 3074.76
...

Sheet Updated
B1: Victaulic Vortex® System Product List Price Effective May 2024
B2: United States
G4: Multiplier:
B5: NOTE: Please add information to the cells shaded in | C5: GREEN. | G5: 0.37
B7: Option Style | C7: Shipping Weight | D7: Part Code | E7: Cost (USD) | F7: List Price (USD) | G7: Extended Price | H7: GM % | I7: 60% Margin Sell | J7: 67.5% Margin Sell | K7: 75% Margin Sell
B9: Emitters | I9: 0.6 | J9: 0.675 | K9: 0.75
B10: 1/8" Emitters
B11: 1/8” Emitter, 954 cavity foil, standard, PVDF, 3/8” FPT, 1/8” FPT | C11: 1 | D11: S003953105 | E11: 195.71 | F11: =CEILING((Master!F13*1.06),0.5) -> 2817 | G11: =F11*$G$5 -> 1042.29 | H11: =((G11-E11)/G11) -> 0.81223076 | I11: =(($E11/(1-$I9))) -> 489.275 | J11: =(($E11/(1-$J$9))) -> 602.18462 | K11: =(($E11/(1-$K9))) -> 782.84
B12: 1/8” Emitter, 953 dome foil, standard, stainless, 3/8” FPT, 1/8” FPT | C12: 1 | D12: S00195310X | E12: 171.534 | F12: =CEILING((Master!F14*1.06),0.5) -> 2711.5 | G12: =F12*$G$5 -> 1003.255 | H12: =((G12-E12)/G12) -> 0.82902253 | I12: =(($E12/(1-$I$9))) -> 428.835 | J12: =(($E12/(1-$J$9))) -> 527.79692 | K12: =(($E12/(1-$K$9))) -> 686.136
B13: 1/4" Emitters
B14: 1/4” Emitter, 953 dome foil, standard, stainless, 3/4” MPT, 1/4” FPT | C14: 1 | D14: S002953X02 | E14: 160.1174 | F14: =CEILING((Master!F16*1.06),0.5) -> 3144 | G14: =F14*$G$5 -> 1163.28 | H14: =((G14-E14)/G14) -> 0.86235696 | I14: =(($E14/(1-I$9))) -> 400.2935 | J14: =(($E14/(1-$J$9))) -> 492.66892 | K14: =(($E14/(1-K$9))) -> 640.4696
B15: 1/4” Emitter, 954 cavity foil, standard, PVDF, 3/8” FPT, 1/8” FPT | C15: 1 | D15: S003953170 | E15: 241.4136 | F15: =CEILING((Master!F18*1.06),0.5) -> 2816.5 | G15: =F15*$G$5 -> 1042.105 | H15: =((G15-E15)/G15) -> 0.76834043 | I15: =(($E15/(1-$I$9))) -> 603.534 | J15: =(($E15/(1-$J$9))) -> 742.81108 | K15: =(($E15/(1-$K$9))) -> 965.6544
B16: 3/8" Emitters
B17: 3/8” Emitter, 953 dome foil, escutcheon, stainless, 3/4” FPT, 1/4” FPT | C17: 1 | D17: S003953032 | E17: 52.3201 | F17: 1257 | G17: =F17*$G$5 -> 465.09 | H17: =((G17-E17)/G17) -> 0.88750543 | I17: =(($E17/(1-I$9))) -> 130.80025 | J17: =(($E17/(1-$J$9))) -> 160.98492 | K17: =(($E17/(1-K$9))) -> 209.2804
B18: 3/8” Emitter, 953 dome foil, standard, stainless, 3/4” FPT, 1/4” FPT | C18: 1 | D18: S003953034 | E18: 34.5438 | F18: 1191 | G18: =F18*$G$5 -> 440.67 | H18: =((G18-E18)/G18) -> 0.92161073 | I18: =(($E18/(1-I$9))) -> 86.3595 | J18: =(($E18/(1-$J$9))) -> 106.28862 | K18: =(($E18/(1-K$9))) -> 138.1752
B19: 3/8” Emitter, 954 cavity foil, escutcheon, stainless, 3/4” FPT, 1/4” FPT | C19: 1 | D19: S003953031 | E19: 51.85424 | F19: 1257 | G19: =F19*$G$5 -> 465.09 | H19: =((G19-E19)/G19) -> 0.88850708 | I19: =(($E19/(1-I$9))) -> 129.6356 | J19: =(($E19/(1-$J$9))) -> 159.55151 | K19: =(($E19/(1-K$9))) -> 207.41696
B20: 3/8” Emitter, 954 cavity foil, standard, stainless, 3/4” FPT, 1/4” FPT | C20: 1 | D20: S003953033 | E20: 34.07794 | F20: 1191 | G20: =F20*$G$5 -> 440.67 | H20: =((G20-E20)/G20) -> 0.92266789 | I20: =(($E20/(1-I$9))) -> 85.19485 | J20: =(($E20/(1-$J$9))) -> 104.8552 | K20: =(($E20/(1-K$9))) -> 136.31176
B21: 1/2" Emitters
B22: 1/2” Emitter, 953 dome foil, standard, brass, 3/4” MPT, 1/4” FPT | C22: 1 | D22: S006953400 | E22: 102.34866 | F22: =CEILING((Master!F33*1.06),0.5) -> 1191 | G22: =F22*$G$5 -> 440.67 | H22: =((G22-E22)/G22) -> 0.76774307 | I22: =(($E22/(1-I$9))) -> 255.87165 | J22: =(($E22/(1-$J$9))) -> 314.91895 | K22: =(($E22/(1-K$9))) -> 409.39464
B23: 1/2” Emitter, 953 dome foil, standard, PVDF, 3/4” MPT, 1/4” FPT | C23: 1 | D23: S006953406 | E23: 230.5925 | F23: =CEILING((Master!F35*1.06),0.5) -> 2212 | G23: =F23*$G$5 -> 818.44 | H23: =((G23-E23)/G23) -> 0.71825363 | I23: =(($E23/(1-I$9))) -> 576.48125 | J23: =(($E23/(1-$J$9))) -> 709.51538 | K23: =(($E23/(1-K$9))) -> 922.37
B24: 1/2” Emitter, 953 dome foil, escutcheon, stainless, 3/4” FPT, 1/4” FPT | C24: 1 | D24: S004953511 | E24: 60.22 | F24: 1257 | G24: =F24*$G$5 -> 465.09 | H24: =((G24-E24)/G24) -> 0.87051968 | I24: =(($E24/(1-I$9))) -> 150.55 | J24: =(($E24/(1-$J$9))) -> 185.29231 | K24: =(($E24/(1-K$9))) -> 240.88
B25: 1/2” Emitter, 953 dome foil, standard, stainless, 3/4” FPT, 1/4” FPT | C25: 1 | D25: S004953513 | E25: 35.2038 | F25: 1659 | G25: =F25*$G$5 -> 613.83 | H25: =((G25-E25)/G25) -> 0.94264894 | I25: =(($E25/(1-I$9))) -> 88.0095 | J25: =(($E25/(1-$J$9))) -> 108.31938 | K25: =(($E25/(1-K$9))) -> 140.8152
B26: 5/8" Emitters
B27: 5/8” Emitter, 954 cavity foil, standard, PVDF, 3/4” FPT, 1/4" FPT | C27: 1 | D27: S006953503 | E27: 193.3368 | F27: =CEILING((Master!F41*1.06),0.5) -> 2817 | G27: =F27*$G$5 -> 1042.29 | H27: =((G27-E27)/G27) -> 0.81450767 | I27: =(($E27/(1-I$9))) -> 483.342 | J27: =(($E27/(1-$J$9))) -> 594.88246 | K27: =(($E27/(1-K$9))) -> 773.3472
B28: 5/8” Emitter, 954 cavity foil, escutcheon, stainless, 3/4” FPT, 1/4” FPT | C28: 1 | D28: S006953512 | E28: 50.4801 | F28: 1257 | G28: =F28*$G$5 -> 465.09 | H28: =((G28-E28)/G28) -> 0.89146165 | I28: =(($E28/(1-I$9))) -> 126.20025 | J28: =(($E28/(1-$J$9))) -> 155.32338 | K28: =(($E28/(1-K$9))) -> 201.9204
B29: 5/8” Emitter, 954 cavity foil, standard, stainless, 3/4” FPT, 1/4” FPT | C29: 1 | D29: S006953514 | E29: 32.7038 | F29: 1191 | G29: =F29*$G$5 -> 440.67 | H29: =((G29-E29)/G29) -> 0.92578619 | I29: =(($E29/(1-I$9))) -> 81.7595 | J29: =(($E29/(1-$J$9))) -> 100.62708 | K29: =(($E29/(1-K$9))) -> 130.8152
B30: 1" Emitters
B31: 1” Emitter, 953/954 dome foil, escutcheon, stainless, 1” FPT, 1/8” FPT | C31: 1 | D31: S010953511 | E31: 68.4904 | F31: 2185 | G31: =F31*$G$5 -> 808.45 | H31: =((G31-E31)/G31) -> 0.91528184 | I31: =(($E31/(1-I$9))) -> 171.226 | J31: =(($E31/(1-$J$9))) -> 210.73969 | K31: =(($E31/(1-K$9))) -> 273.9616
B33: Water Flow Kits (Strainer, Flow Cartridge, Emitter Trim Kit)
B34: Water Flow Cartridge Kit, .13 GPM, Brass, 3/4” NPT | C34: 1 | D34: K000953013 | E34: 103.42 | F34: =CEILING((Master!F51*1.06),0.5) -> 1235.5 | G34: =F34*$G$5 -> 457.135 | H34: =((G34-E34)/G34) -> 0.77376486 | I34: =(($E34/(1-I$9))) -> 258.55 | J34: =(($E34/(1-$J$9))) -> 318.21538 | K34: =(($E34/(1-K$9))) -> 413.68
B35: Water Flow Cartridge Kit, .13 GPM, Stainless, 3/4” NPT | C35: 1 | D35: K000953X13 | E35: 133.39 | F35: =CEILING((Master!F52*1.06),0.5) -> 1468 | G35: =F35*$G$5 -> 543.16 | H35: =((G35-E35)/G35) -> 0.75441859 | I35: =(($E35/(1-I$9))) -> 333.475 | J35: =(($E35/(1-$J$9))) -> 410.43077 | K35: =(($E35/(1-K$9))) -> 533.56
B36: Water Flow Cartridge Kit, .26 GPM, Brass, 3/4” NPT | C36: 1 | D36: K000953026 | E36: 109.44 | F36: =CEILING((Master!F53*1.06),0.5) -> 1235.5 | G36: =F36*$G$5 -> 457.135 | H36: =((G36-E36)/G36) -> 0.76059589 | I36: =(($E36/(1-I$9))) -> 273.6 | J36: =(($E36/(1-$J$9))) -> 336.73846 | K36: =(($E36/(1-K$9))) -> 437.76
B37: Water Flow Cartridge Kit, .26 GPM, Stainless, 3/4” NPT | C37: 1 | D37: K000953X26 | E37: 133.39 | F37: =CEILING((Master!F54*1.06),0.5) -> 1468 | G37: =F37*$G$5 -> 543.16 | H37: =((G37-E37)/G37) -> 0.75441859 | I37: =(($E37/(1-I$9))) -> 333.475 | J37: =(($E37/(1-$J$9))) -> 410.43077 | K37: =(($E37/(1-K$9))) -> 533.56
B38: Water Flow Cartridge Kit, .53 GPM, Brass, 3/4” NPT | C38: 1 | D38: K000953053 | E38: 103.42 | F38: =CEILING((Master!F55*1.06),0.5) -> 1235.5 | G38: =F38*$G$5 -> 457.135 | H38: =((G38-E38)/G38) -> 0.77376486 | I38: =(($E38/(1-I$9))) -> 258.55 | J38: =(($E38/(1-$J$9))) -> 318.21538 | K38: =(($E38/(1-K$9))) -> 413.68
B39: Water Flow Cartridge Kit, .53 GPM, Stainless, 3/4” NPT | C39: 1 | D39: K000953X53 | E39: 135.51 | F39: =CEILING((Master!F56*1.06),0.5) -> 1468 | G39: =F39*$G$5 -> 543.16 | H39: =((G39-E39)/G39) -> 0.7505155 | I39: =(($E39/(1-I$9))) -> 338.775 | J39: =(($E39/(1-$J$9))) -> 416.95385 | K39: =(($E39/(1-K$9))) -> 542.04
B40: Water Flow Cartridge Kit, .79 GPM, Brass, 3/4” NPT | C40: 1 | D40: K000953079 | E40: 103.42 | F40: =CEILING((Master!F57*1.06),0.5) -> 1235.5 | G40: =F40*$G$5 -> 457.135 | H40: =((G40-E40)/G40) -> 0.77376486 | I40: =(($E40/(1-I$9))) -> 258.55 | J40: =(($E40/(1-$J$9))) -> 318.21538 | K40: =(($E40/(1-K$9))) -> 413.68
B41: Water Flow Cartridge Kit, .79 GPM, Stainless, 3/4” NPT | C41: 1 | D41: K000953X79 | E41: 135.51 | F41: =CEILING((Master!F58*1.06),0.5) -> 1468 | G41: =F41*$G$5 -> 543.16 | H41: =((G41-E41)/G41) -> 0.7505155 | I41: =(($E41/(1-I$9))) -> 338.775 | J41: =(($E41/(1-$J$9))) -> 416.95385 | K41: =(($E41/(1-K$9))) -> 542.04
B42: Water Flow Cartridge Kit, 1.06 GPM, Brass, 3/4” NPT | C42: 1 | D42: K000953106 | E42: 103.42 | F42: =CEILING((Master!F59*1.06),0.5) -> 1235.5 | G42: =F42*$G$5 -> 457.135 | H42: =((G42-E42)/G42) -> 0.77376486 | I42: =(($E42/(1-I$9))) -> 258.55 | J42: =(($E42/(1-$J$9))) -> 318.21538 | K42: =(($E42/(1-K$9))) -> 413.68
B43: Water Flow Cartridge Kit, 1.06 GPM, Stainless, 3/4” NPT | C43: 1 | D43: K000953X06 | E43: 135.51 | F43: =CEILING((Master!F60*1.06),0.5) -> 1468 | G43: =F43*$G$5 -> 543.16 | H43: =((G43-E43)/G43) -> 0.7505155 | I43: =(($E43/(1-I$9))) -> 338.775 | J43: =(($E43/(1-$J$9))) -> 416.95385 | K43: =(($E43/(1-K$9))) -> 542.04
B44: Water Flow Cartridge Kit, 1.59 GPM, Brass, 3/4” NPT | C44: 1 | D44: K000953153 | E44: 114.8635 | F44: 1235.5 | G44: =F44*$G$5 -> 457.135 | H44: =((G44-E44)/G44) -> 0.74873178 | I44: =(($E44/(1-I$9))) -> 287.15875 | J44: =(($E44/(1-$J$9))) -> 353.42615 | K44: =(($E44/(1-K$9))) -> 459.454
B45: Water Flow Cartridge Kit, 1.59 GPM, Stainless, 3/4” NPT | C45: 1 | D45: K00095315X | E45: 148.8035 | F45: 1468 | G45: =F45*$G$5 -> 543.16 | H45: =((G45-E45)/G45) -> 0.72604113 | I45: =(($E45/(1-I$9))) -> 372.00875 | J45: =(($E45/(1-$J$9))) -> 457.85692 | K45: =(($E45/(1-K$9))) -> 595.214
B46: Water Flow Cartridge Kit, 2.11 GPM, Brass, 3/4” NPT | C46: 1 | D46: K000953211 | E46: 114.8635 | F46: 1235.5 | G46: =F46*$G$5 -> 457.135 | H46: =((G46-E46)/G46) -> 0.74873178 | I46: =(($E46/(1-I$9))) -> 287.15875 | J46: =(($E46/(1-$J$9))) -> 353.42615 | K46: =(($E46/(1-K$9))) -> 459.454
B47: Water Flow Cartridge Kit, 2.11 GPM, Stainless, 3/4” NPT | C47: 1 | D47: K000953X11 | E47: 148.8035 | F47: 1468 | G47: =F47*$G$5 -> 543.16 | H47: =((G47-E47)/G47) -> 0.72604113 | I47: =(($E47/(1-I$9))) -> 372.00875 | J47: =(($E47/(1-$J$9))) -> 457.85692 | K47: =(($E47/(1-K$9))) -> 595.214
B48: Water Flow Cartridge Kit, 4.23 GPM, Brass, 3/4” NPT | C48: 1 | D48: K000953423 | E48: 114.8635 | F48: 1235.5 | G48: =F48*$G$5 -> 457.135 | H48: =((G48-E48)/G48) -> 0.74873178 | I48: =(($E48/(1-I$9))) -> 287.15875 | J48: =(($E48/(1-$J$9))) -> 353.42615 | K48: =(($E48/(1-K$9))) -> 459.454
B49: Water Flow Cartridge Kit, 4.23 GPM, Stainless, 3/4” NPT | C49: 1 | D49: K000953X23 | E49: 148.8035 | F49: 1468 | G49: =F49*$G$5 -> 543.16 | H49: =((G49-E49)/G49) -> 0.72604113 | I49: =(($E49/(1-I$9))) -> 372.00875 | J49: =(($E49/(1-$J$9))) -> 457.85692 | K49: =(($E49/(1-K$9))) -> 595.214
B51: Components
B52: 1/4" MNPT x 7/16-20 Male JIC Straight adapter, brass | C52: 0.1 | D52: PAY7000C01 | E52: 4.26 | F52: =CEILING((Master!F63*1.06),0.5) -> 22.5 | G52: =F52*$G$5 -> 8.325 | H52: =((G52-E52)/G52) -> 0.48828829 | I52: =(($E52/(1-I$9))) -> 10.65 | J52: =(($E52/(1-$J$9))) -> 13.107692 | K52: =(($E52/(1-K$9))) -> 17.04
B53: 7/16-20 Female JIC x 31” PTFE lined braided stainless hose, 1/4” ID | C53: 0.4 | D53: P310955228 | E53: 67.5127 | F53: =CEILING((Master!F64*1.06),0.5) -> 374.5 | G53: =F53*$G$5 -> 138.565 | H53: =((G53-E53)/G53) -> 0.51277235 | I53: =(($E53/(1-I$9))) -> 168.78175 | J53: =(($E53/(1-$J$9))) -> 207.73138 | K53: =(($E53/(1-K$9))) -> 270.0508
B54: 7/16-20 Female JIC x 36” PTFE lined braided stainless hose, 1/4” ID | C54: 0.4 | D54: P360955228 | E54: 76.17 | F54: =CEILING((Master!F65*1.06),0.5) -> 563 | G54: =F54*$G$5 -> 208.31 | H54: =((G54-E54)/G54) -> 0.63434305 | I54: =(($E54/(1-I$9))) -> 190.425 | J54: =(($E54/(1-$J$9))) -> 234.36923 | K54: =(($E54/(1-K$9))) -> 304.68
B55: 7/16-20 Female JIC x 48” PTFE lined braided stainless hose, 1/4” ID | C55: 1 | D55: P480955228 | E55: 107.544 | F55: =CEILING((Master!F66*1.06),0.5) -> 654.5 | G55: =F55*$G$5 -> 242.165 | H55: =((G55-E55)/G55) -> 0.5559061 | I55: =(($E55/(1-I$9))) -> 268.86 | J55: =(($E55/(1-$J$9))) -> 330.90462 | K55: =(($E55/(1-K$9))) -> 430.176
B56: 1/4" MNPT x 7/16-20 Male JIC 90 degree adapter, brass | C56: 0.1 | D56: PAY0955001 | E56: 1.13 | F56: =CEILING((Master!F67*1.06),0.5) -> 8.5 | G56: =F56*$G$5 -> 3.145 | H56: =((G56-E56)/G56) -> 0.64069952 | I56: =(($E56/(1-I$9))) -> 2.825 | J56: =(($E56/(1-$J$9))) -> 3.4769231 | K56: =(($E56/(1-K$9))) -> 4.52
B57: 1/4" NPT x 3/8" OD compression, 90 degree adapter, brass | C57: 0.1 | D57: SY45953001 | E57: 2.92 | F57: =CEILING((Master!F68*1.06),0.5) -> 22.5 | G57: =F57*$G$5 -> 8.325 | H57: =((G57-E57)/G57) -> 0.64924925 | I57: =(($E57/(1-I$9))) -> 7.3 | J57: =(($E57/(1-$J$9))) -> 8.9846154 | K57: =(($E57/(1-K$9))) -> 11.68
B58: 1/4" NPT x 3/8" OD compression, straight adapter, brass | C58: 0.1 | D58: SY45953002 | E58: 2.19 | F58: =CEILING((Master!F69*1.06),0.5) -> 17 | G58: =F58*$G$5 -> 6.29 | H58: =((G58-E58)/G58) -> 0.6518283 | I58: =(($E58/(1-I$9))) -> 5.475 | J58: =(($E58/(1-$J$9))) -> 6.7384615 | K58: =(($E58/(1-K$9))) -> 8.76
B60: Vortex Panels
B61: Combination Panels
B62: 1"
B63: 1” 951 Combination Panel, Dry Contact, Ball Valve | C63: 170 | D63: S010951DRY | E63: 3997.8518 | F63: =CEILING((K63/G5),0.5) -> 43220.5 | G63: =F63*$G$5 -> 15991.585 | H63: =((G63-E63)/G63) -> 0.75000278 | I63: =(($E63/(1-I$9))) -> 9994.6294 | J63: =(($E63/(1-$J$9))) -> 12301.082 | K63: =(($E63/(1-K$9))) -> 15991.407
B64: 1” 951 Combination Panel, Active Release, Ball Valve | C64: 170 | D64: S010951ACT | E64: 4014.89 | F64: =CEILING((K64/G5),0.5) -> 43404.5 | G64: =F64*$G$5 -> 16059.665 | H64: =((G64-E64)/G64) -> 0.75000163 | I64: =(($E64/(1-I$9))) -> 10037.225 | J64: =(($E64/(1-$J$9))) -> 12353.508 | K64: =(($E64/(1-K$9))) -> 16059.56
B65: 1.5"
B66: 1.5” 951 Combination Panel, Dry Contact, Ball Valve | C66: 180 | D66: S014951DRY | E66: 4207.94 | F66: =CEILING((K66/G$5),0.5) -> 45491.5 | G66: =F66*$G$5 -> 16831.855 | H66: =((G66-E66)/G66) -> 0.75000141 | I66: =(($E66/(1-I$9))) -> 10519.85 | J66: =(($E66/(1-$J$9))) -> 12947.508 | K66: =(($E66/(1-K$9))) -> 16831.76
B67: 1.5” 951 Combination Panel, Active Release, Ball Valve | C67: 180 | D67: S014951ACT | E67: 4208.44 | F67: =CEILING((K67/G$5),0.5) -> 45497 | G67: =F67*$G$5 -> 16833.89 | H67: =((G67-E67)/G67) -> 0.75000193 | I67: =(($E67/(1-I$9))) -> 10521.1 | J67: =(($E67/(1-$J$9))) -> 12949.046 | K67: =(($E67/(1-K$9))) -> 16833.76
B68: * Please note each Combination Panels requires a pressure transducer to be ordered separately. Reference spare parts section for pressure transducer selection.
B70: Fluid Panels
B71: 1"
B72: 1” 951 Fluid Panel, Dry Contact | C72: 130 | D72: S010951F00 | E72: 2813.51 | F72: =CEILING((K72/G$5),0.5) -> 30416.5 | G72: =F72*$G$5 -> 11254.105 | H72: =((G72-E72)/G72) -> 0.75000144 | I72: =(($E72/(1-I$9))) -> 7033.775 | J72: =(($E72/(1-$J$9))) -> 8656.9538 | K72: =(($E72/(1-K$9))) -> 11254.04
B73: 1” 951 Fluid Panel, Active Release | C73: 130 | D73: S010951FA0 | E73: 3016.09 | F73: =CEILING((K73/G$5),0.5) -> 32606.5 | G73: =F73*$G$5 -> 12064.405 | H73: =((G73-E73)/G73) -> 0.75000093 | I73: =(($E73/(1-I$9))) -> 7540.225 | J73: =(($E73/(1-$J$9))) -> 9280.2769 | K73: =(($E73/(1-K$9))) -> 12064.36
B74: 1.5"
B75: 1.5” 951 Fluid Panel, Dry Contact | C75: 140 | D75: S014951F00 | E75: 3007.06 | F75: =CEILING((K75/G$5),0.5) -> 32509 | G75: =F75*$G$5 -> 12028.33 | H75: =((G75-E75)/G75) -> 0.75000187 | I75: =(($E75/(1-I$9))) -> 7517.65 | J75: =(($E75/(1-$J$9))) -> 9252.4923 | K75: =(($E75/(1-K$9))) -> 12028.24
B76: 1.5” 951 Fluid Panel, Active Release | C76: 140 | D76: S014951FA0 | E76: 3105.65 | F76: =CEILING((K76/G$5),0.5) -> 33575 | G76: =F76*$G$5 -> 12422.75 | H76: =((G76-E76)/G76) -> 0.75000302 | I76: =(($E76/(1-I$9))) -> 7764.125 | J76: =(($E76/(1-$J$9))) -> 9555.8462 | K76: =(($E76/(1-K$9))) -> 12422.6
B77: *Please note that each Fluid Panel requires a pressure transducer to be ordered separately. Reference spare parts section for pressure transducer selection.
B79: Zone Panels
B80: 1.5"
B81: 1.5” 951 Zone Panel, Dry Contact, Ball Valve | C81: 150 | D81: S01495110A | E81: 2114.93 | F81: =CEILING((K81/G$5),0.5) -> 22864.5 | G81: =F81*$G$5 -> 8459.865 | H81: =((G81-E81)/G81) -> 0.75000428 | I81: =(($E81/(1-I$9))) -> 5287.325 | J81: =(($E81/(1-$J$9))) -> 6507.4769 | K81: =(($E81/(1-K$9))) -> 8459.72
B82: 2"
B83: 2” 951 Zone Panel, Dry Contact, Ball Valve | C83: 150 | D83: S02095110A | E83: 2433.5 | F83: =CEILING((K83/G$5),0.5) -> 26308.5 | G83: =F83*$G$5 -> 9734.145 | H83: =((G83-E83)/G83) -> 0.75000372 | I83: =(($E83/(1-I$9))) -> 6083.75 | J83: =(($E83/(1-$J$9))) -> 7487.6923 | K83: =(($E83/(1-K$9))) -> 9734
B84: Pressure Transducers
B85: Pressure Transducer, Standard, 0-100 psi | C85: 1 | D85: P000951134 | E85: 125.48 | F85: =CEILING((Master!F116*1.06),0.5) -> 1840 | G85: =F85*$G$5 -> 680.8 | H85: =((G85-E85)/G85) -> 0.81568743 | I85: =(($E85/(1-I$9))) -> 313.7 | J85: =(($E85/(1-$J$9))) -> 386.09231 | K85: =(($E85/(1-K$9))) -> 501.92
B86: Pressure Transducer Spec. App, Explosion Proof | C86: 1 | D86: P000951TRM | E86: 761.6 | F86: =CEILING((Master!F117*1.06),0.5) -> 4338.5 | G86: =F86*$G$5 -> 1605.245 | H86: =((G86-E86)/G86) -> 0.52555529 | I86: =(($E86/(1-I$9))) -> 1904 | J86: =(($E86/(1-$J$9))) -> 2343.3846 | K86: =(($E86/(1-K$9))) -> 3046.4
B88: Design Method Labels
B89: FM Approved for Data Processing Rooms (Engineered) | C89: 0.1 | D89: Z519889LBL | F89: 55 | G89: =F89*$G$5 -> 20.35 | H89: =((G89-E89)/G89) -> 1 | I89: =(($E89/(1-I$9))) -> 0 | J89: =(($E89/(1-$J$9))) -> 0 | K89: =(($E89/(1-K$9))) -> 0
B90: FM Approved for Turbine and Machine Spaces | C90: 0.1 | D90: Z519890LBL | F90: 55 | G90: =F90*$G$5 -> 20.35 | H90: =((G90-E90)/G90) -> 1 | I90: =(($E90/(1-I$9))) -> 0 | J90: =(($E90/(1-$J$9))) -> 0 | K90: =(($E90/(1-K$9))) -> 0
B91: FM Approved for Wet Benches | C91: 0.1 | D91: Z519891LBL | F91: 55 | G91: =F91*$G$5 -> 20.35 | H91: =((G91-E91)/G91) -> 1 | I91: =(($E91/(1-I$9))) -> 0 | J91: =(($E91/(1-$J$9))) -> 0 | K91: =(($E91/(1-K$9))) -> 0
A92: NEW | B92: FM Approved for Data Processing Rooms (Pre-Engineered) | C92: 0.1 | D92: Z521073LBL | F92: 55 | G92: =F92*$G$5 -> 20.35 | H92: =((G92-E92)/G92) -> 1 | I92: =(($E92/(1-I$9))) -> 0 | J92: =(($E92/(1-$J$9))) -> 0 | K92: =(($E92/(1-K$9))) -> 0
B93: Performance Based Designs | C93: 0.1 | D93: Z519892LBL | F93: 55 | G93: =F93*$G$5 -> 20.35 | H93: =((G93-E93)/G93) -> 1 | I93: =(($E93/(1-I$9))) -> 0 | J93: =(($E93/(1-$J$9))) -> 0 | K93: =(($E93/(1-K$9))) -> 0
B94: Note: Each panel requires a design method label. Design method labels are sold separately.
B95: Nitrogen Supply
B96: Relief Valves
B97: Fluid to Zone Piping Relief Valve .85 Orifice 11/2” | C97: 12 | D97: S010951RLV | E97: 288.17 | F97: =CEILING((Master!F121*1.06),0.5) -> 6159 | G97: =F97*$G$5 -> 2278.83 | H97: =((G97-E97)/G97) -> 0.87354476 | I97: =(($E97/(1-I$9))) -> 720.425 | J97: =(($E97/(1-$J$9))) -> 886.67692 | K97: =(($E97/(1-K$9))) -> 1152.68
B98: Fluid to Zone Piping Relief Valve 1.39 Orifice 2” | C98: 12 | D98: S020951RLV | E98: 369.04 | F98: =CEILING((Master!F122*1.06),0.5) -> 6347.5 | G98: =F98*$G$5 -> 2348.575 | H98: =((G98-E98)/G98) -> 0.84286642 | I98: =(($E98/(1-I$9))) -> 922.6 | J98: =(($E98/(1-$J$9))) -> 1135.5077 | K98: =(($E98/(1-K$9))) -> 1476.16
B100: Cylinders
B101: Victaulic Vortex Nitrogen Cylinder, 80L, w/Valve, Filled | C101: 320 | D101: S000950A01 | E101: 851.09 | F101: =CEILING((I101/0.37),0.5) -> 5751 | G101: =F101*$G$5 -> 2127.87 | H101: =((G101-E101)/G101) -> 0.60002726 | I101: =(($E101/(1-I$9))) -> 2127.725 | J101: =(($E101/(1-$J$9))) -> 2618.7385 | K101: =(($E101/(1-K$9))) -> 3404.36
B102: Victaulic Vortex Nitrogen Cylinder, 49L, w/Valve, Filled | C102: 134 | D102: S000950A02 | E102: 341.67 | F102: 2308.5 | G102: =F102*$G$5 -> 854.145 | H102: =((G102-E102)/G102) -> 0.59998595 | I102: =(($E102/(1-I$9))) -> 854.175 | J102: =(($E102/(1-$J$9))) -> 1051.2923 | K102: =(($E102/(1-K$9))) -> 1366.68
B103: Victaulic Vortex Nitrogen Cylinder, 80L, w/Valve, Filled | C103: 320 | D103: PE-S000950A01 | E103: 851.09 | F103: =CEILING((I103/0.37),0.5) -> 5000 | G103: =F103*$G$5 -> 1850 | H103: =((G103-E103)/G103) -> 0.53995135 | I103: 1850 | J103: =(($E103/(1-$J$9))) -> 2618.7385 | K103: =(($E103/(1-K$9))) -> 3404.36
B104: Victaulic Vortex Nitrogen Cylinder, 49L, w/Valve, Filled | C104: 134 | D104: PE-S000950A02 | E104: 341.67 | F104: =CEILING((I104/G$5),0.5) -> 2309 | G104: =F104*$G$5 -> 854.33 | H104: =((G104-E104)/G104) -> 0.60007257 | I104: =(($E104/(1-I$9))) -> 854.175 | J104: =(($E104/(1-$J$9))) -> 1051.2923 | K104: =(($E104/(1-K$9))) -> 1366.68
B106: Discharge Hose Kits and Accessories
B107: 80L Cylinder Primary Pilot Kit | C107: 5 | D107: S0009500PP | E107: 551.3426 | F107: =CEILING((Master!F128*1.06),0.5) -> 6391.5 | G107: =F107*$G$5 -> 2364.855 | H107: =((G107-E107)/G107) -> 0.76685987 | I107: =(($E107/(1-I$9))) -> 1378.3565 | J107: =(($E107/(1-$J$9))) -> 1696.4388 | K107: =(($E107/(1-K$9))) -> 2205.3704
B108: 80L Cylinder Secondary Kit, With Gauge | C108: 2 | D108: S0009500SP | E108: 130.0367 | F108: =CEILING((Master!F129*1.06),0.5) -> 1513 | G108: =F108*$G$5 -> 559.81 | H108: =((G108-E108)/G108) -> 0.7677128 | I108: =(($E108/(1-I$9))) -> 325.09175 | J108: =(($E108/(1-$J$9))) -> 400.11292 | K108: =(($E108/(1-K$9))) -> 520.1468
B109: 80L Cylinder Secondary Pilot Kit, With Gauge and Pressure Switch | C109: 2 | D109: S000950PSP | E109: 136.3425 | F109: =CEILING((Master!F130*1.06),0.5) -> 2355.5 | G109: =F109*$G$5 -> 871.535 | H109: =((G109-E109)/G109) -> 0.8435605 | I109: =(($E109/(1-I$9))) -> 340.85625 | J109: =(($E109/(1-$J$9))) -> 419.51538 | K109: =(($E109/(1-K$9))) -> 545.37
A110: NEW | B110: 49L CYLINDER PRIMARY PILOT KIT | C110: 5 | D110: S4909500PP | E110: 550.49 | F110: 2975.5 | G110: =F110*$G$5 -> 1100.935 | H110: =((G110-E110)/G110) -> 0.49997956 | I110: =(($E110/(1-I$9))) -> 1376.225 | J110: =(($E110/(1-$J$9))) -> 1693.8154 | K110: =(($E110/(1-K$9))) -> 2201.96
A111: NEW | B111: 49L CYLINDER SECONDARY KIT WITH GAUGE | C111: 2 | D111: S4909500SP | E111: 133.22 | F111: 720 | G111: =F111*$G$5 -> 266.4 | H111: =((G111-E111)/G111) -> 0.49992492 | I111: =(($E111/(1-I$9))) -> 333.05 | J111: =(($E111/(1-$J$9))) -> 409.90769 | K111: =(($E111/(1-K$9))) -> 532.88
...

Sheet Master
B1: Victaulic Vortex® System Product List Price Effective 3 April 2023
B2: United States
G4: Multiplier:
B5: NOTE: Please add information to the cells shaded in | C5: GREEN. | G5: 0.37
N6: =SUM(N11:N245) -> 49919.66
B7: Option Style | C7: Shipping Weight | D7: Part Code | E7: Cost (USD) | F7: List Price (USD) | G7: Extended Price | H7: GM % | I7: 60% Margin Sell | J7: 75% Margin Sell | K7: Requested to be removed | M7: QTY | N7: NET
B9: Emitters | O9: Applied Formulas
B10: 1/8" Emitters | O10: IPROD | P10: PL23
B11: 1/8” Emitter, 953 dome foil, standard, brass, 3/8” FPT, 1/8” FPT | C11: 1 | D11: S001953100 | E11: 162.334 | F11: 2019 | G11: =F11*$G$5 -> 747.03 | H11: =((G11-E11)/G11) -> 0.78269414 | I11: =(5*E11)/2 -> 405.835 | J11: =(4*E11) -> 649.336 | K11: Yes | O11: P480955228 | P11: 617
B12: 1/8” Emitter, 954 cavity foil, standard, brass, 3/8” FPT, 1/8” FPT | C12: 1 | D12: S001953101 | E12: 142.334 | F12: 2018 | G12: =F12*$G$5 -> 746.66 | H12: =((G12-E12)/G12) -> 0.80937241 | I12: =(5*E12)/2 -> 355.835 | J12: =(4*E12) -> 569.336 | K12: Yes | O12: S000950HCW | P12: 4871
B13: 1/8” Emitter, 953 cavity foil, standard, PVDF, 3/8” FPT, 1/8” FPT | C13: 1 | D13: S003953105 | E13: 195.7136 | F13: 2657.5 | G13: =F13*$G$5 -> 983.275 | H13: =((G13-E13)/G13) -> 0.80095741 | I13: =(5*E13)/2 -> 489.284 | J13: =(4*E13) -> 782.8544 | O13: P000950PAL | P13: 6
B14: 1/8” Emitter, 953 dome foil, standard, stainless, 3/8” FPT, 1/8” FPT | C14: 1 | D14: S00195310X | E14: 171.534 | F14: 2558 | G14: =F14*$G$5 -> 946.46 | H14: =((G14-E14)/G14) -> 0.81876255 | I14: =(5*E14)/2 -> 428.835 | J14: =(4*E14) -> 686.136 | O14: S001953101 | P14: 2018
B15: 1/4" Emitters | I15: =(5*E15)/2 -> 0 | J15: =(4*E15) -> 0 | O15: S003953170 | P15: 2657
B16: 1/4” Emitter, 953 dome foil, standard, stainless, 3/4” MPT, 1/4” FPT | C16: 1 | D16: S002953X02 | E16: 160.1174 | F16: 2966 | G16: =F16*$G$5 -> 1097.42 | H16: =((G16-E16)/G16) -> 0.85409652 | I16: =(5*E16)/2 -> 400.2935 | J16: =(4*E16) -> 640.4696 | O16: S00495350A | P16: 3383
B17: 1/4” Emitter, 953 dome foil, standard, brass, 3/4” MPT, 1/4” FPT | C17: 1 | D17: S002953101 | E17: 111.1814 | F17: 1969.5 | G17: =F17*$G$5 -> 728.715 | H17: =((G17-E17)/G17) -> 0.84742814 | I17: =(5*E17)/2 -> 277.9535 | J17: =(4*E17) -> 444.7256 | K17: Yes | O17: K800950003 | P17: 5965.5
B18: 1/4” Emitter, 954 cavity foil, standard, PVDF, 3/8” FPT, 1/8” FPT | C18: 1 | D18: S003953170 | E18: 241.4136 | F18: 2657 | G18: =F18*$G$5 -> 983.09 | H18: =((G18-E18)/G18) -> 0.75443388 | I18: =(5*E18)/2 -> 603.534 | J18: =(4*E18) -> 965.6544 | O18: K800950104 | P18: 6721.5
B19: 1/4” Emitter, 954 cavity foil, standard, brass, 3/4” MPT, 1/4” FPT | C19: 1 | D19: S002953100 | E19: 111.1814 | F19: 1968.5 | G19: =F19*$G$5 -> 728.345 | H19: =((G19-E19)/G19) -> 0.84735064 | I19: =(5*E19)/2 -> 277.9535 | J19: =(4*E19) -> 444.7256 | K19: Yes | O19: P00495000U | P19: 820.5
B20: 1/4” Emitter, 954 cavity foil, standard, stainless, 3/4” MPT, 1/4” FPT | C20: 1 | D20: S002953X01 | E20: 159.8124 | F20: 2966 | G20: =F20*$G$5 -> 1097.42 | H20: =((G20-E20)/G20) -> 0.85437444 | I20: =(5*E20)/2 -> 399.531 | J20: =(4*E20) -> 639.2496 | K20: Yes | O20: K000950KIT | P20: 173.5
B21: 1/4” Emitter, 954 cavity foil, escutcheon, stainless, 3/4” FPT, 1/4” FPT | C21: 1 | D21: S00295310A | E21: 446.1574 | F21: 5074 | G21: =F21*$G$5 -> 1877.38 | H21: =((G21-E21)/G21) -> 0.76235104 | I21: =(5*E21)/2 -> 1115.3935 | J21: =(4*E21) -> 1784.6296 | K21: Yes | O21: K490950008 | P21: 7510.5
B22: 3/8" Emitters | I22: =(5*E22)/2 -> 0 | J22: =(4*E22) -> 0 | O22: K800950002 | P22: 5264.5
B23: 3/8” Emitter, 953 dome foil, standard, stainless, 3/4” MPT, 1/4” FPT | C23: 1 | D23: S003953X30 | E23: 159.14672 | F23: 2374 | G23: =F23*$G$5 -> 878.38 | H23: =((G23-E23)/G23) -> 0.81881791 | I23: =(5*E23)/2 -> 397.8668 | J23: =(4*E23) -> 636.58688 | K23: Yes | O23: K800950004 | P23: 5374.5
B24: 3/8” Emitter, 953 dome foil, standard, brass, 3/4” MPT, 1/4” FPT | C24: 1 | D24: S003953131 | E24: 98.51572 | F24: 1477.5 | G24: =F24*$G$5 -> 546.675 | H24: =((G24-E24)/G24) -> 0.81979106 | I24: =(5*E24)/2 -> 246.2893 | J24: =(4*E24) -> 394.06288 | K24: Yes | O24: K800950006 | P24: 6590.5
B25: 3/8” Emitter, 954 cavity foil, standard, brass, 3/4” MPT, 1/4” FPT | C25: 1 | D25: S003953130 | E25: 98.46572 | F25: 1477.5 | G25: =F25*$G$5 -> 546.675 | H25: =((G25-E25)/G25) -> 0.81988253 | I25: =(5*E25)/2 -> 246.1643 | J25: =(4*E25) -> 393.86288 | K25: Yes | O25: K800950008 | P25: 7471.5
B26: 3/8” Emitter, 954 cavity foil, escutcheon, stainless, 3/4” FPT, 1/4” FPT | C26: 1.5 | D26: S00395310A | E26: 132.80184 | F26: 5074 | G26: =F26*$G$5 -> 1877.38 | H26: =((G26-E26)/G26) -> 0.92926214 | I26: =(5*E26)/2 -> 332.0046 | J26: =(4*E26) -> 531.20736 | K26: Yes | O26: K800950012 | P26: 9143
A27: NEW | B27: 3/8” Emitter, 953 dome foil, escutcheon, stainless, 3/4” FPT, 1/4” FPT | D27: S003953032 | E27: 52.3201 | F27: 2374 | G27: =F27*$G$5 -> 878.38 | H27: =((G27-E27)/G27) -> 0.94043569 | I27: =(5*E27)/2 -> 130.80025 | J27: =(4*E27) -> 209.2804 | O27: K800950106 | P27: 8105
A28: NEW | B28: 3/8” Emitter, 953 dome foil, standard, stainless, 3/4” FPT, 1/4” FPT | D28: S003953034 | E28: 34.5438 | F28: 1447.5 | G28: =F28*$G$5 -> 535.575 | H28: =((G28-E28)/G28) -> 0.93550147 | I28: =(5*E28)/2 -> 86.3595 | J28: =(4*E28) -> 138.1752 | O28: K000953X06 | P28: 1384.5
A29: NEW | B29: 3/8” Emitter, 954 cavity foil, escutcheon, stainless, 3/4” FPT, 1/4” FPT | D29: S003953031 | E29: 51.85424 | F29: 2374 | G29: =F29*$G$5 -> 878.38 | H29: =((G29-E29)/G29) -> 0.94096605 | I29: =(5*E29)/2 -> 129.6356 | J29: =(4*E29) -> 207.41696 | O29: K000953X13 | P29: 1384.5
A30: NEW | B30: 3/8” Emitter, 954 cavity foil, standard, stainless, 3/4” FPT, 1/4” FPT | D30: S003953033 | E30: 34.07794 | F30: 1447.5 | G30: =F30*$G$5 -> 535.575 | H30: =((G30-E30)/G30) -> 0.9363713 | I30: =(5*E30)/2 -> 85.19485 | J30: =(4*E30) -> 136.31176 | O30: K000953X26 | P30: 1384.5
B31: 1/2" Emitters | I31: =(5*E31)/2 -> 0 | J31: =(4*E31) -> 0 | O31: K000953X53 | P31: 1384.5
B32: 1/2” Emitter, 953 dome foil, standard, stainless, 3/4” MPT, 1/4” FPT | C32: 1 | D32: S006953X40 | E32: 27.14865 | F32: 1565 | G32: =F32*$G$5 -> 579.05 | H32: =((G32-E32)/G32) -> 0.95311519 | I32: =(5*E32)/2 -> 67.871625 | J32: =(4*E32) -> 108.5946 | K32: Yes | O32: K000953X79 | P32: 1384.5
B33: 1/2” Emitter, 953 dome foil, standard, brass, 3/4” MPT, 1/4” FPT | C33: 1 | D33: S006953400 | E33: 102.34866 | F33: 1123.5 | G33: =F33*$G$5 -> 415.695 | H33: =((G33-E33)/G33) -> 0.75378905 | I33: =(5*E33)/2 -> 255.87165 | J33: =(4*E33) -> 409.39464 | O33: K000953013 | P33: 1165.5
B34: 1/2” Emitter, 953 dome foil, escutcheon, stainless 3/4” FPT, 1/4” FPT | C34: 1 | D34: S00495350A | E34: 142.6213 | F34: 3383 | G34: =F34*$G$5 -> 1251.71 | H34: =((G34-E34)/G34) -> 0.88605883 | I34: =(5*E34)/2 -> 356.55325 | J34: =(4*E34) -> 570.4852 | K34: Yes | O34: K000953026 | P34: 1165.5
B35: 1/2” Emitter, 953 dome foil, standard, PVDF, 3/4” MPT, 1/4” FPT | C35: 1 | D35: S006953406 | E35: 230.5925 | F35: 2086.5 | G35: =F35*$G$5 -> 772.005 | H35: =((G35-E35)/G35) -> 0.70130699 | I35: =(5*E35)/2 -> 576.48125 | J35: =(4*E35) -> 922.37 | O35: K000953053 | P35: 1165.5
A36: NEW | B36: 1/2” Emitter, 953 dome foil, escutcheon, stainless, 3/4” FPT, 1/4” FPT | D36: S004953511 | E36: 60.22476 | H36: =((G36-E36)/G36) -> #DIV/0! | I36: =(5*E36)/2 -> 150.5619 | J36: =(4*E36) -> 240.89904 | O36: K000953079 | P36: 1165.5
A37: NEW | B37: 1/2” Emitter, 953 dome foil, standard, stainless, 3/4” FPT, 1/4” FPT | D37: S004953513 | E37: 35.2038 | H37: =((G37-E37)/G37) -> #DIV/0! | I37: =(5*E37)/2 -> 88.0095 | J37: =(4*E37) -> 140.8152 | O37: K000953106 | P37: 1165.5
B38: 5/8" Emitters | I38: =(5*E38)/2 -> 0 | J38: =(4*E38) -> 0 | O38: P000950001 | P38: 9.5
B39: 5/8” Emitter, 953 dome foil, standard, stainless, 3/4” MPT, 1/4” FPT | C39: 1 | D39: S006953X50 | E39: 93.35758 | F39: 1936.5 | G39: =F39*$G$5 -> 716.505 | H39: =((G39-E39)/G39) -> 0.86970422 | I39: =(5*E39)/2 -> 233.39395 | J39: =(4*E39) -> 373.43032 | K39: Yes | O39: P000950018 | P39: 18.5
B40: 5/8” Emitter, 953 dome foil, standard, brass, 3/4” MPT, 1/4” FPT | C40: 1 | D40: S006953500 | E40: 77.0266 | F40: 1318.5 | G40: =F40*$G$5 -> 487.845 | H40: =((G40-E40)/G40) -> 0.84210846 | I40: =(5*E40)/2 -> 192.5665 | J40: =(4*E40) -> 308.1064 | K40: Yes | O40: P000950034 | P40: 24
B41: 5/8” Emitter, 953 cavity foil, PVDF, 3/4” FPT, 1/4" FPT | C41: 1 | D41: S006953503 | E41: 193.3368 | F41: 2657.5 | G41: =F41*$G$5 -> 983.275 | H41: =((G41-E41)/G41) -> 0.80337464 | I41: =(5*E41)/2 -> 483.342 | J41: =(4*E41) -> 773.3472 | O41: P000950065 | P41: 1973
B42: 5/8” Emitter, 954 cavity foil, standard, stainless, 3/4” MPT, 1/4” FPT | C42: 1 | D42: S006953X51 | E42: 24.62865 | F42: 1935.5 | G42: =F42*$G$5 -> 716.135 | H42: =((G42-E42)/G42) -> 0.96560893 | I42: =(5*E42)/2 -> 61.571625 | J42: =(4*E42) -> 98.5146 | K42: Yes | O42: P000951RFP | P42: 6
B43: 5/8” Emitter, 954 cavity foil, standard, brass, 3/4” MPT, 1/4” FPT | C43: 1 | D43: S006953501 | E43: 88.91758 | F43: 1318.5 | G43: =F43*$G$5 -> 487.845 | H43: =((G43-E43)/G43) -> 0.81773395 | I43: =(5*E43)/2 -> 222.29395 | J43: =(4*E43) -> 355.67032 | K43: Yes | O43: P000951TRM | P43: 4092.5
B44: 5/8” Emitter, 954 cavity foil, escutcheon, stainless, 3/4” MPT, 1/4” FPT | C44: 1.5 | D44: S00695350A | E44: 140.1213 | F44: 3383.5 | G44: =F44*$G$5 -> 1251.895 | H44: =((G44-E44)/G44) -> 0.88807264 | I44: =(5*E44)/2 -> 350.30325 | J44: =(4*E44) -> 560.4852 | K44: Yes | O44: P000951134 | P44: 1735.5
A45: NEW | B45: 5/8” Emitter, 954 cavity foil, escutcheon, stainless, 3/4” FPT, 1/4” FPT | D45: S006953512 | E45: 50.4801 | G45: =F45*$G$5 -> 0 | H45: =((G45-E45)/G45) -> #DIV/0! | I45: =(5*E45)/2 -> 126.20025 | J45: =(4*E45) -> 201.9204 | O45: P000951135 | P45: 1477.5
A46: NEW | B46: 5/8” Emitter, 954 cavity foil, standard, stainless, 3/4” FPT, 1/4” FPT | D46: S006953514 | E46: 32.7038 | H46: =((G46-E46)/G46) -> #DIV/0! | I46: =(5*E46)/2 -> 81.7595 | J46: =(4*E46) -> 130.8152 | O46: P000951136 | P46: 1840.5
B47: 1" Emitters | I47: =(5*E47)/2 -> 0 | J47: =(4*E47) -> 0 | O47: P000951304 | P47: 4092.5
A48: NEW | B48: 1” Emitter, 953/954 dome foil, escutcheon, stainless, 1” FPT, 1/8” FPT | D48: S010953511 | E48: 68.4904 | H48: =((G48-E48)/G48) -> #DIV/0! | I48: =(5*E48)/2 -> 171.226 | J48: =(4*E48) -> 273.9616 | O48: P002953260 | P48: 30
I49: =(5*E49)/2 -> 0 | J49: =(4*E49) -> 0 | O49: P006953X07 | P49: 1104
B50: Water Flow Kits (Strainer, Flow Cartridge, Emitter Trim Kit) | I50: =(5*E50)/2 -> 0 | J50: =(4*E50) -> 0 | O50: P006953X13 | P50: 1104
B51: Water Flow Cartridge Kit, .13 GPM, Brass, 3/4” NPT | C51: 1 | D51: K000953013 | E51: 103.42 | F51: 1165.5 | G51: =F51*$G$5 -> 431.235 | H51: =((G51-E51)/G51) -> 0.76017717 | I51: =(5*E51)/2 -> 258.55 | J51: =(4*E51) -> 413.68 | O51: P006953005 | P51: 1043
B52: Water Flow Cartridge Kit, .13 GPM, Stainless, 3/4” NPT | C52: 1 | D52: K000953X13 | E52: 133.39 | F52: 1384.5 | G52: =F52*$G$5 -> 512.265 | H52: =((G52-E52)/G52) -> 0.73960743 | I52: =(5*E52)/2 -> 333.475 | J52: =(4*E52) -> 533.56 | O52: P006953007 | P52: 1043
B53: Water Flow Cartridge Kit, .26 GPM, Brass, 3/4” NPT | C53: 1 | D53: K000953026 | E53: 109.44 | F53: 1165.5 | G53: =F53*$G$5 -> 431.235 | H53: =((G53-E53)/G53) -> 0.74621726 | I53: =(5*E53)/2 -> 273.6 | J53: =(4*E53) -> 437.76 | O53: P006953013 | P53: 1043
B54: Water Flow Cartridge Kit, .26 GPM, Stainless, 3/4” NPT | C54: 1 | D54: K000953X26 | E54: 133.39 | F54: 1384.5 | G54: =F54*$G$5 -> 512.265 | H54: =((G54-E54)/G54) -> 0.73960743 | I54: =(5*E54)/2 -> 333.475 | J54: =(4*E54) -> 533.56 | O54: P006953522 | P54: 30
B55: Water Flow Cartridge Kit, .53 GPM, Brass, 3/4” NPT | C55: 1 | D55: K000953053 | E55: 103.42 | F55: 1165.5 | G55: =F55*$G$5 -> 431.235 | H55: =((G55-E55)/G55) -> 0.76017717 | I55: =(5*E55)/2 -> 258.55 | J55: =(4*E55) -> 413.68 | O55: P006953560 | P55: 30
B56: Water Flow Cartridge Kit, .53 GPM, Stainless, 3/4” NPT | C56: 1 | D56: K000953X53 | E56: 135.51 | F56: 1384.5 | G56: =F56*$G$5 -> 512.265 | H56: =((G56-E56)/G56) -> 0.73546895 | I56: =(5*E56)/2 -> 338.775 | J56: =(4*E56) -> 542.04 | O56: P000955A29 | P56: 455.5
B57: Water Flow Cartridge Kit, .79 GPM, Brass, 3/4” NPT | C57: 1 | D57: K000953079 | E57: 103.42 | F57: 1165.5 | G57: =F57*$G$5 -> 431.235 | H57: =((G57-E57)/G57) -> 0.76017717 | I57: =(5*E57)/2 -> 258.55 | J57: =(4*E57) -> 413.68 | O57: P000955B29 | P57: 496
B58: Water Flow Cartridge Kit, .79 GPM, Stainless, 3/4” NPT | C58: 1 | D58: K000953X79 | E58: 135.51 | F58: 1384.5 | G58: =F58*$G$5 -> 512.265 | H58: =((G58-E58)/G58) -> 0.73546895 | I58: =(5*E58)/2 -> 338.775 | J58: =(4*E58) -> 542.04 | O58: P000955035 | P58: 238
B59: Water Flow Cartridge Kit, 1.06 GPM, Brass, 3/4” NPT | C59: 1 | D59: K000953106 | E59: 103.42 | F59: 1165.5 | G59: =F59*$G$5 -> 431.235 | H59: =((G59-E59)/G59) -> 0.76017717 | I59: =(5*E59)/2 -> 258.55 | J59: =(4*E59) -> 413.68 | O59: K000953153 | P59: 1165.5
B60: Water Flow Cartridge Kit, 1.06 GPM, Stainless, 3/4” NPT | C60: 1 | D60: K000953X06 | E60: 135.51 | F60: 1384.5 | G60: =F60*$G$5 -> 512.265 | H60: =((G60-E60)/G60) -> 0.73546895 | I60: =(5*E60)/2 -> 338.775 | J60: =(4*E60) -> 542.04 | O60: K00095315X | P60: 1165.5
I61: =(5*E61)/2 -> 0 | J61: =(4*E61) -> 0 | O61: S00M95PP12 | P61: 3075.5
B62: Components | I62: =(5*E62)/2 -> 0 | J62: =(4*E62) -> 0 | O62: S00M950PM2 | P62: 1761
B63: 1/4" MNPT x 7/16-20 Male JIC Straight adapter, brass | C63: 0.1 | D63: PAY7000C01 | E63: 4.26 | F63: 21 | G63: =F63*$G$5 -> 7.77 | H63: =((G63-E63)/G63) -> 0.45173745 | I63: =(5*E63)/2 -> 10.65 | J63: =(4*E63) -> 17.04 | O63: S00M950PM3 | P63: 1819.5
B64: 7/16-20 Female JIC x 31” PTFE lined braided stainless hose, 1/4” ID | C64: 0.4 | D64: P310955228 | E64: 67.5127 | F64: 353 | G64: =F64*$G$5 -> 130.61 | H64: =((G64-E64)/G64) -> 0.48309701 | I64: =(5*E64)/2 -> 168.78175 | J64: =(4*E64) -> 270.0508 | O64: S00M950PM4 | P64: 1858.5
B65: 7/16-20 Female JIC x 36” PTFE lined braided stainless hose, 1/4” ID | C65: 0.4 | D65: P360955228 | E65: 76.17 | F65: 531 | G65: =F65*$G$5 -> 196.47 | H65: =((G65-E65)/G65) -> 0.61230722 | I65: =(5*E65)/2 -> 190.425 | J65: =(4*E65) -> 304.68 | O65: S00M950PM6 | P65: 2004
B66: 7/16-20 Female JIC x 48” PTFE lined braided stainless hose, 1/4” ID | C66: 1 | D66: P480955228 | E66: 107.544 | F66: 617 | G66: =F66*$G$5 -> 228.29 | H66: =((G66-E66)/G66) -> 0.52891498 | I66: =(5*E66)/2 -> 268.86 | J66: =(4*E66) -> 430.176 | O66: S00M950PP4 | P66: 1807.5
B67: 1/4" MNPT x 7/16-20 Male JIC 90 degree adapter, brass | C67: 0.1 | D67: PAY0955001 | E67: 1.13 | F67: 8 | G67: =F67*$G$5 -> 2.96 | H67: =((G67-E67)/G67) -> 0.61824324 | I67: =(5*E67)/2 -> 2.825 | J67: =(4*E67) -> 4.52 | O67: S00M950PP6 | P67: 2200.5
B68: 1/4" NPT x 3/8" OD compression, 90 degree adapter, brass | C68: 0.1 | D68: SY45953001 | E68: 2.92 | F68: 21 | G68: =F68*$G$5 -> 7.77 | H68: =((G68-E68)/G68) -> 0.62419562 | I68: =(5*E68)/2 -> 7.3 | J68: =(4*E68) -> 11.68 | O68: S00M950PP8 | P68: 2681.5
B69: 1/4" NPT x 3/8" OD compression, straight adapter, brass | C69: 0.1 | D69: SY45953002 | E69: 2.19 | F69: 16 | G69: =F69*$G$5 -> 5.92 | H69: =((G69-E69)/G69) -> 0.63006757 | I69: =(5*E69)/2 -> 5.475 | J69: =(4*E69) -> 8.76 | O69: S00M950P12 | P69: 3076.5
I70: =(5*E70)/2 -> 0 | J70: =(4*E70) -> 0 | O70: S000950A01 | P70: 8102.5
B71: Vortex Panels | I71: =(5*E71)/2 -> 0 | J71: =(4*E71) -> 0 | O71: S000950A02 | P71: 5163
B72: Combination Panels | I72: =(5*E72)/2 -> 0 | J72: =(4*E72) -> 0 | O72: S000950A30 | P72: 14758
B73: 1" | I73: =(5*E73)/2 -> 0 | J73: =(4*E73) -> 0 | O73: S000950BA1 | P73: 298
B74: 1” 951 V1000 Combination Panel, Dry Contact, Ball Valve | C74: 170 | D74: S010951DRY | E74: 3997.8518 | F74: 53893 | G74: =F74*$G$5 -> 19940.41 | H74: =((G74-E74)/G74) -> 0.79951005 | I74: =(5*E74)/2 -> 9994.6294 | J74: =(4*E74) -> 15991.407 | M74: 1 | N74: =M74*G74 -> 19940.41 | O74: S000950BA2 | P74: 83
B75: 1” 951 V1500 Combination Panel, Dry Contact, Ball Valve | C75: 170 | D75: S01095115D | E75: 4005.198 | F75: 53891 | G75: =F75*$G$5 -> 19939.67 | H75: =((G75-E75)/G75) -> 0.79913419 | I75: =(5*E75)/2 -> 10012.995 | J75: =(4*E75) -> 16020.792 | K75: Yes | O75: S000950BA4 | P75: 396.5
B76: 1” 951 V2000 Combination Panel, Dry Contact, Ball Valve | C76: 170 | D76: S010951200 | E76: 4000.9637 | F76: 53893 | G76: =F76*$G$5 -> 19940.41 | H76: =((G76-E76)/G76) -> 0.79935399 | I76: =(5*E76)/2 -> 10002.409 | J76: =(4*E76) -> 16003.855 | K76: Yes | O76: S000950B02 | P76: 5101
B77: 1” 951 V1000 Combination Panel, Active Release, Ball Valve | C77: 170 | D77: S010951ACT | E77: 4014.8949 | F77: 53891 | G77: =F77*$G$5 -> 19939.67 | H77: =((G77-E77)/G77) -> 0.79864788 | I77: =(5*E77)/2 -> 10037.237 | J77: =(4*E77) -> 16059.579 | O77: S000950B03 | P77: 690.5
B78: 1” 951 V1500 Combination Panel, Active Release, Ball Valve | C78: 170 | D78: S01095115R | E78: 4019.1291 | F78: 53891 | G78: =F78*$G$5 -> 19939.67 | H78: =((G78-E78)/G78) -> 0.79843553 | I78: =(5*E78)/2 -> 10047.823 | J78: =(4*E78) -> 16076.516 | K78: Yes | O78: S000950B08 | P78: 150.5
B79: 1” 951 V2000 Combination Panel, Active Release, Ball Valve | C79: 170 | D79: S010951A20 | E79: 4014.8949 | F79: 53894.5 | G79: =F79*$G$5 -> 19940.965 | H79: =((G79-E79)/G79) -> 0.79866095 | I79: =(5*E79)/2 -> 10037.237 | J79: =(4*E79) -> 16059.579 | K79: Yes | O79: S000950B22 | P79: 5101
B80: 1.5" | I80: =(5*E80)/2 -> 0 | J80: =(4*E80) -> 0 | O80: S000950E01 | P80: 8102.5
B81: 1.5” 951 V1000 Combination Panel, Dry Contact, Ball Valve | C81: 180 | D81: S014951DRY | E81: 4207.9386 | F81: 54648 | G81: =F81*$G$5 -> 20219.76 | H81: =((G81-E81)/G81) -> 0.79188978 | I81: =(5*E81)/2 -> 10519.847 | J81: =(4*E81) -> 16831.754 | O81: S000950PSP | P81: 2222
B82: 1.5” 951 V1500 Combination Panel, Dry Contact, Ball Valve | C82: 180 | D82: S01495115D | E82: 4077.9628 | F82: 54648 | G82: =F82*$G$5 -> 20219.76 | H82: =((G82-E82)/G82) -> 0.79831794 | I82: =(5*E82)/2 -> 10194.907 | J82: =(4*E82) -> 16311.851 | K82: Yes | O82: S000950P32 | P82: 101
B83: 1.5” 951 V2000 Combination Panel, Dry Contact, Ball Valve | C83: 180 | D83: S014951200 | E83: 4207.9386 | F83: 54648 | G83: =F83*$G$5 -> 20219.76 | H83: =((G83-E83)/G83) -> 0.79188978 | I83: =(5*E83)/2 -> 10519.847 | J83: =(4*E83) -> 16831.754 | K83: Yes | O83: S000950P50 | P83: 119
B84: 1.5” 951 V1000 Combination Panel, Active Release, Ball Valve | C84: 180 | D84: S014951ACT | E84: 4208.4386 | F84: 54648 | G84: =F84*$G$5 -> 20219.76 | H84: =((G84-E84)/G84) -> 0.79186506 | I84: =(5*E84)/2 -> 10521.097 | J84: =(4*E84) -> 16833.754 | O84: S000950P70 | P84: 141
B85: 1.5” 951 V1500 Combination Panel, Active Release, Ball Valve | C85: 180 | D85: S01495115R | E85: 4078.4628 | F85: 54648 | G85: =F85*$G$5 -> 20219.76 | H85: =((G85-E85)/G85) -> 0.79829321 | I85: =(5*E85)/2 -> 10196.157 | J85: =(4*E85) -> 16313.851 | K85: Yes | O85: S0009500PP | P85: 6029.5
B86: 1.5” 951 V2000 Combination Panel, Active Release, Ball Valve | C86: 180 | D86: S014951A20 | E86: 4208.4386 | F86: 54648 | G86: =F86*$G$5 -> 20219.76 | H86: =((G86-E86)/G86) -> 0.79186506 | I86: =(5*E86)/2 -> 10521.097 | J86: =(4*E86) -> 16833.754 | K86: Yes | O86: S0009500SP | P86: 1427
B87: * Please note each Combination Panels requires a pressure transducer to be ordered separately. Reference spare parts section for pressure transducer selection. | I87: =(5*E87)/2 -> 0 | J87: =(4*E87) -> 0 | O87: S000950010 | P87: 3207
I88: =(5*E88)/2 -> 0 | J88: =(4*E88) -> 0 | O88: S000950015 | P88: 6092.5
B89: Fluid Panels | I89: =(5*E89)/2 -> 0 | J89: =(4*E89) -> 0 | O89: S000950027 | P89: 5124.5
B90: 1" | I90: =(5*E90)/2 -> 0 | J90: =(4*E90) -> 0 | O90: S000950060 | P90: 17531
B91: 1” 951 V1000 Fluid Panel, Dry Contact | C91: 130 | D91: S010951F00 | E91: 2813.5138 | F91: 40979 | G91: =F91*$G$5 -> 15162.23 | H91: =((G91-E91)/G91) -> 0.81443932 | I91: =(5*E91)/2 -> 7033.7844 | J91: =(4*E91) -> 11254.055 | O91: S000950080 | P91: 20154
B92: 1” 951 V1500 Fluid Panel, Dry Contact | C92: 130 | D92: S0109515DC | E92: 2815.1552 | F92: 40977.5 | G92: =F92*$G$5 -> 15161.675 | H92: =((G92-E92)/G92) -> 0.81432426 | I92: =(5*E92)/2 -> 7037.8881 | J92: =(4*E92) -> 11260.621 | K92: Yes | O92: S000950120 | P92: 24444
B93: 1” 951 V2000 Fluid Panel, Dry Contact | C93: 130 | D93: S010951F20 | E93: 2813.5138 | F93: 40979 | G93: =F93*$G$5 -> 15162.23 | H93: =((G93-E93)/G93) -> 0.81443932 | I93: =(5*E93)/2 -> 7033.7844 | J93: =(4*E93) -> 11254.055 | K93: Yes | O93: S0009502X1 | P93: 4592.5
B94: 1” 951 V1000 Fluid Panel, Active Release | C94: 130 | D94: S010951FA0 | E94: 3016.0932 | F94: 40977.5 | G94: =F94*$G$5 -> 15161.675 | H94: =((G94-E94)/G94) -> 0.80107124 | I94: =(5*E94)/2 -> 7540.2331 | J94: =(4*E94) -> 12064.373 | O94: S0009502X2 | P94: 4986
B95: 1” 951 V1500 Fluid Panel, Active Release | C95: 130 | D95: S0109515AR | E95: 3017.7347 | F95: 40977.5 | G95: =F95*$G$5 -> 15161.675 | H95: =((G95-E95)/G95) -> 0.80096297 | I95: =(5*E95)/2 -> 7544.3368 | J95: =(4*E95) -> 12070.939 | K95: Yes | O95: S000950200 | P95: 30715.5
B96: 1” 951 V2000 Fluid Panel, Active Release | C96: 130 | D96: S010951FA2 | E96: 3016.0932 | F96: 40982 | G96: =F96*$G$5 -> 15163.34 | H96: =((G96-E96)/G96) -> 0.80109308 | I96: =(5*E96)/2 -> 7540.2331 | J96: =(4*E96) -> 12064.373 | K96: Yes | O96: S000950220 | P96: 5126.5
B97: 1.5" | I97: =(5*E97)/2 -> 0 | J97: =(4*E97) -> 0 | O97: S0009503X1 | P97: 4789.5
B98: 1.5” 951 V1000 Fluid Panel, Dry Contact | C98: 140 | D98: S014951F00 | E98: 3007.0575 | F98: 40979 | G98: =F98*$G$5 -> 15162.23 | H98: =((G98-E98)/G98) -> 0.80167446 | I98: =(5*E98)/2 -> 7517.6438 | J98: =(4*E98) -> 12028.23 | O98: S0009503X2 | P98: 4660.5
B99: 1.5” 951 V1500 Fluid Panel, Dry Contact | C99: 140 | D99: S0149515DC | E99: 2874.489 | F99: 40977.5 | G99: =F99*$G$5 -> 15161.675 | H99: =((G99-E99)/G99) -> 0.81041086 | I99: =(5*E99)/2 -> 7186.2225 | J99: =(4*E99) -> 11497.956 | K99: Yes | O99: S0009504X1 | P99: 4986
B100: 1.5” 951 V2000 Fluid Panel, Dry Contact | C100: 140 | D100: S014951F20 | E100: 3007.0575 | F100: 40979 | G100: =F100*$G$5 -> 15162.23 | H100: =((G100-E100)/G100) -> 0.80167446 | I100: =(5*E100)/2 -> 7517.6438 | J100: =(4*E100) -> 12028.23 | K100: Yes | O100: S0009504X2 | P100: 5517
B101: 1.5” 951 V1000 Fluid Panel, Active Release | C101: 140 | D101: S014951FA0 | E101: 3105.6475 | F101: 40982 | G101: =F101*$G$5 -> 15163.34 | H101: =((G101-E101)/G101) -> 0.79518711 | I101: =(5*E101)/2 -> 7764.1188 | J101: =(4*E101) -> 12422.59 | O101: S0009506X1 | P101: 5182.5
B102: 1.5” 951 V1500 Fluid Panel, Active Release | C102: 140 | D102: S0149515AR | E102: 2973.079 | F102: 40977.5 | G102: =F102*$G$5 -> 15161.675 | H102: =((G102-E102)/G102) -> 0.80390828 | I102: =(5*E102)/2 -> 7432.6975 | J102: =(4*E102) -> 11892.316 | K102: Yes | O102: S0009506X2 | P102: 5890.5
...

Sheet Margin Analysis
A1: Instructions: Copy and Paste columns A-D from Configurator BOM | F1: System Cost | H1: Raw List | J1: Multiplier | K1: Net List | L1: Gross Margin
F2: =SUM(F5:F200) -> 13043.461 | H2: =SUM(H5:H200) -> 96878.5 | J2: 0.3 | K2: =H2*J2 -> 29063.55 | L2: =IFERROR((K2-F2)/K2,"") -> 0.55120895
A4: Item # | B4: Description | C4: Quantity | D4: Partcode | F4: Item Cost | H4: Item List
A5: 1 | B5: Victaulic Vortex Nitrogen Cylinder, 80L, w/Valve, Filled | C5: 4 | D5: S000950A01 | F5: =IFERROR(VLOOKUP(D5,Updated!D:E,2,FALSE())*C5,"") -> 3404.36 | H5: =IFERROR(VLOOKUP(D5,Updated!D:F,3,FALSE())*C5,"") -> 23004
A6: 2 | B6: 80L Cylinder Primary Pilot Kit | C6: 1 | D6: S0009500PP | F6: =IFERROR(VLOOKUP(D6,Updated!D:E,2,FALSE())*C6,"") -> 551.3426 | H6: =IFERROR(VLOOKUP(D6,Updated!D:F,3,FALSE())*C6,"") -> 6391.5
A7: 3 | B7: 80L Cylinder Secondary Kit, With Gauge | C7: 3 | D7: S0009500SP | F7: =IFERROR(VLOOKUP(D7,Updated!D:E,2,FALSE())*C7,"") -> 390.1101 | H7: =IFERROR(VLOOKUP(D7,Updated!D:F,3,FALSE())*C7,"") -> 4539
A8: 4 | B8: VORTEX PRE ENGINEERED FOUR 80L CYLINDER | C8: 1 | D8: S800950004 | F8: =IFERROR(VLOOKUP(D8,Updated!D:E,2,FALSE())*C8,"") -> 5338.1933 | H8: =IFERROR(VLOOKUP(D8,Updated!D:F,3,FALSE())*C8,"") -> 28855.5
A9: 5 | B9: Performance Based Designs | C9: 1 | D9: Z519892LBL | F9: =IFERROR(VLOOKUP(D9,Updated!D:E,2,FALSE())*C9,"") -> 0 | H9: =IFERROR(VLOOKUP(D9,Updated!D:F,3,FALSE())*C9,"") -> 55
A10: 6 | B10: 5/8” Emitter, 954 cavity foil, standard, stainless, 3/4” FPT, 1/4” FPT | C10: 2 | D10: S006953514 | F10: =IFERROR(VLOOKUP(D10,Updated!D:E,2,FALSE())*C10,"") -> 65.4076 | H10: =IFERROR(VLOOKUP(D10,Updated!D:F,3,FALSE())*C10,"") -> 2382
A11: 7 | B11: Water Flow Cartridge Kit, .53 GPM, Stainless, 3/4” NPT | C11: 2 | D11: K000953X53 | F11: =IFERROR(VLOOKUP(D11,Updated!D:E,2,FALSE())*C11,"") -> 271.02 | H11: =IFERROR(VLOOKUP(D11,Updated!D:F,3,FALSE())*C11,"") -> 2936
A12: 8 | B12: 10 Gallon Water Tank, Red, w/ Trim, ASME and FM approved | C12: 1 | D12: S100950140 | F12: =IFERROR(VLOOKUP(D12,Updated!D:E,2,FALSE())*C12,"") -> 1470.2704 | H12: =IFERROR(VLOOKUP(D12,Updated!D:F,3,FALSE())*C12,"") -> 11534
A13: 9 | B13: I-VORTEX PE.DIOM | C13: 1 | D13: Z000VTXPES | F13: =IFERROR(VLOOKUP(D13,Updated!D:E,2,FALSE())*C13,"") | H13: =IFERROR(VLOOKUP(D13,Updated!D:F,3,FALSE())*C13,"")
A14: 10 | B14: Pressure Transducer, Standard, 0-100 psi | C14: 1 | D14: P000951134 | F14: =IFERROR(VLOOKUP(D14,Updated!D:E,2,FALSE())*C14,"") -> 125.48 | H14: =IFERROR(VLOOKUP(D14,Updated!D:F,3,FALSE())*C14,"") -> 1840
A15: 11 | B15: 115VAC Battery Backup Power Supply w/ (2) 12 Ah batteries | C15: 1 | D15: S000950027 | F15: =IFERROR(VLOOKUP(D15,Updated!D:E,2,FALSE())*C15,"") -> 405.04 | H15: =IFERROR(VLOOKUP(D15,Updated!D:F,3,FALSE())*C15,"") -> 5432
A16: 12 | B16: Vortex Single Cylinder Refill Adapter, CGA-580 Inlet | C16: 4 | D16: S002950000 | F16: =IFERROR(VLOOKUP(D16,Updated!D:E,2,FALSE())*C16,"") -> 192.5872 | H16: =IFERROR(VLOOKUP(D16,Updated!D:F,3,FALSE())*C16,"") -> 3028
... A23: 19 | B23: In Place Bulk Cylinder Refill Kit, 1” NPT Inlet | C23: 1 | D23: S000950015 | F23: =IFERROR(VLOOKUP(D23,Updated!D:E,2,FALSE())*C23,"") -> 768.69 | H23: =IFERROR(VLOOKUP(D23,Updated!D:F,3,FALSE())*C23,"") -> 6458.5
F24: =IFERROR(VLOOKUP(D24,Updated!D:E,2,FALSE())*C24,"") | H24: =IFERROR(VLOOKUP(D24,Updated!D:F,3,FALSE())*C24,"")
F25: =IFERROR(VLOOKUP(D25,Updated!D:E,2,FALSE())*C25,"") | H25: =IFERROR(VLOOKUP(D25,Updated!D:F,3,FALSE())*C25,"")
F26: =IFERROR(VLOOKUP(D26,Updated!D:E,2,FALSE())*C26,"") | H26: =IFERROR(VLOOKUP(D26,Updated!D:F,3,FALSE())*C26,"")
F27: =IFERROR(VLOOKUP(D27,Updated!D:E,2,FALSE())*C27,"") | H27: =IFERROR(VLOOKUP(D27,Updated!D:F,3,FALSE())*C27,"")
F28: =IFERROR(VLOOKUP(D28,Updated!D:E,2,FALSE())*C28,"") | H28: =IFERROR(VLOOKUP(D28,Updated!D:F,3,FALSE())*C28,"")
F29: =IFERROR(VLOOKUP(D29,Updated!D:E,2,FALSE())*C29,"") | H29: =IFERROR(VLOOKUP(D29,Updated!D:F,3,FALSE())*C29,"")
F30: =IFERROR(VLOOKUP(D30,Updated!D:E,2,FALSE())*C30,"") | H30: =IFERROR(VLOOKUP(D30,Updated!D:F,3,FALSE())*C30,"")
F31: =IFERROR(VLOOKUP(D31,Updated!D:E,2,FALSE())*C31,"") | H31: =IFERROR(VLOOKUP(D31,Updated!D:F,3,FALSE())*C31,"")
F32: =IFERROR(VLOOKUP(D32,Updated!D:E,2,FALSE())*C32,"") | H32: =IFERROR(VLOOKUP(D32,Updated!D:F,3,FALSE())*C32,"")
F33: =IFERROR(VLOOKUP(D33,Updated!D:E,2,FALSE())*C33,"") | H33: =IFERROR(VLOOKUP(D33,Updated!D:F,3,FALSE())*C33,"")
F34: =IFERROR(VLOOKUP(D34,Updated!D:E,2,FALSE())*C34,"") | H34: =IFERROR(VLOOKUP(D34,Updated!D:F,3,FALSE())*C34,"")
F35: =IFERROR(VLOOKUP(D35,Updated!D:E,2,FALSE())*C35,"") | H35: =IFERROR(VLOOKUP(D35,Updated!D:F,3,FALSE())*C35,"")
... F54: =IFERROR(VLOOKUP(D54,Updated!D:E,2,FALSE())*C54,"") | H54: =IFERROR(VLOOKUP(D54,Updated!D:F,3,FALSE())*C54,"")
H55: =IFERROR(VLOOKUP(D55,Updated!D:F,3,FALSE())*C55,"")
H56: =IFERROR(VLOOKUP(D56,Updated!D:F,3,FALSE())*C56,"")
H57: =IFERROR(VLOOKUP(D57,Updated!D:F,3,FALSE())*C57,"")
H58: =IFERROR(VLOOKUP(D58,Updated!D:F,3,FALSE())*C58,"")
H59: =IFERROR(VLOOKUP(D59,Updated!D:F,3,FALSE())*C59,"")
H60: =IFERROR(VLOOKUP(D60,Updated!D:F,3,FALSE())*C60,"")
H61: =IFERROR(VLOOKUP(D61,Updated!D:F,3,FALSE())*C61,"")
H62: =IFERROR(VLOOKUP(D62,Updated!D:F,3,FALSE())*C62,"")
H63: =IFERROR(VLOOKUP(D63,Updated!D:F,3,FALSE())*C63,"")
H64: =IFERROR(VLOOKUP(D64,Updated!D:F,3,FALSE())*C64,"")
H65: =IFERROR(VLOOKUP(D65,Updated!D:F,3,FALSE())*C65,"")
H66: =IFERROR(VLOOKUP(D66,Updated!D:F,3,FALSE())*C66,"")
H67: =IFERROR(VLOOKUP(D67,Updated!D:F,3,FALSE())*C67,"")

Sheet Sheet1
A1: Product Line | B1: Item BPCS Number | C1: M3 Item Number | D1: CURRENT 2025 Listprice EUR | E1: CURRENT 2025 Listprice USD | F1: NEW 2025 Listprice EUR | G1: NEW 2025 Listprice USD | H1: Item Description | I1: Status | J1: Product Class | K1: Sales Cat Code | L1: Material | M1: Gasket Option | N1: Size 1 | O1: Size 2 | P1: Catalog Code | Q1: Outlet | R1: Style Number
A2: V2700003- VORTEX - CYLINDERS | B2: Z212760LBL | C2: ZL2127600000000 | H2: VICTAULIC VORTEX WATER TANK FILLING PROCEDURE | I2: 20- Released | J2: D- Devices/Trim/Disc/Ring for VBSP | K2: V27000000- VORTEX -HVLP | L2: N/A- Not applicable | M2: N/A- No Gasket | R2: D950
A3: V2700006- VORTEX - MISCELLANEOUS | B3: Z000950030 | C3: ZL0663600000000 | D3: 136.9 | E3: 195.11 | H3: RACK PLACARD | I3: 20- Released | J3: D- Devices/Trim/Disc/Ring for VBSP | K3: V27000000- VORTEX -HVLP | L3: N/A- Not applicable | M3: N/A- No Gasket | P3: XVX | Q3: SYWA | R3: MISC
A4: V2700006- VORTEX - MISCELLANEOUS | B4: Z000950012 | C4: ZL0552300000000 | D4: 30.83 | E4: 43.94 | H4: ZONE EXTERNAL LOW OXYGEN CONDITION PLACARD | I4: 20- Released | J4: D- Devices/Trim/Disc/Ring for VBSP | K4: V27000000- VORTEX -HVLP | L4: N/A- Not applicable | M4: N/A- No Gasket | P4: XVX | Q4: SYWA | R4: MISC
A5: V2700006- VORTEX - MISCELLANEOUS | B5: Z000950011 | C5: ZL0552200000000 | D5: 19.33 | E5: 27.55 | H5: INSIDE ZONE ALARM VACATING PLACARD | I5: 20- Released | J5: D- Devices/Trim/Disc/Ring for VBSP | K5: V27000000- VORTEX -HVLP | L5: N/A- Not applicable | M5: N/A- No Gasket | P5: XVX | Q5: SYWA | R5: MISC
A6: V2700006- VORTEX - MISCELLANEOUS | B6: Z000950004 | C6: ZL0497600000000 | D6: 75.24 | E6: 107.23 | H6: MANUAL PULL STATION PLACARD | I6: 20- Released | J6: D- Devices/Trim/Disc/Ring for VBSP | K6: V27000000- VORTEX -HVLP | L6: N/A- Not applicable | M6: N/A- No Gasket | P6: XVX | Q6: SYWA | R6: MISC
A7: V2700003- VORTEX - CYLINDERS | B7: Z000950115 | C7: Z09500VXSS00000 | H7: M950/ SUPPRESSION SYSTEM INFL TAG | I7: 20- Released | J7: Z- Label, Tag, Shipping Supplies | K7: V27000000- VORTEX -HVLP | L7: N/A- Not applicable | M7: N/A- No Gasket | R7: M951
A8: V2700006- VORTEX - MISCELLANEOUS | B8: P010000ZHP | C8: PZZZZ0010NPTZHP | H8: M/ 033 HIGH PRESSURE SQUARE HEAD PIPE PLUG PLATED | I8: 20- Released | J8: P- Parts/Pipe/Tube | K8: V99999000- MISCELLANEOUS | L8: CS- Carbon Steel | M8: N/A- No Gasket | N8: 0033 | R8: MISC
A9: V2700006- VORTEX - MISCELLANEOUS | B9: P010955005 | C9: P09550000VXMIRC | H9: M955/1 NPT FEMx3/4 NPT FEM RD CPL CL150 MALLEABLE IRON PLAIN | I9: 20- Released | J9: P- Parts/Pipe/Tube | K9: V27000000- VORTEX -HVLP | L9: N/A- Not applicable | M9: N/A- No Gasket | N9: 0033 | R9: M955
A10: V2700006- VORTEX - MISCELLANEOUS | B10: PU01955M01 | C10: P09550000VXHHSS | H10: D955/1x1/4NPTMxF HX HD 316SS BSH PLN MCMASTER CARR #4443K415 | I10: 20- Released | J10: P- Parts/Pipe/Tube | K10: V27000000- VORTEX -HVLP | L10: N/A- Not applicable | M10: N/A- No Gasket | N10: 0033 | R10: M955
A11: V2700006- VORTEX - MISCELLANEOUS | B11: PY64955M01 | C11: P09550000VXHHBB | H11: D955/ 3/4 NPTMx1/4 NPTF HX HEAD BRASS BUSH PLAIN | I11: 20- Released | J11: P- Parts/Pipe/Tube | K11: V27000000- VORTEX -HVLP | L11: N/A- Not applicable | M11: N/A- No Gasket | N11: 0026 | R11: M955
A12: V2700000- VORTEX | B12: P014951P23 | C12: P09510014VXSNZN | H12: M951/ 1 1/2 NPTx4 LG SCH 160 ZINC PLT NPL | I12: 20- Released | J12: P- Parts/Pipe/Tube | K12: V27000000- VORTEX -HVLP | L12: N/A- Not applicable | M12: N/A- No Gasket | N12: 0048 | O12: 0114 | R12: M951
A13: V2700006- VORTEX - MISCELLANEOUS | B13: P014951008 | C13: P09510014VXRG00 | H13: M951/ 048 RUBBER GROMMET | I13: 20- Released | J13: P- Parts/Pipe/Tube | K13: V27000000- VORTEX -HVLP | L13: N/A- Not applicable | M13: N/A- No Gasket | N13: 0048 | R13: M951
A14: V2700000- VORTEX | B14: P014951364 | C14: P09510014VXG000 | D14: 7.17 | E14: 10.22 | H14: M951/ 048 GROMMET PUSH IN PANEL HOLE | I14: 20- Released | J14: P- Parts/Pipe/Tube | K14: V27000000- VORTEX -HVLP | L14: N/A- Not applicable | M14: N/A- No Gasket | N14: 0048 | R14: M951
A15: V2700000- VORTEX | B15: P010951C01 | C15: P09510010VXSTRN | H15: P/951 1"/33MM NPT WYE STRAINER 100 MESH DOUBLE SCREEN BRASS 150 PSI | I15: 20- Released | J15: P- Parts/Pipe/Tube | K15: V27000000- VORTEX -HVLP | L15: N/A- Not applicable | M15: N/A- No Gasket | N15: 0033 | R15: M951
A16: V2700000- VORTEX | B16: P014951062 | C16: P09510010VXSMP0 | H16: M951/ 033-048 SWCH MTG PLATE F/ACT NDL VLV ASY | I16: 20- Released | J16: P- Parts/Pipe/Tube | K16: V27000000- VORTEX -HVLP | L16: N/A- Not applicable | M16: N/A- No Gasket | N16: 0033 | O16: 0048 | R16: M951
A17: V2700000- VORTEX | B17: P010951363 | C17: P09510010VXG00P | D17: 6.61 | E17: 9.42 | H17: M951/ 033 GROMMET PUSH IN PANEL HOLE | I17: 20- Released | J17: P- Parts/Pipe/Tube | K17: V27000000- VORTEX -HVLP | L17: N/A- Not applicable | M17: N/A- No Gasket | N17: 0033 | R17: M951
A18: V2700000- VORTEX | B18: P006951Z05 | C18: P09510006SGX000 | D18: 425.32 | E18: 606.17 | H18: M951/ 026 NPT 316SS SIGHT GLASS 250 PSI 316.0 75RB REFLECTOR BALL | I18: 20- Released | J18: P- Parts/Pipe/Tube | K18: V99999000- MISCELLANEOUS | L18: N/A- Not applicable | M18: N/A- No Gasket | N18: 0026 | R18: M951
A19: V2700000- VORTEX | B19: P000951TCH | C19: P09510000VXWTCH | H19: P/951 VORTEX WR HRN TOUCHSCREEN PNL W/PLUGGABLE TERM STRIP 10PIN IDL CONN INT ENCODER 25:1 GEARBOX NEMA OUTPUT FLG | I19: 20- Released | J19: P- Parts/Pipe/Tube | K19: V27000000- VORTEX -HVLP | L19: N/A- Not applicable | M19: N/A- No Gasket | R19: M951
A20: V2700000- VORTEX | B20: P000951326 | C20: P09510000VXW326 | H20: P/951 VORTEX WIRE HARNESS PANEL ZONE FE/ZN 3A CLEAR ZINC PLATED | I20: 20- Released | J20: P- Parts/Pipe/Tube | K20: V27000000- VORTEX -HVLP | L20: N/A- Not applicable | M20: N/A- No Gasket | R20: M951
A21: V2700000- VORTEX | B21: P000951312 | C21: P09510000VXT312 | H21: P/951 VORTEX CABLE TIE UL 94 V2 BLACK POLYAMIDE 6.6 | I21: 20- Released | J21: P- Parts/Pipe/Tube | K21: V27000000- VORTEX -HVLP | L21: N/A- Not applicable | M21: N/A- No Gasket | R21: M951
A22: V2700000- VORTEX | B22: P000951310 | C22: P09510000VXA310 | H22: P/951 VORTEX ADHESIVE BACK MOUNT PANDUIT ABMS-A | I22: 20- Released | J22: P- Parts/Pipe/Tube | K22: V27000000- VORTEX -HVLP | L22: N/A- Not applicable | M22: N/A- No Gasket | R22: M951
A23: V2700000- VORTEX | B23: P000951002 | C23: P09510000ARV002 | H23: P/951 MDRIVE23PLUS MOTION CNTL(MDI1PRD23C7-EQ-G1B9-F)W/PLUGGABLE TERM STRIP 10PIN IDL CONN INR ENCODER 79:1GR NEMA FLG | I23: 20- Released | J23: P- Parts/Pipe/Tube | K23: V27000000- VORTEX -HVLP | L23: N/A- Not applicable | M23: N/A- No Gasket | R23: M951
A24: V2700000- VORTEX | B24: P000951001 | C24: P09510000ARV001 | H24: P/951 COMBO MDRIVE23PLUS MOTION CNTL(MDI1PRD23B7-EQ-G1A9-F)W/PLGGABLE TERM 10PIN IDL CONN INR ENCODER 25:1GR NEMA FLG | I24: 20- Released | J24: P- Parts/Pipe/Tube | K24: V27000000- VORTEX -HVLP | L24: N/A- Not applicable | M24: N/A- No Gasket | N24: 0026 | R24: M951
A25: V2700000- VORTEX | C25: P09500010ZZB8B0 | H25: D950/1"ASTM A733 SCH80 ASTM A53 TYPE E GR B CS BLACK 6M LEN | I25: 20- Released | J25: P- Parts/Pipe/Tube | K25: V27000000- VORTEX -HVLP | L25: N/A- Not applicable | M25: N/A- No Gasket | N25: 0033 | R25: D950
A26: V2700000- VORTEX | C26: P09500010ZZB4GB | H26: D950/1"ASTM A733 SCH40 ASTM A53 TYPE E GR A CS BLACK 6M LEN | I26: 20- Released | J26: P- Parts/Pipe/Tube | K26: V27000000- VORTEX -HVLP | L26: N/A- Not applicable | M26: N/A- No Gasket | N26: 0048 | R26: D950
A27: V2700000- VORTEX | C27: P09500010ZZB4B7 | H27: D950/48 ASTM A733 SCH40 ASTM A53 TYPE E GR B CS BLACK 6M LEN | I27: 20- Released | J27: P- Parts/Pipe/Tube | K27: V27000000- VORTEX -HVLP | L27: N/A- Not applicable | M27: N/A- No Gasket | N27: 0048 | R27: D950
A28: V2700000- VORTEX | C28: P09500010ZZB4B0 | H28: D950/1"ASTM A733 SCH40 ASTM A53 TYPE E GR B CS BLACK 6M LEN | I28: 20- Released | J28: P- Parts/Pipe/Tube | K28: V27000000- VORTEX -HVLP | L28: N/A- Not applicable | M28: N/A- No Gasket | N28: 0033 | R28: D950
A29: V2700006- VORTEX - MISCELLANEOUS | B29: P010955002 | C29: P09500010ZZ0SEF | H29: D950/1 NPT FEMALE 90 STR ELL CL3000 ALLOY STL PLAIN | I29: 20- Released | J29: P- Parts/Pipe/Tube | K29: V27000000- VORTEX -HVLP | L29: N/A- Not applicable | M29: N/A- No Gasket | N29: 0033 | R29: D950
A30: V2700006- VORTEX - MISCELLANEOUS | B30: P010955004 | C30: P09500010ZZ00UF | H30: D950/ 1 NPT FEM UNION CL3000 MALLEABLE IRON PLAIN | I30: 20- Released | J30: P- Parts/Pipe/Tube | K30: V27000000- VORTEX -HVLP | L30: N/A- Not applicable | M30: N/A- No Gasket | N30: 0033 | R30: D950
A31: V2700000- VORTEX | C31: P09500010ZZ00GB | H31: D950/1" ASME B36.10M SCH40 ASTM A53 TYPE E GR A CS ZINC 6M L | I31: 20- Released | J31: P- Parts/Pipe/Tube | K31: V27000000- VORTEX -HVLP | L31: N/A- Not applicable | M31: N/A- No Gasket | N31: 0033 | R31: D950
A32: V2700000- VORTEX | C32: P09500010ZZ00G0 | H32: D950/ 1"ASTM A733 SCH40 ASTM A53 TYPE E GR A CS ZINC 6M LEN | I32: 20- Released | J32: P- Parts/Pipe/Tube | K32: V27000000- VORTEX -HVLP | L32: N/A- Not applicable | M32: N/A- No Gasket | N32: 0033 | R32: D950
A33: V2700003- VORTEX - CYLINDERS | C33: P09500006ZZXZ30 | H33: D950/3/4 NPTxCLOSE NPL ASTM A733 304SS/40S PLAIN 3C | I33: 20- Released | J33: P- Parts/Pipe/Tube | K33: V27000000- VORTEX -HVLP | L33: N/A- Not applicable | M33: N/A- No Gasket | R33: D950
A34: V2700003- VORTEX - CYLINDERS | C34: P09500006ZZXP00 | H34: D950/GA SIG WIN W/REFLECTOR 3/4 NPTM 250 PSI SS POLY BALL 3C | I34: 20- Released | J34: P- Parts/Pipe/Tube | K34: V27000000- VORTEX -HVLP | L34: N/A- Not applicable | M34: N/A- No Gasket | R34: D950
A35: V2700003- VORTEX - CYLINDERS | C35: P09500006ZZXD3F | H35: D950//STREET ELL90 3/4 NPTFxNPTM 304SS PLAIN CLASS 150 3C | I35: 20- Released | J35: P- Parts/Pipe/Tube | K35: V27000000- VORTEX -HVLP | L35: N/A- Not applicable | M35: N/A- No Gasket | R35: D950
A36: V2700003- VORTEX - CYLINDERS | C36: P09500006ZZFX30 | H36: D950/3/4 GHT FEMx NPTM SWVL HEX FEM CONN HS ADP SS304 PLN 3C | I36: 20- Released | J36: P- Parts/Pipe/Tube | K36: V27000000- VORTEX -HVLP | L36: N/A- Not applicable | M36: N/A- No Gasket | R36: D950
A37: V2700000- VORTEX | C37: P09500004ZZZ000 | H37: D950/1/2"ASTM A733 SCH40 ASTM A53 TYPE E GR B CS ZINC 6M LEN | I37: 20- Released | J37: P- Parts/Pipe/Tube | K37: V27000000- VORTEX -HVLP | L37: N/A- Not applicable | M37: N/A- No Gasket | N37: 0021 | R37: D950
A38: V2700003- VORTEX - CYLINDERS | C38: P09500004ZZXSE0 | H38: D950/1/2 NPTF STR ELL90 304SS ASME B16.3 CLASS 150 PLAIN 3C | I38: 20- Released | J38: P- Parts/Pipe/Tube | K38: V27000000- VORTEX -HVLP | L38: N/A- Not applicable | M38: N/A- No Gasket | R38: D950
A39: V2700003- VORTEX - CYLINDERS | C39: P09500004ZZXBHN | H39: D950/BUSHING HEX HD 1 NPTM x 1/2 NPTF CLASS150 304SS PLAIN | I39: 20- Released | J39: P- Parts/Pipe/Tube | K39: V27000000- VORTEX -HVLP | L39: N/A- Not applicable | M39: N/A- No Gasket | R39: D950
A40: V2700003- VORTEX - CYLINDERS | C40: P09500004ZZX0LN | H40: D950/1/2 NPTx1 1/2 LONG NPL 304SS PLAIN SCH40 ASTM A733 3C | I40: 20- Released | J40: P- Parts/Pipe/Tube | K40: V27000000- VORTEX -HVLP | L40: N/A- Not applicable | M40: N/A- No Gasket | R40: D950
A41: V2700003- VORTEX - CYLINDERS | C41: P09500004ZZSX3F | H41: D950/STREET TEE 1/2 NPTFxNPTFxNPTM 304SS PLAIN 3C | I41: 20- Released | J41: P- Parts/Pipe/Tube | K41: V27000000- VORTEX -HVLP | L41: N/A- Not applicable | M41: N/A- No Gasket | R41: D950
A42: V2700006- VORTEX - MISCELLANEOUS | B42: P004950010 | C42: P09500004ZZ0WTR | D42: 598.26 | E42: 852.64 | H42: P/950 1/2 MNPTx36 SS HOSE FOR WATER TANK REGULATOR END TO END LENGTH 304SS | I42: 20- Released | J42: P- Parts/Pipe/Tube | K42: V27000000- VORTEX -HVLP | L42: N/A- Not applicable | M42: N/A- No Gasket | P42: XVV | Q42: TANK | R42: D950
A43: V2700003- VORTEX - CYLINDERS | C43: P0950000410X0LN | H43: D950/1/2 NPTx10 LONG NIPPLE 304SS PLAIN ASTM A733 SCH40 3C | I43: 20- Released | J43: P- Parts/Pipe/Tube | K43: V27000000- VORTEX -HVLP | L43: N/A- Not applicable | M43: N/A- No Gasket | R43: D950
A44: V2700004- VORTEX - WATER SUPPLY | B44: P002745X03 | C44: P09500002ZZX900 | D44: 1080.98 | E44: 1540.61 | H44: D950/1/4 MNPTx3 FT SS BRAID 304SS GA HOSE ASY | I44: 20- Released | J44: P- Parts/Pipe/Tube | K44: V14745000- FIREPAC DEVICE KIT | L44: N/A- Not applicable | M44: N/A- No Gasket | R44: D950
A45: V2700003- VORTEX - CYLINDERS | C45: P09500002ZZSX3F | H45: D950/STREET TEE 1/4 NPTFxNPTFxNPTM 304SS PLAIN 3C | I45: 20- Released | J45: P- Parts/Pipe/Tube | K45: V27000000- VORTEX -HVLP | L45: N/A- Not applicable | M45: N/A- No Gasket | R45: D950
A46: V2700006- VORTEX - MISCELLANEOUS | B46: P000950PAL | C46: P09500000RPPPAL | D46: 14.76 | E46: 21.04 | H46: P/950 VORTEX REPLACEMENT PAL NUT FOR PRIMARY SOLENOID RELEASE ASSEMBLY | I46: 20- Released | J46: P- Parts/Pipe/Tube | K46: V27000000- VORTEX -HVLP | L46: N/A- Not applicable | M46: N/A- No Gasket | P46: XVV | Q46: SP | R46: D950
A47: V2700002- VORTEX - PANELS | C47: P0950000000V0HS | H47: P950/951 SCR #6-32x3/8 BUTTON HD CAP HEX SOC ASME B18.3 F835 ALY STL | I47: 20- Released | J47: P- Parts/Pipe/Tube | K47: V27000000- VORTEX -HVLP | L47: N/A- Not applicable | M47: N/A- No Gasket | R47: D951
A48: V2700006- VORTEX - MISCELLANEOUS | C48: P0950000000PT00 | D48: 183.56 | E48: 261.61 | H48: D950/100L WATER TANK PLEXIGLASS TUBE | I48: 20- Released | J48: P- Parts/Pipe/Tube | K48: V27000000- VORTEX -HVLP | L48: N/A- Not applicable | M48: N/A- No Gasket | R48: D950
A49: V2700006- VORTEX - MISCELLANEOUS | B49: P000950018 | C49: P0950000000CW00 | D49: 8.82 | E49: 12.57 | H49: D950/ COPPER WASHER VORTEX BLEED VLV | I49: 20- Released | J49: P- Parts/Pipe/Tube | K49: V27000000- VORTEX -HVLP | L49: N/A- Not applicable | M49: N/A- No Gasket | P49: XVV | Q49: SP | R49: D950
A50: V2700002- VORTEX - PANELS | C50: P09500000000W60 | H50: P950/951 WASHER #6 NOMINAL PLIAN .156 X .375 X .049 ASME B18.21.1 PLT | I50: 20- Released | J50: P- Parts/Pipe/Tube | K50: V27000000- VORTEX -HVLP | L50: N/A- Not applicable | M50: N/A- No Gasket | R50: D951
A51: V2700003- VORTEX - CYLINDERS | B51: P000950037 | C51: P09500000000URA | H51: D950/ STEM SEAT REFILL ADAPTER ASY | I51: 20- Released | J51: P- Parts/Pipe/Tube | K51: V27100000- VORTEX 500 | L51: N/A- Not applicable | M51: N/A- No Gasket | R51: D950
A52: V2700003- VORTEX - CYLINDERS | B52: P002950002 | C52: P09500000000SNT | H52: D950/ SEAL NUT THD ADP ASY F/CGA 580 CON PT | I52: 20- Released | J52: P- Parts/Pipe/Tube | K52: V27000000- VORTEX -HVLP | L52: N/A- Not applicable | M52: N/A- No Gasket | R52: D950
A53: V2700003- VORTEX - CYLINDERS | C53: P09500000000BNM | H53: D950/BASE NUT F/BS341 No.3, G 5/8 THREAD PER BS2779 MALE ADP | I53: 20- Released | J53: P- Parts/Pipe/Tube | K53: V27000000- VORTEX -HVLP | L53: N/A- Not applicable | M53: N/A- No Gasket | R53: D950
A54: V2700000- VORTEX | C54: P00000000VXT000 | D54: 2123.92 | E54: 3027.01 | H54: VORTEX TROLLEY FOR 80LT GAS CYLINDER | I54: 20- Released | J54: P- Parts/Pipe/Tube | K54: V27000000- VORTEX -HVLP | L54: N/A- Not applicable | M54: N/A- No Gasket | R54: MISC
A55: V2700006- VORTEX - MISCELLANEOUS | B55: K00095315X | C55: K09530006VXWCX9 | D55: 1267.59 | E55: 1806.57 | H55: K/953 KIT WATER FLOW CARTRIDGE STAINLESS STEEL 1.59 GPM 3/4" NPT FOR VORTEX | I55: 20- Released | J55: K- Kits, Koils, Repair Kits, Pump Drop | K55: V27000000- VORTEX -HVLP | L55: N/A- Not applicable | M55: N/A- No Gasket | N55: 0073 | P55: XVV | Q55: WFK | R55: MISC
A56: V2700006- VORTEX - MISCELLANEOUS | B56: K000953X23 | C56: K09530006VXWCX3 | D56: 1267.59 | E56: 1806.57 | H56: K/953 KIT WATER FLOW CARTRIDGE STAINLESS STEEL 4.23 GPM 3/4" NPT FOR VORTEX | I56: 20- Released | J56: K- Kits, Koils, Repair Kits, Pump Drop | K56: V27000000- VORTEX -HVLP | L56: N/A- Not applicable | M56: N/A- No Gasket | N56: 0073 | P56: XVV | Q56: WFK | R56: MISC
A57: V2700006- VORTEX - MISCELLANEOUS | B57: K000953X11 | C57: K09530006VXWCX1 | D57: 1267.59 | E57: 1806.57 | H57: K/953 KIT WATER FLOW CARTRIDGE STAINLESS STEEL 2.11 GPM 3/4" NPT FOR VORTEX | I57: 20- Released | J57: K- Kits, Koils, Repair Kits, Pump Drop | K57: V27000000- VORTEX -HVLP | L57: N/A- Not applicable | M57: N/A- No Gasket | N57: 0073 | P57: XVV | Q57: WFK | R57: MISC
A58: V2700006- VORTEX - MISCELLANEOUS | B58: K000953153 | C58: K09530006VXWCB9 | D58: 979.69 | E58: 1396.25 | H58: K/953 KIT WATER FLOW CARTRIDGE BRASS 1.59 GPM 3/4" NPT FOR VORTEX | I58: 20- Released | J58: K- Kits, Koils, Repair Kits, Pump Drop | K58: V27000000- VORTEX -HVLP | L58: N/A- Not applicable | M58: N/A- No Gasket | N58: 0073 | P58: XVV | Q58: WFK | R58: MISC
A59: V2700006- VORTEX - MISCELLANEOUS | B59: K000953423 | C59: K09530006VXWCB3 | D59: 979.69 | E59: 1396.25 | H59: K/953 KIT WATER FLOW CARTRIDGE BRASS 4.23 GPM 3/4" NPT FOR VORTEX | I59: 20- Released | J59: K- Kits, Koils, Repair Kits, Pump Drop | K59: V27000000- VORTEX -HVLP | L59: N/A- Not applicable | M59: N/A- No Gasket | N59: 0073 | P59: XVV | Q59: WFK | R59: MISC
A60: V2700006- VORTEX - MISCELLANEOUS | B60: K000953211 | C60: K09530006VXWCB1 | D60: 979.69 | E60: 1396.25 | H60: K/953 KIT WATER FLOW CARTRIDGE BRASS 2.11 GPM 3/4" NPT FOR VORTEX | I60: 20- Released | J60: K- Kits, Koils, Repair Kits, Pump Drop | K60: V27000000- VORTEX -HVLP | L60: N/A- Not applicable | M60: N/A- No Gasket | N60: 0073 | P60: XVV | Q60: WFK | R60: MISC
A61: V2700006- VORTEX - MISCELLANEOUS | B61: K090950055 | C61: K09500090VXCRST | D61: 3799.1 | E61: 5414.48 | H61: K/950 VORTEX CYLINDER RESTRAINT KIT FOR 9-12 CYLINDERS BRONZE BODY | I61: 20- Released | J61: K- Kits, Koils, Repair Kits, Pump Drop | K61: V27100000- VORTEX 500 | L61: N/A- Not applicable | M61: N/A- No Gasket | P61: XVV | Q61: CRK | R61: K950
A62: V2700006- VORTEX - MISCELLANEOUS | B62: K050950055 | C62: K09500050VXCRST | D62: 2583.24 | E62: 3681.63 | H62: K/950 VORTEX CYLINDER RESTRAINT KIT FOR 5-8 CYLINDERS BRONZE BODY | I62: 20- Released | J62: K- Kits, Koils, Repair Kits, Pump Drop | K62: V27100000- VORTEX 500 | L62: N/A- Not applicable | M62: N/A- No Gasket | P62: XVV | Q62: CRK | R62: K950
A63: V2700006- VORTEX - MISCELLANEOUS | C63: K09500024VX8000 | H63: K/950 VORTEX SYSTEM WITH 80L NITROGEN CYLINDERS | I63: 20- Released | J63: K- Kits, Koils, Repair Kits, Pump Drop | K63: V27000000- VORTEX -HVLP | L63: N/A- Not applicable | M63: N/A- No Gasket | R63: K950
A64: V2700006- VORTEX - MISCELLANEOUS | B64: K010950055 | C64: K09500010VXCRST | D64: 1423.29 | E64: 2028.47 | H64: K/950 VORTEX CYLINDER RESTRAINT KIT FOR 1-4 CYLINDERS BRONZE BODY | I64: 20- Released | J64: K- Kits, Koils, Repair Kits, Pump Drop | K64: V27100000- VORTEX 500 | L64: N/A- Not applicable | M64: N/A- No Gasket | P64: XVV | Q64: CRK | R64: K950
A65: V2700004- VORTEX - WATER SUPPLY | B65: K000950WTR | C65: K09500000VXWTRR | D65: 319.77 | E65: 455.74 | H65: K/950 KIT WATER TANK REGULATOR TAMPER RESISTANT FOR VORTEX | I65: 20- Released | J65: K- Kits, Koils, Repair Kits, Pump Drop | K65: V27000000- VORTEX -HVLP | L65: N/A- Not applicable | M65: N/A- No Gasket | P65: XVV | Q65: TANK | R65: K950
A66: V2700006- VORTEX - MISCELLANEOUS | B66: P000950001 | C66: K09500000VXRCCW | D66: 4.41 | E66: 6.29 | H66: K/950 REPLACEMENT CRUSHED COPPER WASHER E1235R F/VORTEX PRI/SEC GAUGE | I66: 20- Released | J66: K- Kits, Koils, Repair Kits, Pump Drop | K66: V27000000- VORTEX -HVLP | L66: N/A- Not applicable | M66: N/A- No Gasket | P66: XVV | Q66: SP | R66: K950
A67: V2700006- VORTEX - MISCELLANEOUS | B67: K000950KIT | C67: K09500000VXPK00 | D67: 61.18 | E67: 87.19 | H67: K/950 REPAIR KIT F/PRIMARY PILOT/SECOND KIT IN PLACE KIT | I67: 20- Released | J67: K- Kits, Koils, Repair Kits, Pump Drop | K67: V27000000- VORTEX -HVLP | L67: N/A- Not applicable | M67: N/A- No Gasket | P67: XVV | Q67: SP | R67: K950
A68: V2700004- VORTEX - WATER SUPPLY | B68: K100950149 | C68: K0950000000WTTT | D68: 3708.73 | E68: 5285.68 | H68: K/950 10 GAL TO 80 GAL WATER TANK TRIM (-01) | I68: 20- Released | J68: K- Kits, Koils, Repair Kits, Pump Drop | K68: V27000000- VORTEX -HVLP | L68: N/A- Not applicable | M68: N/A- No Gasket | R68: K950
A69: V2700004- VORTEX - WATER SUPPLY | B69: K120950139 | C69: K0950000000WTT1 | D69: 3823.38 | E69: 5449.08 | H69: K/950 120 GAL AND UP WATER TANK TRIM(-02) | I69: 20- Released | J69: K- Kits, Koils, Repair Kits, Pump Drop | K69: V27000000- VORTEX -HVLP | L69: N/A- Not applicable | M69: N/A- No Gasket | R69: K950
A70: V2700005- VORTEX - VORTEX 500 | C70: E09550000VX82FR | H70: D955/ VORTEX 80L 200BAR RAL9005 25E TPED -EU USE - FILLED | I70: 80- Not carrd | J70: E- Engineered Products | K70: V27000000- VORTEX -HVLP | L70: N/A- Not applicable | M70: N/A- No Gasket | R70: D955
A71: V2700005- VORTEX - VORTEX 500 | C71: E09550000VX82ER | H71: D955/ VORTEX 80L 200BAR RAL9005 25E TPED -EU USE - EMPTY | I71: 80- Not carrd | J71: E- Engineered Products | K71: V27000000- VORTEX -HVLP | L71: N/A- Not applicable | M71: N/A- No Gasket | R71: D955
A72: V2700001- VORTEX - EMITTERS | C72: E09530014VXPEG0 | H72: EP/953 1 1/2"/48MM VORTEX HIGH TEMPERATURE PROTECTIVE RUBBER CAP | I72: 20- Released | J72: D- Devices/Trim/Disc/Ring for VBSP | K72: V27000000- VORTEX -HVLP | L72: N/A- Not applicable | M72: N/A- No Gasket | N72: 0026 | R72: D953
A73: V2700001- VORTEX - EMITTERS | C73: E09530006VX5ETK | H73: D953/ EMITTER TRIM KIT BRASS 1/2 ORIFICE 3/4 NPT F/V1500 | I73: 20- Released | J73: E- Engineered Products | K73: V27000000- VORTEX -HVLP | L73: BRS- Brass | M73: N/A- No Gasket | N73: 0026 | R73: D953
A74: V2700001- VORTEX - EMITTERS | B74: @003953KX0 | C74: E09530003VXKX0 | H74: EP/953 3/8” VORTEX EMITTER ASSEMBLY WITH HIGH TEMP O-RINGS | I74: 20- Released | J74: E- Engineered Products | K74: V27000000- VORTEX -HVLP | L74: SS- Stainless Steel | M74: N/A- No Gasket | R74: D953
A75: V2700005- VORTEX - VORTEX 500 | C75: E09510000VX8230 | H75: D951/ VORTEX 2 80L CYLINDER W/30GALLON WATER TANK PRE-BUILT | I75: 20- Released | J75: E- Engineered Products | K75: V27000000- VORTEX -HVLP | L75: N/A- Not applicable | M75: N/A- No Gasket | R75: D951
A76: V2700005- VORTEX - VORTEX 500 | C76: E09510000VX58PF | H76: D951/ VORTEX 1500 FRAM PRE-BUILT 80L | I76: 20- Released | J76: E- Engineered Products | K76: V27000000- VORTEX -HVLP | L76: N/A- Not applicable | M76: N/A- No Gasket | R76: D951
A77: V2700004- VORTEX - WATER SUPPLY | C77: E09500000VXBGST | H77: D950/BULK GAS SERVICE TUBE (4 TUBE ASY) | I77: 10- Prel. item | J77: E- Engineered Products | K77: V27000000- VORTEX -HVLP | L77: N/A- Not applicable | M77: N/A- No Gasket | R77: D950
A78: V2700003- VORTEX - CYLINDERS | C78: D950/1/2 NPTX10 | H78: D950/1/2 NPTF STR ELL90 304SS ASME B16.3 CLASS 150 PLAIN 3C | I78: 90- Not stock | J78: D- Devices/Trim/Disc/Ring for VBSP | K78: V27000000- VORTEX -HVLP | L78: N/A- Not applicable | M78: N/A- No Gasket | R78: D950
A79: V2700005- VORTEX - VORTEX 500 | C79: D09550800VX00PF | H79: D/955 PREBUILT FRAME ASY F/80L VORTEX 500 CCCF | I79: 20- Released | J79: D- Devices/Trim/Disc/Ring for VBSP | K79: V27100000- VORTEX 500 | L79: N/A- Not applicable | M79: N/A- No Gasket | N79: 0080 | R79: D955
A80: V2700006- VORTEX - MISCELLANEOUS | B80: P480955228 | C80: D09550480VXJICX | D80: 775.39 | E80: 1105.09 | H80: M955/ 1220/48" SS JIC HOSE ASSEMBLY | I80: 20- Released | J80: D- Devices/Trim/Disc/Ring for VBSP | K80: V27000000- VORTEX -HVLP | L80: SS- Stainless Steel | M80: N/A- No Gasket | N80: 1220 | P80: XVV | Q80: COMP | R80: M955
A81: V2700006- VORTEX - MISCELLANEOUS | B81: P360955228 | C81: D09550360VXJICX | D81: 549.67 | E81: 783.39 | H81: M955/ 914/36" SS JIC HOSE ASSEMBLY | I81: 20- Released | J81: D- Devices/Trim/Disc/Ring for VBSP | K81: V27000000- VORTEX -HVLP | L81: SS- Stainless Steel | M81: N/A- No Gasket | N81: 0914 | P81: XVV | Q81: COMP | R81: M955
A82: V2700006- VORTEX - MISCELLANEOUS | B82: P310955228 | C82: D09550310VXJICX | D82: 488.02 | E82: 695.53 | H82: M955/ 790/31" SS JIC HOSE ASSEMBLY | I82: 20- Released | J82: D- Devices/Trim/Disc/Ring for VBSP | K82: V27000000- VORTEX -HVLP | L82: SS- Stainless Steel | M82: N/A- No Gasket | N82: 0790 | P82: XVV | Q82: COMP | R82: M955
A83: V2700006- VORTEX - MISCELLANEOUS | B83: P000955307 | C83: D09550080VXSIWA | H83: D/955 8x11 SCHEMATIC"TERNAL WIRING PANEL SELF ADHESIVE | I83: 20- Released | J83: D- Devices/Trim/Disc/Ring for VBSP | K83: V27000000- VORTEX -HVLP | L83: N/A- Not applicable | M83: N/A- No Gasket | N83: 0000 | R83: D955
A84: V2700006- VORTEX - MISCELLANEOUS | B84: P000955309 | C84: D09550080VXSFCA | H84: D/955 8x11 SCHEMATIC FIELD CONN WIRING PANEL SELF ADHESIVE | I84: 20- Released | J84: D- Devices/Trim/Disc/Ring for VBSP | K84: V27000000- VORTEX -HVLP | L84: N/A- Not applicable | M84: N/A- No Gasket | N84: 0000 | R84: D955
A85: V2700006- VORTEX - MISCELLANEOUS | B85: P000955A29 | C85: D09550080VX8DH0 | D85: 174.19 | E85: 248.26 | H85: D955/DISCHARGE HOSE ASY 80L 1/2 BSPP X 3/4 BSPP ISOMATIC | I85: 20- Released | J85: D- Devices/Trim/Disc/Ring for VBSP | K85: V27000000- VORTEX -HVLP | L85: N/A- Not applicable | M85: N/A- No Gasket | P85: XVV | Q85: SP | R85: D955
A86: V2700005- VORTEX - VORTEX 500 | C86: D09550080000030 | H86: D955/ VORTEX 2 80L CYLINDER ASY W/ENCLOSURE W/O CYL OR PILOT | I86: 90- Not stock | J86: D- Devices/Trim/Disc/Ring for VBSP | K86: V27100000- VORTEX 500 | L86: N/A- Not applicable | M86: N/A- No Gasket | R86: D955
A87: V2700005- VORTEX - VORTEX 500 | B87: S490VPPC01 | C87: D09550049VX04WN | H87: D/955 1 49L CYL ASY W/ENCLOSURE W/O CYLINDER | I87: 90- Not stock | J87: D- Devices/Trim/Disc/Ring for VBSP | K87: V27000000- VORTEX -HVLP | L87: N/A- Not applicable | M87: N/A- No Gasket | R87: D955
A88: V2700005- VORTEX - VORTEX 500 | C88: D09550049000003 | H88: D955/ VORTEX 955 1 49L CYLINDER ASY W/O ENCLOSURE | I88: 90- Not stock | J88: D- Devices/Trim/Disc/Ring for VBSP | K88: V27000000- VORTEX -HVLP | L88: N/A- Not applicable | M88: N/A- No Gasket | R88: D955
A89: V2700005- VORTEX - VORTEX 500 | B89: P000955004 | C89: D09550040VX90C0 | H89: D955/ 4x80 CABINET F/V500 | I89: 20- Released | J89: D- Devices/Trim/Disc/Ring for VBSP | K89: V27000000- VORTEX -HVLP | L89: N/A- Not applicable | M89: N/A- No Gasket | R89: D955
A90: V2700005- VORTEX - VORTEX 500 | C90: D09550040VX8ENC | H90: D/955 FOUR 80L CYLINDER ASSEMBLY WITH ENCLOSURE WITHOUT CYLINDER | I90: 90- Not stock | J90: D- Devices/Trim/Disc/Ring for VBSP | K90: V27100000- VORTEX 500 | L90: N/A- Not applicable | M90: N/A- No Gasket | N90: 0080 | R90: D955
A91: V2700005- VORTEX - VORTEX 500 | B91: S800955004 | C91: D09550040VX8CWE | D91: 106150.15 | E91: 151285.19 | H91: D955/ VORTEX 4 80L CYLINDER ASY WITHOUT ENCLOSURE | I91: 20- Released | J91: D- Devices/Trim/Disc/Ring for VBSP | K91: V27100000- VORTEX 500 | L91: N/A- Not applicable | M91: N/A- No Gasket | R91: D955
A92: V2700005- VORTEX - VORTEX 500 | C92: D09550040VX8CPF | H92: D/955 FOUR CYLINDER 80L VORTEX 500 PRE-BUILT CCCF | I92: 20- Released | J92: D- Devices/Trim/Disc/Ring for VBSP | K92: V27100000- VORTEX 500 | L92: N/A- Not applicable | M92: N/A- No Gasket | N92: 0080 | R92: D955
A93: V2700005- VORTEX - VORTEX 500 | C93: D09550040VX8CEE | D93: 102368.12 | E93: 145895.04 | H93: D955/ VORTEX 4 80L CYLINDER ASY W/ENCLOSURE F/EUROPE ONLY | I93: 90- Not stock | J93: D- Devices/Trim/Disc/Ring for VBSP | K93: V27000000- VORTEX -HVLP | L93: N/A- Not applicable | M93: N/A- No Gasket | R93: D955
A94: V2700005- VORTEX - VORTEX 500 | B94: S8009550E4 | C94: D09550040VX8CE0 | D94: 28229.97 | E94: 40233.35 | H94: D955/ VORTEX 4 80L CYLINDER ASY F/EUROPE ONLY | I94: 20- Released | J94: D- Devices/Trim/Disc/Ring for VBSP | K94: V27100000- VORTEX 500 | L94: N/A- Not applicable | M94: N/A- No Gasket | R94: D955
A95: V2700005- VORTEX - VORTEX 500 | B95: S800955C04 | C95: D09550040VX8C0E | D95: 127528.25 | E95: 181753.26 | H95: D955/ VORTEX 4 80L CYLINDER ASY W/ENCLOSURE | I95: 90- Not stock | J95: D- Devices/Trim/Disc/Ring for VBSP | K95: V27100000- VORTEX 500 | L95: N/A- Not applicable | M95: N/A- No Gasket | R95: D955
A96: V2700005- VORTEX - VORTEX 500 | B96: S490955004 | C96: D09550040VX4CWE | H96: D955/ VORTEX 4 49L CYLINDER ASY W/O ENCLOSURE | I96: 20- Released | J96: D- Devices/Trim/Disc/Ring for VBSP | K96: V27000000- VORTEX -HVLP | L96: N/A- Not applicable | M96: N/A- No Gasket | R96: D955
A97: V2700005- VORTEX - VORTEX 500 | C97: D09550040VX40C0 | H97: D/955 FOUR 49L CYL ASY WITH CABINENT WITHOUT CYLINDER | I97: 90- Not stock | J97: D- Devices/Trim/Disc/Ring for VBSP | K97: V27100000- VORTEX 500 | L97: N/A- Not applicable | M97: N/A- No Gasket | R97: D955
A98: V2700006- VORTEX - MISCELLANEOUS | C98: D09550030VXWT33 | H98: D/955 WATER TANK WITH TRIM ASSEMBLY 30L 3C | I98: 20- Released | J98: D- Devices/Trim/Disc/Ring for VBSP | K98: V27100000- VORTEX 500 | L98: N/A- Not applicable | M98: N/A- No Gasket | N98: 0030 | R98: D955
A99: V2700005- VORTEX - VORTEX 500 | C99: D09550030VX8ENC | H99: D/955 THREE 80L CYL ASY W/ENCLOSURE W/O CYLINDER | I99: 90- Not stock | J99: D- Devices/Trim/Disc/Ring for VBSP | K99: V27100000- VORTEX 500 | L99: N/A- Not applicable | M99: N/A- No Gasket | N99: 0080 | R99: D955
A100: V2700005- VORTEX - VORTEX 500 | B100: S800955003 | C100: D09550030VX8CWE | D100: 92654.2 | E100: 132050.77 | H100: D955/ VORTEX 3 80L CYLINDER ASY W/O ENCLOSURE | I100: 20- Released | J100: D- Devices/Trim/Disc/Ring for VBSP | K100: V27100000- VORTEX 500 | L100: N/A- Not applicable | M100: N/A- No Gasket | R100: D955
...
